Workbook
Name asmClasses: Miscellaneous!$F$25:$G$27
Name asmCosts: Miscellaneous!$AG$29:$AK$31
Name asmSupplier: 'Car Purchase'!$O$33:$P$35
Name bronzePayments: 'Costs (2)'!$L$14:$M$21
Name bronzePayments: Costs!$L$14:$M$21
Name classIndexes: Miscellaneous!$J$4:$K$22
Name driverCosts: 'Costs (2)'!$L$5:$M$7
Name driverCosts: Costs!$L$5:$M$7
Name euemClasses: Miscellaneous!$F$15:$G$17
Name euemCosts: Miscellaneous!$AG$21:$AK$23
Name euemSupplier: 'Car Purchase'!$O$19:$P$21
Name gemClasses: Miscellaneous!$F$5:$G$8
Name gemCosts: Miscellaneous!$AG$5:$AK$8
Name gemSupplier: 'Car Purchase'!$O$7:$P$10
Name modelData: 'Costs (2)'!$B$5:$I$46
Name modelData: Costs!$B$5:$I$41
Name nasccClasses: Miscellaneous!$F$10:$G$13
Name nasccCosts: Miscellaneous!$AG$9:$AK$12
Name nasccEcCosts: Miscellaneous!$AG$17:$AK$20
Name nasccScCosts: Miscellaneous!$AG$13:$AK$16
Name nasccSupplier: 'Car Purchase'!$O$13:$P$16
Name oneOffs: Miscellaneous!$AN$5:$AP$14
Name purchasedCars: 'Car Purchase'!$B$5:$D$49
Name seriesClasses: Miscellaneous!$B$5:$C$13
Name seriesCodeClasses: Miscellaneous!$B$17:$C$23
Name setupCostsAero: Miscellaneous!$AW$9:$AX$11
Name setupCostsChassis: Miscellaneous!$AW$24:$AX$26
Name setupCostsFrontSusp: Miscellaneous!$AW$14:$AX$16
Name setupCostsGeneral: Miscellaneous!$AW$4:$AX$6
Name setupCostsRearSusp: Miscellaneous!$AW$19:$AX$21
Name setupCostsReliability: Miscellaneous!$AW$34:$AX$38
Name setupCostsTyres: Miscellaneous!$AW$29:$AX$31
Name t_asmGT3: Miscellaneous!$R$47:$S$47
Name t_asmGT4: Miscellaneous!$R$49:$S$49
Name t_asmLMP3: Miscellaneous!$R$45:$S$45
Name t_euemLMGTE: Miscellaneous!$R$31:$S$32
Name t_euemLMP2: Miscellaneous!$R$26:$S$27
Name t_euemLMP3: Miscellaneous!$R$29:$S$29
Name t_gemLMGTE: Miscellaneous!$R$11:$S$12
Name t_gemLMP1: Miscellaneous!$R$5:$S$6
Name t_gemLMP2: Miscellaneous!$R$8:$S$9
Name t_nasccDPi: Miscellaneous!$R$14:$S$15
Name t_nasccGTD: Miscellaneous!$R$23:$S$24
Name t_nasccGTLM: Miscellaneous!$R$20:$S$21
Name t_nasccLMP2: Miscellaneous!$R$17:$S$18
Name t_wgtmGT3A: Miscellaneous!$R$41:$S$41
Name t_wgtmGT3P: Miscellaneous!$R$38:$S$39
Name t_wgtmGT4: Miscellaneous!$R$43:$S$43
Name t_wgtssGT3: Miscellaneous!$R$34:$S$34
Name t_wgtssGT4: Miscellaneous!$R$36:$S$36
Name wgtmClasses: Miscellaneous!$F$22:$G$23
Name wgtmCosts: Miscellaneous!$AG$26:$AK$28
Name wgtmSupplier: 'Car Purchase'!$O$28:$P$30
Name wgtssClasses: Miscellaneous!$F$19:$G$20
Name wgtssCosts: Miscellaneous!$AG$24:$AK$25
Name wgtssSupplier: 'Car Purchase'!$O$24:$P$25

Sheet Costs (2)
B2: Team Creator V10 - 2018 | L2: Team Creator V10 - 2018 | P2: Team Creator V10 - 2018 | U2: Team Creator V10 - 2018
B3: Model Name | C3: Platform | D3: Cost ($M) | E3: Spare Chassis ($M) | F3: Spare Engine ($M) | G3: Spares Package ($M) | H3: Maintenance Cost ($M) | I3: Running Cost ($M) | L3: Driver Costs | P3: Tyre Supplier Costs | U3: Series Data
L4: Rank | M4: Cost | P4: Global Endurance Masters | U4: Series Name | V4: Classes | W4: Races | Z4: Race Times (Hrs) | AC4: Entry Cost ($M) | AF4: One Off ($M)
B5: Audi R18 | C5: LMP1-H | D5: 4.8 | E5: 0.85 | F5: 1.15 | G5: 1.1 | H5: 1.75 | I5: 0.375 | L5: Platinum | M5: 0.015 | P5: Class | Q5: Tyre Supplier | R5: Cost Per Race ($M) | U5: Global Endurance Masters | V5: LMP1 | W5: 8 | Z5: 72 | AC5: 2.5 | AF5: 0.35
B6: Porsche 919 Hybrid | C6: LMP1-H | D6: 4.85 | E6: 0.85 | F6: 1.25 | G6: 1.1 | H6: 0.75 | I6: 0.375 | L6: Gold | M6: 0.01 | P6: LMP1 | Q6: Michelin | R6: 0.03 | V6: LMP2 | W6: 8 | Z6: 72 | AC6: 1 | AF6: 0.2
B7: Toyota TS050 Hybrid | C7: LMP1-H | D7: 4.8 | E7: 0.85 | F7: 1.1 | G7: 1 | H7: 0.7 | I7: 0.35 | L7: Silver | M7: 0.005 | P7: LMP2 | Q7: Dunlop | R7: 0.008 | V7: LMGTE PRO | W7: 8 | Z7: 72 | AC7: 2 | AF7: 0.3
B8: ENSO CLM P1/01 | C8: LMP1-L | D8: 2.3 | E8: 0.55 | F8: 0.45 | G8: 0.5 | H8: 0.4 | I8: 0.09 | L8: Bronze | M8: 0 | Q8: Michelin | R8: 0.008 | V8: LMGTE AM | W8: 8 | Z8: 72 | AC8: 1 | AF8: 0.2
B9: Cadillac DPi-V.R | C9: DPi | D9: 1.5 | E9: 0.25 | F9: 0.5 | G9: 0.5 | H9: 0.3 | I9: 0.035 | P9: LMGTE (PRO + AM) | Q9: Dunlop | R9: 0.012 | U9: North American Sportscar Championship | V9: DPi | W9: 10 | X9: 5 | Y9: 5 | Z9: 72 | AA9: 14 | AB9: 58 | AC9: 2 | AD9: 1 | AE9: 1 | AF9: 0.2
B10: Mazda RT24-P | C10: DPi | D10: 1.5 | E10: 0.25 | F10: 0.5 | G10: 0.5 | H10: 0.3 | I10: 0.035 | Q10: Michelin | R10: 0.012 | V10: LMP2 | W10: 9 | X10: 4 | Y10: 5 | Z10: 70 | AA10: 12 | AB10: 58 | AC10: 1.25 | AD10: 0.6 | AE10: 0.75 | AF10: 0.1
B11: Nissan Onroak DPi | C11: DPi | D11: 1.5 | E11: 0.25 | F11: 0.5 | G11: 0.5 | H11: 0.3 | I11: 0.035 | L11: Team Creator V10 - 2018 | P11: NASCC | V11: GTLM | W11: 11 | X11: 6 | Y11: 5 | Z11: 76 | AA11: 18 | AB11: 58 | AC11: 2 | AD11: 1 | AE11: 1 | AF11: 0.2
B12: Dallara P217 | C12: LMP2 | D12: 0.45 | E12: 0.175 | F12: 0.35 | G12: 0.35 | H12: 0.085 | I12: 0.0125 | L12: Bronze Payments | P12: Class | Q12: Tyre Supplier | R12: Cost Per Race ($M) | V12: GTD | W12: 11 | X12: 6 | Y12: 5 | Z12: 75 | AA12: 17 | AB12: 58 | AC12: 1.25 | AD12: 0.6 | AE12: 0.75 | AF12: 0.1
B13: Ligier JS P217 | C13: LMP2 | D13: 0.45 | E13: 0.175 | F13: 0.35 | G13: 0.35 | H13: 0.085 | I13: 0.0125 | L13: Platform | M13: Funding | P13: DPi | Q13: Continental | R13: 0.025 | U13: Eurasian Endurance Masters | V13: LMP2 | W13: 9 | Z13: 36 | AC13: 0.35 | AF13: -
B14: Oreca 07 | C14: LMP2 | D14: 0.45 | E14: 0.175 | F14: 0.35 | G14: 0.35 | H14: 0.085 | I14: 0.0125 | L14: LMP1-H | M14: 0.09 | P14: LMP2 | Q14: Continental | R14: 0.008 | V14: LMP3 | W14: 9 | Z14: 36 | AC14: 0.35 | AF14: -
B15: Riley-Multimatic Mk. 30 | C15: LMP2 | D15: 0.45 | E15: 0.175 | F15: 0.35 | G15: 0.35 | H15: 0.085 | I15: 0.0125 | L15: LMP1-L | M15: 0.07 | Q15: Michelin | R15: 0.008 | V15: LMGTE | W15: 9 | Z15: 36 | AC15: 0.35 | AF15: -
B16: ADESS-03 | C16: LMP3 | D16: 0.21 | E16: 0.08 | F16: 0.02 | G16: 0.15 | H16: 0.05 | I16: 0.01 | L16: DPi | M16: 0.055 | P16: GTLM | Q16: Michelin | R16: 0.014 | U16: World GT Sprint Series | V16: GT3 | W16: 11 | Z16: 22 | AC16: 0.85 | AF16: 0.15
B17: Ginetta-Juno P3 | C17: LMP3 | D17: 0.21 | E17: 0.08 | F17: 0.02 | G17: 0.15 | H17: 0.05 | I17: 0.01 | L17: LMP2 | M17: 0.035 | P17: GTD | Q17: Continental | R17: 0.01 | V17: GT4 | W17: 11 | Z17: 22 | AC17: 0.7 | AF17: 0.15
B18: Ligier JS P3 | C18: LMP3 | D18: 0.21 | E18: 0.08 | F18: 0.02 | G18: 0.15 | H18: 0.05 | I18: 0.01 | L18: LMP3 | M18: 0.025 | P18: EuEM | U18: World GT Masters | V18: GT3-P | W18: 7 | Z18: 93 | AC18: 1.25 | AF18: 0.2
B19: Norma M30 | C19: LMP3 | D19: 0.21 | E19: 0.08 | F19: 0.02 | G19: 0.15 | H19: 0.05 | I19: 0.01 | L19: LMGTE | M19: 0.05 | P19: Class | Q19: Tyre Supplier | R19: Cost Per Race ($M) | V19: GT3-A | W19: 7 | Z19: 93 | AC19: 1 | AF19: 0.2
B20: Aston Martin Vantage GTE | C20: LMGTE | D20: 0.8 | E20: 0.25 | F20: 0.3 | G20: 0.5 | H20: 0.2 | I20: 0.025 | L20: GT3 | M20: 0.035 | P20: LMP2 | Q20: Dunlop | R20: 0.006 | V20: GT4 | W20: 7 | Z20: 93 | AC20: 1 | AF20: 0.2
B21: BMW M6 GTLM | C21: LMGTE | D21: 0.8 | E21: 0.25 | F21: 0.3 | G21: 0.5 | H21: 0.2 | I21: 0.025 | L21: GT4 | M21: 0.025 | Q21: Michelin | R21: 0.006 | U21: American Sportscar Masters | V21: LMP3 | W21: 9 | Z21: 24 | AC21: 0.2 | AF21: -
B22: Chevrolet Corvette C7.R | C22: LMGTE | D22: 0.8 | E22: 0.25 | F22: 0.3 | G22: 0.5 | H22: 0.2 | I22: 0.025 | P22: LMP3 | Q22: Michelin | R22: 0.006 | V22: GT3 | W22: 9 | Z22: 24 | AC22: 0.2 | AF22: -
B23: Ferrari 488 GTE | C23: LMGTE | D23: 0.8 | E23: 0.25 | F23: 0.3 | G23: 0.5 | H23: 0.2 | I23: 0.025 | P23: LMGTE | Q23: Dunlop | R23: 0.007 | V23: GT4 | W23: 9 | Z23: 24 | AC23: 0.2 | AF23: -
B24: Ford GT | C24: LMGTE | D24: 0.8 | E24: 0.25 | F24: 0.3 | G24: 0.5 | H24: 0.2 | I24: 0.025 | Q24: Michelin | R24: 0.007
B25: Porsche 911 RSR | C25: LMGTE | D25: 0.8 | E25: 0.25 | F25: 0.3 | G25: 0.5 | H25: 0.2 | I25: 0.025 | P25: WGTSS
B26: Acura NSX GT3 | C26: GT3 | D26: 0.6 | E26: 0.175 | F26: 0.225 | G26: 0.4 | H26: 0.125 | I26: 0.015 | P26: Class | Q26: Tyre Supplier | R26: Cost Per Race ($M)
B27: Aston Martin V12 Vantage GT3 | C27: GT3 | D27: 0.6 | E27: 0.175 | F27: 0.225 | G27: 0.4 | H27: 0.125 | I27: 0.015 | P27: GT3 | Q27: Dunlop | R27: 0.007
B28: Audi R8 LMS | C28: GT3 | D28: 0.6 | E28: 0.175 | F28: 0.225 | G28: 0.4 | H28: 0.125 | I28: 0.015 | P28: GT4 | Q28: Michelin | R28: 0.005
B29: Bentley Continental GT3 | C29: GT3 | D29: 0.6 | E29: 0.175 | F29: 0.225 | G29: 0.4 | H29: 0.125 | I29: 0.015 | P29: WGTM
B30: BMW M6 GT3 | C30: GT3 | D30: 0.6 | E30: 0.175 | F30: 0.225 | G30: 0.4 | H30: 0.125 | I30: 0.015 | P30: Class | Q30: Tyre Supplier | R30: Cost Per Race ($M)
B31: Callaway Corvette C7 GT3-R | C31: GT3 | D31: 0.6 | E31: 0.175 | F31: 0.225 | G31: 0.4 | H31: 0.125 | I31: 0.015 | P31: GT3-P | Q31: Continental | R31: 0.007
B32: Ferrari 488 GT3 | C32: GT3 | D32: 0.6 | E32: 0.175 | F32: 0.225 | G32: 0.4 | H32: 0.125 | I32: 0.015 | Q32: Dunlop | R32: 0.007
B33: Lamborghini Huracan GT3 | C33: GT3 | D33: 0.6 | E33: 0.175 | F33: 0.225 | G33: 0.4 | H33: 0.125 | I33: 0.015 | P33: GT3-A | Q33: Dunlop | R33: 0.007
B34: Lexus RC F GT3 | C34: GT3 | D34: 0.6 | E34: 0.175 | F34: 0.225 | G34: 0.4 | H34: 0.125 | I34: 0.015 | P34: GT4 | Q34: Michelin | R34: 0.005
B35: McLaren 650S GT3 | C35: GT3 | D35: 0.6 | E35: 0.175 | F35: 0.225 | G35: 0.4 | H35: 0.125 | I35: 0.015 | P35: ASM
B36: Mercedes-AMG GT3 | C36: GT3 | D36: 0.6 | E36: 0.175 | F36: 0.225 | G36: 0.4 | H36: 0.125 | I36: 0.015 | P36: Class | Q36: Tyre Supplier | R36: Cost Per Race ($M)
B37: Porsche 911 GT3 R | C37: GT3 | D37: 0.6 | E37: 0.175 | F37: 0.225 | G37: 0.4 | H37: 0.125 | I37: 0.015 | P37: LMP3 | Q37: Michelin | R37: 0.006
B38: Aston Martin V9 Vantage GT4 | C38: GT4 | D38: 0.4 | E38: 0.2 | F38: 0.175 | G38: 0.25 | H38: 0.075 | I38: 0.01 | P38: GT3 | Q38: Michelin | R38: 0.005
B39: Ekris M4 GT4 | C39: GT4 | D39: 0.4 | E39: 0.2 | F39: 0.175 | G39: 0.25 | H39: 0.075 | I39: 0.01 | P39: GT4 | Q39: Michelin | R39: 0.005
B40: Ford Mustang GT4 | C40: GT4 | D40: 0.4 | E40: 0.2 | F40: 0.175 | G40: 0.25 | H40: 0.075 | I40: 0.01
B41: Ginetta G55 GT4 | C41: GT4 | D41: 0.4 | E41: 0.2 | F41: 0.175 | G41: 0.25 | H41: 0.075 | I41: 0.01
B42: KTM X-Bow GT4 | C42: GT4 | D42: 0.4 | E42: 0.2 | F42: 0.175 | G42: 0.25 | H42: 0.075 | I42: 0.01
B43: Maserati GranTurismo MC GT4 | C43: GT4 | D43: 0.4 | E43: 0.2 | F43: 0.175 | G43: 0.25 | H43: 0.075 | I43: 0.01
B44: McLaren 570S GT4 | C44: GT4 | D44: 0.4 | E44: 0.2 | F44: 0.175 | G44: 0.25 | H44: 0.075 | I44: 0.01
B45: Nissan 370Z GT4 | C45: GT4 | D45: 0.4 | E45: 0.2 | F45: 0.175 | G45: 0.25 | H45: 0.075 | I45: 0.01
B46: Porsche Cayman GT4 Clubsport MR | C46: GT4 | D46: 0.4 | E46: 0.2 | F46: 0.175 | G46: 0.25 | H46: 0.075 | I46: 0.01

Sheet Costs
B2: Team Creator V10 - 2018 | L2: Team Creator V10 - 2018 | P2: Team Creator V10 - 2018 | U2: Team Creator V10 - 2018
B3: Model Name | C3: Platform | D3: Cost ($M) | E3: Spare Chassis ($M) | F3: Spare Engine ($M) | G3: Spares Package ($M) | H3: Maintenance Cost ($M) | I3: Running Cost ($M) | L3: Driver Costs | P3: Tyre Supplier Costs | U3: Series Data
L4: Rank | M4: Cost | P4: Global Endurance Masters | U4: Series Name | V4: Classes | W4: Races | Z4: Race Times (Hrs) | AC4: Entry Cost ($M) | AF4: One Off ($M)
B5: BR Engineering BR1 | C5: LMP1-L | D5: 1.7 | E5: 0.25 | F5: 0.45 | G5: 0.5 | I5: 0.09 | L5: Platinum | M5: 0.015 | P5: Class | Q5: Tyre Supplier | R5: Cost Per Race ($M) | U5: Global Endurance Masters | V5: LMP1 | W5: 8 | Z5: 72 | AC5: 2.5 | AF5: 0.35
B6: ENSO CLM P1/01 | C6: LMP1-L | D6: 2 | E6: 0.45 | F6: 0.45 | G6: 0.5 | H6: 0.4 | I6: 0.09 | L6: Gold | M6: 0.01 | P6: LMP1 | Q6: Dunlop | R6: 0.03 | V6: LMP2 | W6: 8 | Z6: 72 | AC6: 1 | AF6: 0.2
B7: Ginetta G60-LT-P1 | C7: LMP1-L | D7: 1.65 | E7: 0.45 | F7: 0.45 | G7: 0.5 | I7: 0.09 | L7: Silver | M7: 0.005 | Q7: Michelin | R7: 0.03 | V7: LMGTE PRO | W7: 8 | Z7: 72 | AC7: 2 | AF7: 0.3
B8: Rebellion R13 | C8: LMP1-L | D8: 1.9 | E8: 0.25 | F8: 0.45 | G8: 0.5 | I8: 0.09 | L8: Bronze | M8: 0 | P8: LMP2 | Q8: Dunlop | R8: 0.008 | V8: LMGTE AM | W8: 8 | Z8: 72 | AC8: 1 | AF8: 0.2
B9: Porsche 919 Hybrid | C9: LMP1-H | D9: 4.85 | E9: 0.75 | F9: 1.25 | G9: 1.1 | H9: 0.75 | I9: 0.375 | Q9: Michelin | R9: 0.008 | U9: North American Sportscar Championship | V9: DPi | W9: 10 | X9: 5 | Y9: 5 | Z9: 72 | AA9: 14 | AB9: 58 | AC9: 2 | AD9: 1 | AE9: 1 | AF9: 0.2
B10: Toyota TS050 - Hybrid | C10: LMP1-H | D10: 4.8 | E10: 0.75 | F10: 1.15 | G10: 1 | H10: 0.7 | I10: 0.35 | P10: LMGTE (PRO + AM) | Q10: Dunlop | R10: 0.012 | V10: LMP2 | W10: 9 | X10: 4 | Y10: 5 | Z10: 70 | AA10: 12 | AB10: 58 | AC10: 1.25 | AD10: 0.6 | AE10: 0.75 | AF10: 0.1
B11: Acura ARX-05 | C11: DPi | D11: 1.5 | E11: 0.25 | F11: 0.5 | G11: 0.5 | H11: 0.3 | I11: 0.035 | L11: Team Creator V10 - 2018 | Q11: Michelin | R11: 0.012 | V11: GTLM | W11: 11 | X11: 6 | Y11: 5 | Z11: 76 | AA11: 18 | AB11: 58 | AC11: 2 | AD11: 1 | AE11: 1 | AF11: 0.2
B12: Cadillac DPi-V.R | C12: DPi | D12: 1.5 | E12: 0.25 | F12: 0.5 | G12: 0.5 | H12: 0.3 | I12: 0.035 | L12: Bronze Payments | P12: North American Sportscar Championship | V12: GTD | W12: 11 | X12: 6 | Y12: 5 | Z12: 75 | AA12: 17 | AB12: 58 | AC12: 1.25 | AD12: 0.6 | AE12: 0.75 | AF12: 0.1
B13: Mazda RT24-P | C13: DPi | D13: 1.5 | E13: 0.25 | F13: 0.5 | G13: 0.5 | H13: 0.3 | I13: 0.035 | L13: Platform | M13: Funding | P13: Class | Q13: Tyre Supplier | R13: Cost Per Race ($M) | U13: Eurasian Endurance Masters | V13: LMP2 | W13: 9 | Z13: 36 | AC13: 0.35 | AF13: -
B14: Nissan Onroak DPi | C14: DPi | D14: 1.5 | E14: 0.25 | F14: 0.5 | G14: 0.5 | H14: 0.3 | I14: 0.035 | L14: LMP1-H | M14: 0.09 | P14: DPi | Q14: Continental | R14: 0.025 | V14: LMP3 | W14: 9 | Z14: 36 | AC14: 0.35 | AF14: -
B15: Dallara P217 | C15: LMP2 | D15: 0.45 | E15: 0.175 | F15: 0.35 | G15: 0.35 | H15: 0.085 | I15: 0.0125 | L15: LMP1-L | M15: 0.07 | Q15: Michelin | R15: 0.025 | V15: LMGTE | W15: 9 | Z15: 36 | AC15: 0.35 | AF15: -
B16: Ligier JS P217 | C16: LMP2 | D16: 0.45 | E16: 0.175 | F16: 0.35 | G16: 0.35 | H16: 0.085 | I16: 0.0125 | L16: DPi | M16: 0.055 | P16: LMP2 | Q16: Continental | R16: 0.008
B17: Oreca 07 | C17: LMP2 | D17: 0.45 | E17: 0.175 | F17: 0.35 | G17: 0.35 | H17: 0.085 | I17: 0.0125 | L17: LMP2 | M17: 0.035 | Q17: Michelin | R17: 0.008
B18: Riley-Multimatic Mk. 30 | C18: LMP2 | D18: 0.45 | E18: 0.175 | F18: 0.35 | G18: 0.35 | H18: 0.085 | I18: 0.0125 | L18: LMP3 | M18: 0.025 | P18: GTLM | Q18: Continental | R18: 0.014
B19: ADESS-03 | C19: LMP3 | D19: 0.21 | E19: 0.08 | F19: 0.02 | G19: 0.15 | H19: 0.05 | I19: 0.01 | L19: LMGTE | M19: 0.05 | Q19: Michelin | R19: 0.014
B20: Ginetta-Juno P3 | C20: LMP3 | D20: 0.21 | E20: 0.08 | F20: 0.02 | G20: 0.15 | H20: 0.05 | I20: 0.01 | L20: GT3 | M20: 0.035 | P20: GTD | Q20: Continental | R20: 0.01
B21: Ligier JS P3 | C21: LMP3 | D21: 0.21 | E21: 0.08 | F21: 0.02 | G21: 0.15 | H21: 0.05 | I21: 0.01 | L21: GT4 | M21: 0.025 | Q21: Michelin | R21: 0.01
B22: Norma M30 | C22: LMP3 | D22: 0.21 | E22: 0.08 | F22: 0.02 | G22: 0.15 | H22: 0.05 | I22: 0.01 | P22: Eurasian Endurance Masters
B23: Aston Martin Vantage GTE | C23: LMGTE | D23: 0.8 | E23: 0.25 | F23: 0.3 | G23: 0.5 | H23: 0.2 | I23: 0.025 | P23: Class | Q23: Tyre Supplier | R23: Cost Per Race ($M)
B24: BMW M8 GTE | C24: LMGTE | D24: 0.8 | E24: 0.25 | F24: 0.3 | G24: 0.5 | H24: 0.2 | I24: 0.025 | P24: LMP2 | Q24: Dunlop | R24: 0.006
B25: Chevrolet Corvette C7.R | C25: LMGTE | D25: 0.8 | E25: 0.25 | F25: 0.3 | G25: 0.5 | H25: 0.2 | I25: 0.025 | Q25: Michelin | R25: 0.006
B26: Ferrari 488 GTE Evo | C26: LMGTE | D26: 0.8 | E26: 0.25 | F26: 0.3 | G26: 0.5 | H26: 0.2 | I26: 0.025 | P26: LMP3 | Q26: Michelin | R26: 0.006
B27: Ford GT | C27: LMGTE | D27: 0.8 | E27: 0.25 | F27: 0.3 | G27: 0.5 | H27: 0.2 | I27: 0.025 | P27: LMGTE | Q27: Dunlop | R27: 0.007
B28: Porsche 911 RSR | C28: LMGTE | D28: 0.8 | E28: 0.25 | F28: 0.3 | G28: 0.5 | H28: 0.2 | I28: 0.025 | Q28: Michelin | R28: 0.007
B29: Acura NSX GT3 | C29: GT3 | D29: 0.6 | E29: 0.175 | F29: 0.225 | G29: 0.4 | H29: 0.125 | I29: 0.015
B30: Aston Martin Vantage GT3 | C30: GT3 | D30: 0.6 | E30: 0.175 | F30: 0.225 | G30: 0.4 | H30: 0.125 | I30: 0.015
B31: Audi R8 LMS | C31: GT3 | D31: 0.6 | E31: 0.175 | F31: 0.225 | G31: 0.4 | H31: 0.125 | I31: 0.015
B32: Bentley Continental GT3 | C32: GT3 | D32: 0.6 | E32: 0.175 | F32: 0.225 | G32: 0.4 | H32: 0.125 | I32: 0.015
B33: BMW M6 GT3 | C33: GT3 | D33: 0.6 | E33: 0.175 | F33: 0.225 | G33: 0.4 | H33: 0.125 | I33: 0.015
B34: Callaway Corvette C7 GT3-R | C34: GT3 | D34: 0.6 | E34: 0.175 | F34: 0.225 | G34: 0.4 | H34: 0.125 | I34: 0.015
B35: Ferrari 488 GT3 | C35: GT3 | D35: 0.6 | E35: 0.175 | F35: 0.225 | G35: 0.4 | H35: 0.125 | I35: 0.015
B36: Lamborghini Huracán GT3 | C36: GT3 | D36: 0.6 | E36: 0.175 | F36: 0.225 | G36: 0.4 | H36: 0.125 | I36: 0.015
B37: Lexus RC F GT3 | C37: GT3 | D37: 0.6 | E37: 0.175 | F37: 0.225 | G37: 0.4 | H37: 0.125 | I37: 0.015
B38: McLaren 650S GT3 | C38: GT3 | D38: 0.6 | E38: 0.175 | F38: 0.225 | G38: 0.4 | H38: 0.125 | I38: 0.015
B39: Mercedes-AMG GT3 | C39: GT3 | D39: 0.6 | E39: 0.175 | F39: 0.225 | G39: 0.4 | H39: 0.125 | I39: 0.015
B40: Nissan GT-R NISMO GT3 | C40: GT3 | D40: 0.6 | E40: 0.175 | F40: 0.225 | G40: 0.4 | H40: 0.125 | I40: 0.015
B41: Porsche 911 GT3 R | C41: GT3 | D41: 0.6 | E41: 0.175 | F41: 0.225 | G41: 0.4 | H41: 0.125 | I41: 0.015

Sheet Miscellaneous
V2: Team Creator V10 - 2018 | AF2: Team Creator V8 | AW2: Setup Bonuses - General | BA2: Team Creator V10 - 2018 | BF2: Team Creator V10 - 2018 | BK2: Team Creator V10 - 2018 | BP2: Team Creator V10 - 2018
N3: OLD | V3: Tyre Supplier Costs | AA3: Tyre Supplier Costs | AF3: Series Data | AW3: Level | AX3: Cost | BA3: Team Bonuses - General | BF3: Team Bonuses - Front Susp | BK3: Team Bonuses - Chassis | BP3: Team Bonuses - Reliability
B4: Series Name | C4: Classes | F4: GEM | J4: LMP1 | K4: 1 | N4: GEM | O4: LMP1 | R4: GEM | S4: LMP1 | V4: Global Endurance Masters | AA4: Global Endurance Masters | AF4: Series Name | AG4: Classes | AH4: Races | AI4: Race Times | AJ4: Entry Cost ($M) | AK4: One Off ($M) | AN4: Event | AO4: Series | AP4: Length | AS4: Selected Tyre Suppliers | AW4: Level 1 | AX4: 0.5 | BA4: Level | BB4: Bonus | BC4: Cost | BF4: Level | BG4: Bonus | BH4: Cost | BK4: Level | BL4: Bonus | BM4: Cost | BP4: Level | BQ4: Bonus | BR4: Cost
B5: Global Endurance Masters | C5: 1 | F5: LMP1-H | G5: LMP1 | J5: LMP2 | K5: 2 | N5: Dunlop | O5: 0.06 | R5: Dunlop | S5: 0.03 | V5: Class | W5: Tyre Supplier | X5: Cost Per Race ($M) | AA5: Class | AB5: Tyre Supplier | AC5: Cost Per Race ($M) | AF5: Global Endurance Masters | AG5: LMP1 | AH5: 8 | AI5: 72 | AJ5: 2.5 | AK5: 0.35 | AN5: 6 Hours of Spa | AO5: GEM | AP5: 6 | AS5: Global Endurance Masters | AW5: Level 2 | AX5: 0.8 | BA5: Level 1 | BB5: +1-2 | BC5: $500k | BF5: Level 1 | BG5: +1 | BH5: $200k | BK5: Level 1 | BL5: +1-2 | BM5: $300k | BP5: Level 1 | BQ5: +1 | BR5: $200k
B6: North American Sportscar Championship | C6: 2 | F6: LMP1-L | G6: LMP1 | J6: LMGTE PRO | K6: 3 | N6: Michelin | O6: 0.06 | R6: Michelin | S6: 0.03 | V6: LMP1 | W6: Dunlop | X6: 0.03 | AA6: LMP1 | AB6: Michelin | AC6: 0.06 | AG6: LMP2 | AH6: 8 | AI6: 72 | AJ6: 1 | AK6: 0.2 | AN6: 24 Heures du Mans | AO6: GEM | AP6: 24 | AS6: Class | AT6: Tyre Supplier | AW6: Level 3 | AX6: 1.5 | BA6: Level 2 | BB6: +2-3 | BC6: $800k | BF6: Level 2 | BG6: +2-3 | BH6: $450k | BK6: Level 2 | BL6: +2-3 | BM6: $500k | BP6: Level 2 | BQ6: +2 | BR6: $400k
B7: North American Sportscar Championship - SC | C7: 2.1 | F7: LMP2 | G7: LMP2 | J7: LMGTE AM | K7: 4 | N7: GEM | O7: LMP2 | R7: GEM | S7: LMP2 | W7: Michelin | X7: 0.03 | AA7: LMP2 | AB7: Dunlop | AC7: 0.01 | AG7: LMGTE PRO | AH7: 8 | AI7: 72 | AJ7: 2 | AK7: 0.3 | AN7: Rolex 24 at Daytona | AO7: NASCC | AP7: 24 | AS7: LMP1 | AW7: Setup Bonuses - Aero | BA7: Level 3 | BB7: +4-6 | BC7: $1.5m | BF7: Level 3 | BG7: +3-5 | BH7: $800k | BK7: Level 3 | BL7: +4-6 | BM7: $850k | BP7: Level 3 | BQ7: +3 | BR7: $600k
B8: North American Sportscar Championship - EC | C8: 2.2 | F8: LMGTE | G8: LMGTE PRO | J8: DPi | K8: 1 | N8: Dunlop | O8: 0.01 | R8: Dunlop | S8: 0.008 | V8: LMP2 | W8: Dunlop | X8: 0.008 | AB8: Michelin | AC8: 0.0075 | AG8: LMGTE AM | AH8: 8 | AI8: 72 | AJ8: 1 | AK8: 0.2 | AN8: 12 Hours of Sebring | AO8: NASCC | AP8: 12 | AS8: LMP2 | AW8: Level | AX8: Cost | BP8: Level 4 | BQ8: +4 | BR8: $850k
B9: Eurasian Endurance Masters | C9: 3 | F9: NASCC | J9: LMP2 | K9: 2 | N9: Michelin | O9: 0.0075 | R9: Michelin | S9: 0.008 | W9: Michelin | X9: 0.008 | AA9: LMGTE (PRO + AM) | AB9: Dunlop | AC9: 0.02 | AF9: North American Sportscar Championship | AG9: DPi | AH9: 10 | AI9: =AI13 + AI17 -> 72 | AJ9: 2 | AK9: 0.2 | AN9: Petit Le Mans | AO9: NASCC | AP9: 10 | AS9: LMGTE PRO | AW9: Level 1 | AX9: 0.3 | BP9: Level 5 | BQ9: +5 | BR9: $1.1m
B10: World GT Sprint Series | C10: 4 | F10: DPi | G10: DPi | J10: GTLM | K10: 3 | N10: GEM | O10: LMGTE | R10: GEM | S10: LMGTE | V10: LMGTE (PRO + AM) | W10: Dunlop | X10: 0.012 | AB10: Michelin | AC10: 0.02 | AG10: LMP2 | AH10: 8 | AI10: =AI14 + AI18 -> 70 | AJ10: 1.25 | AK10: 0.1 | AN10: World GT Sprint Series at Le Mans | AO10: WGTSS | AP10: 2 | AS10: LMGTE AM | AW10: Level 2 | AX10: 0.5 | BA10: Team Creator V10 - 2018 | BF10: Team Creator V10 - 2018 | BK10: Team Creator V10 - 2018
B11: World GT Masters | C11: 5 | F11: LMP2 | G11: LMP2 | J11: GTD | K11: 4 | N11: Dunlop | O11: 0.02 | R11: Dunlop | S11: 0.012 | W11: Michelin | X11: 0.012 | AA11: NASCC | AG11: GTLM | AH11: 11 | AI11: =AI15 + AI19 -> 76 | AJ11: 2 | AK11: 0.2 | AN11: Bathurst 12 Hours | AO11: WGTM | AP11: 12 | AS11: NASCC | AW11: Level 3 | AX11: 0.85 | BA11: Team Bonuses - Aero | BF11: Team Bonuses - Rear Susp | BK11: Team Bonuses - Tyres
B12: World Prototype Challenge | C12: 6 | F12: LMGTE | G12: GTLM | J12: LMP2 | K12: 1 | N12: Michelin | O12: 0.02 | R12: Michelin | S12: 0.012 | V12: North American Sportscar Championship | AA12: Class | AB12: Tyre Supplier | AC12: Cost Per Race ($M) | AG12: GTD | AH12: 11 | AI12: =AI16 + AI20 -> 75 | AJ12: 1.2 | AK12: 0.1 | AN12: 24 Hours of The Nurburgring | AO12: WGTM | AP12: 24 | AS12: Class | AT12: Tyre Supplier | AW12: Setup Bonuses - Front Susp | BA12: Level | BB12: Bonus | BC12: Cost | BF12: Level | BG12: Bonus | BH12: Cost | BK12: Level | BL12: Bonus | BM12: Cost
B13: American Sportscar Masters | C13: 7 | F13: GT3 | G13: GTD | J13: LMP3 | K13: 2 | N13: NASCC | O13: DPi | R13: NASCC | S13: DPi | V13: Class | W13: Tyre Supplier | X13: Cost Per Race ($M) | AA13: DPi | AB13: Continental | AC13: 0.045 | AF13: North American Sportscar Championship Sprint Cup | AG13: DPi | AH13: 5 | AI13: 14 | AJ13: 1 | AK13: 0.2 | AN13: 24 Hours of Spa | AO13: WGTM | AP13: 24 | AS13: DPi | AW13: Level | AX13: Cost | BA13: Level 1 | BB13: +1-2 | BC13: $300k | BF13: Level 1 | BG13: +1 | BH13: $200k | BK13: Level 1 | BL13: +1 | BM13: $350k
F14: EuEM | J14: LMGTE | K14: 3 | N14: Continental | O14: 0.045 | R14: Continental | S14: 0.025 | V14: DPi | W14: Continental | X14: 0.025 | AA14: LMP2 | AB14: Continental | AC14: 0.01 | AG14: LMP2 | AH14: 4 | AI14: 12 | AJ14: 0.6 | AK14: 0.1 | AN14: ASM 210 Minutes of CoTA | AO14: ASM | AP14: 3 | AS14: LMP2 | AW14: Level 1 | AX14: 0.2 | BA14: Level 2 | BB14: +2-3 | BC14: $500k | BF14: Level 2 | BG14: +2-3 | BH14: $450k | BK14: Level 2 | BL14: +2 | BM14: $600k
F15: LMP2 | G15: LMP2 | J15: GT3 | K15: 1 | N15: NASCC | O15: LMP2 | R15: Michelin | S15: 0.025 | W15: Michelin | X15: 0.025 | AB15: Michelin | AC15: 0.01 | AG15: GTLM | AH15: 6 | AI15: 18 | AJ15: 1 | AK15: 0.2 | AS15: GTLM | AW15: Level 2 | AX15: 0.45 | BA15: Level 3 | BB15: +4-6 | BC15: $850k | BF15: Level 3 | BG15: +3-5 | BH15: $800k | BK15: Level 3 | BL15: +3-4 | BM15: $1m
B16: Series Name | C16: Classes | F16: LMP3 | G16: LMP3 | J16: GT4 | K16: 2 | N16: Continental | O16: 0.01 | R16: NASCC | S16: LMP2 | V16: LMP2 | W16: Continental | X16: 0.008 | AA16: GTLM | AB16: Michelin | AC16: 0.025 | AG16: GTD | AH16: 6 | AI16: 17 | AJ16: 0.6 | AK16: 0.1 | AS16: GTD | AW16: Level 3 | AX16: 0.8
B17: GEM | C17: 1 | F17: LMGTE | G17: LMGTE | J17: GT3-P | K17: 1 | N17: Michelin | O17: 0.01 | R17: Continental | S17: 0.008 | W17: Michelin | X17: 0.008 | AA17: GTD | AB17: Continental | AC17: 0.015 | AF17: North American Sportscar Championship Endurance Cup | AG17: DPi | AH17: 5 | AI17: 58 | AJ17: 1 | AK17: 0.2 | AS17: EuEM | AW17: Setup Bonuses - Rear Susp
B18: NASCC | C18: 2 | F18: WGTSS | J18: GT3-A | K18: 2 | N18: NASCC | O18: GTLM | R18: Michelin | S18: 0.008 | V18: GTLM | W18: Continental | X18: 0.014 | AA18: EuEM | AG18: LMP2 | AH18: 5 | AI18: 58 | AJ18: 0.75 | AK18: 0.1 | AS18: Class | AT18: Tyre Supplier | AW18: Level | AX18: Cost
B19: EuEM | C19: 3 | F19: GT3 | G19: GT3 | J19: GT4 | K19: 3 | N19: Michelin | O19: 0.025 | R19: NASCC | S19: GTLM | W19: Michelin | X19: 0.014 | AA19: Class | AB19: Tyre Supplier | AC19: Cost Per Race ($M) | AG19: GTLM | AH19: 5 | AI19: 58 | AJ19: 1 | AK19: 0.2 | AS19: LMP2 | AW19: Level 1 | AX19: 0.2
B20: WGTSS | C20: 4 | F20: GT4 | G20: GT4 | J20: LMP3 | K20: 1 | N20: NASCC | O20: GTD | R20: Continental | S20: 0.014 | V20: GTD | W20: Continental | X20: 0.01 | AA20: LMP2 | AB20: Dunlop | AC20: 0.01 | AG20: GTD | AH20: 5 | AI20: 58 | AJ20: 0.75 | AK20: 0.1 | AS20: LMP3 | AT20: Michelin | AW20: Level 2 | AX20: 0.45
B21: WGTM | C21: 5 | F21: WGTM | J21: GT3 | K21: 2 | N21: Continental | O21: 0.015 | R21: Michelin | S21: 0.014 | W21: Michelin | X21: 0.01 | AB21: Michelin | AC21: 0.0075 | AF21: Eurasian Endurance Masters | AG21: LMP2 | AH21: 9 | AI21: 36 | AJ21: 0.35 | AK21: 0 | AS21: LMGTE | AW21: Level 3 | AX21: 0.8
B22: WPC | C22: 6 | F22: GT3 | G22: GT3-P | J22: GT4 | K22: 3 | N22: EuEM | O22: LMP2 | R22: NASCC | S22: GTD | V22: Eurasian Endurance Masters | AA22: LMP3 | AB22: Michelin | AC22: 0.01 | AG22: LMP3 | AH22: 9 | AI22: 36 | AJ22: 0.35 | AK22: 0 | AS22: WGTSS | AW22: Setup Bonuses - Chassis
B23: ASM | C23: 7 | F23: GT4 | G23: GT4 | N23: Dunlop | O23: 0.01 | R23: Michelin | S23: 0.01 | V23: Class | W23: Tyre Supplier | X23: Cost Per Race ($M) | AA23: LMGTE | AB23: Dunlop | AC23: 0.015 | AG23: LMGTE | AH23: 9 | AI23: 36 | AJ23: 0.35 | AK23: 0 | AS23: Class | AT23: Tyre Supplier | AW23: Level | AX23: Cost
F24: ASM | N24: Michelin | O24: 0.0075 | R24: Continental | S24: 0.01 | V24: LMP2 | W24: Dunlop | X24: 0.006 | AB24: Michelin | AC24: 0.015 | AF24: World GT Sprint Series | AG24: GT3 | AH24: 11 | AI24: 22 | AJ24: 0.75 | AK24: 0.15 | AS24: GT3 | AT24: Dunlop | AW24: Level 1 | AX24: 0.3
F25: LMP3 | G25: LMP3 | N25: EuEM | O25: LMP3 | R25: EuEM | S25: LMP2 | W25: Michelin | X25: 0.006 | AA25: WGTSS | AG25: GT4 | AH25: 11 | AI25: 22 | AJ25: 0.7 | AK25: 0.15 | AS25: GT4 | AT25: Michelin | AW25: Level 2 | AX25: 0.5
C26: LMP1 | F26: GT3 | G26: GT3 | N26: Michelin | O26: 0.01 | R26: Dunlop | S26: 0.006 | V26: LMP3 | W26: Michelin | X26: 0.006 | AA26: Class | AB26: Tyre Supplier | AC26: Cost Per Race ($M) | AF26: World GT Masters | AG26: GT3-P | AH26: 7 | AI26: 93 | AJ26: 1.25 | AK26: 0.2 | AS26: WGTM | AW26: Level 3 | AX26: 0.85
C27: DPi | F27: GT4 | G27: GT4 | N27: EuEM | O27: LMGTE | R27: Michelin | S27: 0.006 | V27: LMGTE | W27: Dunlop | X27: 0.007 | AA27: GT3 | AB27: Dunlop | AC27: 0.01 | AG27: GT3-A | AH27: 7 | AI27: 93 | AJ27: 1 | AK27: 0.2 | AS27: Class | AT27: Tyre Supplier | AW27: Setup Bonuses - Tyres
C28: LMP2 | N28: Dunlop | O28: 0.015 | R28: EuEM | S28: LMP3 | W28: Michelin | X28: 0.007 | AA28: GT4 | AB28: Michelin | AC28: 0.0075 | AG28: GT4 | AH28: 7 | AI28: 93 | AJ28: 1 | AK28: 0.2 | AS28: GT3-P | AW28: Level | AX28: Cost
C29: LMP3 | N29: Michelin | O29: 0.015 | R29: Michelin | S29: 0.006 | AA29: WGTM | AF29: American Sportscar Masters | AG29: LMP3 | AH29: 9 | AI29: 24 | AJ29: 0.2 | AK29: 0 | AS29: GT3-A | AT29: Dunlop | AW29: Level 1 | AX29: 0.35
C30: GTE | N30: WGTSS | O30: GT3 | R30: EuEM | S30: LMGTE | AA30: Class | AB30: Tyre Supplier | AC30: Cost Per Race ($M) | AG30: GT3 | AH30: 9 | AI30: 24 | AJ30: 0.2 | AK30: 0 | AS30: GT4 | AT30: Michelin | AW30: Level 2 | AX30: 0.6
C31: GT3 | N31: Dunlop | O31: 0.01 | R31: Dunlop | S31: 0.007 | AA31: GT3-P | AB31: Continental | AC31: 0.01 | AG31: GT4 | AH31: 9 | AI31: 24 | AJ31: 0.2 | AK31: 0 | AS31: ASM | AW31: Level 3 | AX31: 1
C32: GT4 | N32: WGTSS | O32: GT4 | R32: Michelin | S32: 0.007 | AB32: Dunlop | AC32: 0.01 | AS32: Class | AT32: Tyre Supplier | AW32: Setup Bonuses - Reliability
N33: Michelin | O33: 0.0075 | R33: WGTSS | S33: GT3 | AA33: GT3-A | AB33: Dunlop | AC33: 0.01 | AS33: LMP3 | AT33: Michelin | AW33: Level | AX33: Cost
N34: WGTM | O34: GT3-P | R34: Dunlop | S34: 0.01 | AA34: GT4 | AB34: Michelin | AC34: 0.0075 | AS34: GT3 | AT34: Michelin | AW34: Level 1 | AX34: 0.2
N35: Continental | O35: 0.01 | R35: WGTSS | S35: GT4 | AA35: ASM | AS35: GT4 | AT35: Michelin | AW35: Level 2 | AX35: 0.4
N36: Dunlop | O36: 0.01 | R36: Michelin | S36: 0.0075 | AA36: Class | AB36: Tyre Supplier | AC36: Cost Per Race ($M) | AW36: Level 3 | AX36: 0.6
N37: WGTM | O37: GT3-A | R37: WGTM | S37: GT3-P | AA37: LMP3 | AB37: Michelin | AC37: 0.01 | AW37: Level 4 | AX37: 0.85
N38: Dunlop | O38: 0.01 | R38: Continental | S38: 0.01 | AA38: GT3 | AB38: Michelin | AC38: 0.01 | AW38: Level 5 | AX38: 1.1
N39: WGTM | O39: GT4 | R39: Dunlop | S39: 0.01 | AA39: GT4 | AB39: Michelin | AC39: 0.01
N40: Michelin | O40: 0.0075 | R40: WGTM | S40: GT3-A
N41: ASM | O41: LMP3 | R41: Dunlop | S41: 0.01
N42: Michelin | O42: 0.01 | R42: WGTM | S42: GT4
N43: ASM | O43: GT3 | R43: Michelin | S43: 0.0075
N44: Michelin | O44: 0.01 | R44: ASM | S44: LMP3
N45: ASM | O45: GT4 | R45: Michelin | S45: 0.01
N46: Michelin | O46: 0.01 | R46: ASM | S46: GT3
R47: Michelin | S47: 0.01
R48: ASM | S48: GT4
R49: Michelin | S49: 0.01

Sheet Series + Driver Rules
B2: Team Creator V10 - 2018 | F2: Global Endurance Masters | P2: North American Sportscar Championship (Rolex 24 Driver is Completely Free Choice) | Z2: Eurasian Endurance Masters
B3: Driver Rules
B4: Teams may Enter a Maximum of 3 Classes for a Given Series, with the exception of the Global Endurance Masters, where the limit is 2 Classes. | F4: Series Abbreviation | L4: GEM | P4: Series Abbreviation | V4: NASCC | Z4: Series Abbreviation | AF4: EuEM
F5: Class | G5: Platform | H5: Tyres | J5: Max Entries | K5: Lineup Composition | P5: Class | Q5: Platform | R5: Tyres | T5: Max Entries | U5: Lineup Composition | Z5: Class | AA5: Platform | AB5: Tyres | AD5: Max Entries | AE5: Lineup Composition
B6: Lineups may contain AT MOST 1 Bronze Driver (This Requirement is waived in the LMP2 and GTD Classes for the Rolex 24 4th Driver Slot) | F6: LMP1 | G6: LMP1 | H6: Dunlop | I6: Michelin | J6: 2 | K6: Pro | L6: Free (No Bronzes) | P6: DPi | Q6: DPi | R6: Continental | S6: Michelin | T6: 2 | U6: Pro | V6: Free (NB) | W6: Free | Z6: LMP2 | AA6: LMP2 | AB6: Dunlop | AC6: Michelin | AD6: 2 | AE6: Pro | AF6: Free (NB) | AG6: Silver
F7: LMP2 | G7: LMP2 | H7: Dunlop | I7: Michelin | J7: 2 | K7: Pro | L7: Free | M7: Silver | P7: LMP2 | Q7: LMP2 | R7: Continental | S7: Michelin | T7: 2 | U7: Gold | V7: Bronze | W7: Silver | Z7: LMP3 | AA7: LMP3 | AB7: Michelin | AD7: 2 | AE7: Free | AF7: Silver | AG7: Bronze
B8: Events denoted by a Gold Strip in the Calendars Page allow Teams to apply for Up to 2 Additional Entries per Class. All Other One Off Events only permit 1 Additional Entry per Class. | C8: Max Class Entries for each Class are outlined under 'Max Entries'. | F8: LMGTE PRO | G8: LMGTE | H8: Dunlop | I8: Michelin | J8: 2 | K8: Pro | L8: Free (No Bronzes) | P8: GTLM | Q8: LMGTE | R8: Continental | S8: Michelin | T8: 2 | U8: Pro | V8: Free (NB) | W8: Free | Z8: LMGTE | AA8: LMGTE | AB8: Dunlop | AC8: Michelin | AD8: 2 | AE8: Pro | AF8: Silver | AG8: Bronze
F9: LMGTE AM | G9: LMGTE | H9: Dunlop | I9: Michelin | J9: 2 | K9: Pro | L9: Silver | M9: Bronze | P9: GTD | Q9: GT3 | R9: Continental | S9: Michelin | T9: 2 | U9: Pro | V9: Bronze | W9: Silver
C10: Where a Grading is listed, that is the Highest Driver Grading permitted for that Seat on a Crew. Free means any Grading can be chosen. Certain Classes ban the use of Bronze Drivers.
B13: Teams may Apply for up to 3 Additional Entries for any given Event. Unless an Invite has been received. This increases to 4 Entries for an Event with a Gold Strip
C14: A Designation of 'Pro' means the selected Driver for that seat must either be a Platinum or a Gold Ranked Driver.
B17: The Rolex 24 at Daytona is the only Event that permits 4th Drivers, these are Mandatory in LMP2 and GTD, however are optional in DPi and GTLM. | C17: Bronze Drivers may never be Signed to the Driver 1 Seat.
C19: The 'LMP1' platform encompasses both LMP1-H, and LMP1-L

Sheet Series + Driver Rules (2)
B2: Team Creator V10 - 2018 | F2: Global Endurance Masters | O2: Eurasian Endurance Masters | X2: World GT Sprint Series
B3: Driver Rules
B4: Teams may Enter a Maximum of 3 Classes for a Given Series, with the exception of the Global Endurance Masters, where the limit is 2 Classes. | F4: Series Abbreviation | K4: GEM | O4: Series Abbreviation | T4: EuEM | X4: Series Abbreviation
F5: Class | G5: Platform | H5: Tyres | I5: Max Entries | J5: Lineup Composition | O5: Class | P5: Platform | Q5: Tyres | R5: Max Entries | S5: Lineup Composition | X5: Class | Y5: Platform | Z5: Tyres | AA5: Max Entries | AB5: Lineup Composition
B6: Lineups may contain AT MOST 1 Bronze Driver (This Requirement is waived in the LMP2 and GTD Classes for the Rolex 24 4th Driver Slot) | F6: LMP1 | G6: LMP1 | H6: Michelin | I6: 2 | J6: Pro | K6: Free (No Bronzes) | O6: LMP2 | P6: LMP2 | Q6: Free | R6: 2 | S6: Pro | T6: Free (NB) | U6: Silver | X6: GT3 | Y6: GT3 | Z6: Michelin | AA6: 3 | AB6: Pro | AC6: Silver
F7: LMP2 | G7: LMP2 | H7: Free | I7: 2 | J7: Pro | K7: Free | L7: Silver | O7: LMP3 | P7: LMP3 | Q7: Michelin | R7: 2 | S7: Free | T7: Silver | U7: Bronze | X7: GT4 | Y7: GT4 | Z7: Michelin | AA7: 3 | AB7: Gold | AC7: Bronze
B8: Events denoted by a Gold Strip in the Calendars Page allow Teams to apply for Up to 2 Additional Entries per Class. All Other One Off Events only permit 1 Additional Entry per Class. | C8: Max Class Entries for each Class are outlined under 'Max Entries'. | F8: LMGTE PRO | G8: LMGTE | H8: Free | I8: 2 | J8: Pro | K8: Free (No Bronzes) | O8: LMGTE | P8: LMGTE | Q8: Free | R8: 2 | S8: Pro | T8: Silver | U8: Bronze
F9: LMGTE AM | G9: LMGTE | H9: Free | I9: 2 | J9: Pro | K9: Silver | L9: Bronze
C10: Where a Grading is listed, that is the Highest Driver Grading permitted for that Seat on a Crew. Free means any Grading can be chosen. Certain Classes ban the use of Bronze Drivers.
F12: North American Sportscar Championship (Rolex 24 Driver is Completely Free Choice) | O12: World GT Masters | X12: American Sportscar Masters
B13: Teams may Apply for up to 3 Additional Entries for any given Event. Unless an Invite has been received. This increases to 4 Entries for an Event with a Gold Strip
C14: A Designation of 'Pro' means the selected Driver for that seat must either be a Platinum or a Gold Ranked Driver. | F14: Series Abbreviation | K14: NASCC | O14: Series Abbreviation | T14: WGTM | X14: Series Abbreviation
F15: Class | G15: Platform | H15: Tyres | I15: Max Entries | J15: Lineup Composition | O15: Class | P15: Platform | Q15: Tyres | R15: Max Entries | S15: Lineup Composition | X15: Class | Y15: Platform | Z15: Tyres | AA15: Max Entries | AB15: Lineup Composition
F16: DPi | G16: DPi | H16: Michelin | I16: 2 | J16: Pro | K16: Free (NB) | L16: Free | O16: GT3-P | P16: GT3 | Q16: Free | R16: 3 | S16: Pro | T16: Free (No Bronzes) | X16: LMP3 | Y16: LMP3 | Z16: Michelin | AA16: 2 | AB16: Gold | AC16: Bronze
B17: The Rolex 24 at Daytona is the only Event that permits 4th Drivers, these are Mandatory in LMP2 and GTD, however are optional in DPi and GTLM. | C17: Bronze Drivers may never be Signed to the Driver 1 Seat. | F17: LMP2 | G17: LMP2 | H17: Free | I17: 2 | J17: Gold | K17: Bronze | L17: Silver | O17: GT3-A | P17: GT3 | Q17: Michelin | R17: 3 | S17: Pro | T17: Silver | U17: Bronze | X17: GT3 | Y17: GT3 | Z17: Michelin | AA17: 2 | AB17: Pro | AC17: Bronze
F18: GTLM | G18: LMGTE | H18: Michelin | I18: 2 | J18: Pro | K18: Free (NB) | L18: Free | O18: GT4 | P18: GT4 | Q18: Michelin | R18: 3 | S18: Gold | T18: Silver | U18: Bronze | X18: GT4 | Y18: GT4 | Z18: Michelin | AA18: 2 | AB18: Gold | AC18: Bronze
C19: The 'LMP1' platform encompasses both LMP1-H, and LMP1-L | F19: GTD | G19: GT3 | H19: Michelin | I19: 2 | J19: Pro | K19: Bronze | L19: Silver

Sheet Calendars
B2: Team Creator V10 - 2018 | H2: Team Creator V10 - 2018 | R2: Team Creator V10 - 2018 | AC2: Team Creator V10 - 2018 | AL2: Team Creator V10 - 2018 | AU2: Team Creator V10 - 2018 | BE2: Team Creator V10 - 2018
B3: Permitted One Off Entries | H3: Series Calendar | L3: Global Endurance Masters | R3: Series Calendar | W3: North American Sportscar Championship | AC3: Series Calendar | AG3: Eurasian Endurance Masters | AL3: Series Calendar | AP3: World GT Sprint Series | AU3: Series Calendar | AY3: World GT Masters | BE3: Series Calendar | BI3: American Sportscar Masters
B4: Rd No | C4: Title | E4: Notes | H4: Rd No | I4: Title | K4: Track | M4: Length | N4: Points | O4: Date | R4: Rd No | S4: Title | U4: Track | W4: Length | X4: Points | Y4: Classes | Z4: Date | AC4: Rd No | AD4: Title | AF4: Track | AH4: Length | AI4: Date | AL4: Rd No | AM4: Title | AO4: Track | AQ4: Length | AR4: Date | AU4: Rd No | AV4: Title | AX4: Track | AZ4: Length | BA4: Points | BB4: Date | BE4: Rd No | BF4: Title | BH4: Track | BJ4: Length | BK4: Date
B5: GEM | D5: 24 Heures du Mans | E5: Invite + Application | H5: R1 | J5: 8 Hours of Silverstone | K5: Silverstone Circuit | L5: Great Britain | M5: 8 Hours | N5: B | O5: April 15 | R5: R1 | T5: Rolex 24 at Daytona | U5: Daytona International Speedway | V5: United States | W5: 24 Hours | X5: R24, EC | Y5: All | Z5: Jan 27-28 | AC5: R1 | AE5: 4 Hours of Buriram | AF5: Buriram International Circuit | AG5: Thailand | AH5: 4 Hours | AI5: Jan 14 | AL5: R1 | AN5: World GT Sprint Series at Sepang | AO5: Sepang International Circuit | AP5: Malaysia | AQ5: 90 Mins | AR5: Mar 5 | AU5: R1 | AW5: Bathurst 12 Hours | AX5: Mount Panorama | AY5: Australia | AZ5: 12 Hours | BA5: B | BB5: Feb 5 | BE5: R1 | BG5: ASM 150 Minutes of VIR | BH5: Virginia International Raceway | BI5: United States | BJ5: 150 Mins | BK5: Apr 2
B6: NASCC | D6: Rolex 24 at Daytona | E6: Application | H6: R2 | J6: 6 Hours of Spa | K6: Circuit de Spa-Francorshamps | L6: Belgium | M6: 6 Hours | N6: B | O6: May 5 | R6: R2 | T6: 12 Hours of Sebring | U6: Sebring International Raceway | V6: United States | W6: 12 Hours | X6: E, EC | Y6: All | Z6: March 18 | AC6: R2 | AE6: 4 Hours of The Bend | AF6: The Bend Motorsports Park | AG6: Australia | AH6: 4 Hours | AI6: Feb 25 | AL6: R2 | AN6: World GT Sprint Series at Shanghai | AO6: Shanghai International Circuit | AP6: China | AQ6: 90 Mins | AR6: Mar 26 | AU6: R2 | AW6: 8 Hours of Road America | AX6: Road America | AY6: United States | AZ6: 8 Hours | BA6: B | BB6: Apr 9 | BE6: R2 | BG6: ASM 150 Minutes of Sebring | BH6: Sebring International Raceway | BI6: United States | BJ6: 150 Mins | BK6: May 7
B7: NASCC | D7: 12 Hours of Sebring | E7: Application | H7: R3 | J7: 24 Heures du Mans | K7: Circuit de la Sarthe | L7: France | M7: 24 Hours | N7: A | O7: June 16-17 | R7: R3 | T7: Acura Grand Prix of Long Beach | U7: Streets of Long Beach | V7: United States | W7: 100 Mins | X7: S | Y7: DPi, GTD | Z7: April 7 | AC7: R3 | AE7: 4 Hours of Silverstone | AF7: Silverstone Circuit | AG7: Great Britain | AH7: 4 Hours | AI7: April 14 | AL7: R3 | AN7: World GT Sprint Series at Laguna Seca | AO7: WeatherTech Raceway Laguna Seca | AP7: United States | AQ7: 90 Mins | AR7: Apr 30 | AU7: R3 | AW7: 24 Hours of The Nurburgring | AX7: Nurburgring Nordschleiffe | AY7: Germany | AZ7: 24 Hours | BA7: A | BB7: May 28 | BE7: R3 | BG7: ASM 150 Minutes of Daytona | BH7: Daytona International Speedway | BI7: United States | BJ7: 150 Mins | BK7: May 21
B8: NASCC | D8: Petit Le Mans | E8: Application | H8: R4 | J8: 8 Hours of The Nurburgring | K8: Nurburgring | L8: Germany | M8: 8 Hours | N8: B | O8: July 15 | R8: R4 | T8: Mexico City Grand Prix | U8: Autodromo Hermanos Rodriguez | V8: Mexico | W8: 160 Mins | X8: S | Y8: All | Z8: April 29 | AC8: R4 | AE8: 4 Hours of Paul Ricard | AF8: Circuit Paul Ricard | AG8: France | AH8: 4 Hours | AI8: May 13 | AL8: R4 | AN8: World GT Sprint Series at Circuit Zolder | AO8: Circuit Zolder | AP8: Netherlands | AQ8: 90 Mins | AR8: Jun 4 | AU8: R4 | AW8: 24 Hours of Spa | AX8: Circuit de Spa-Francorshamps | AY8: Belgium | AZ8: 24 Hours | BA8: A | BB8: Jul 30 | BE8: R4 | BG8: ASM 150 Minutes of Laguna Seca | BH8: WeatherTech Raceway Laguna Seca | BI8: United States | BJ8: 150 Mins | BK8: Jun 25
H9: R5 | J9: Lonestar Le Mans | K9: Circuit of The Americas | L9: United States | M9: 6 Hours | N9: B | O9: Sept 9 | R9: R5 | T9: Michelin Grand Prix at VIR | U9: Virginia International Raceway | V9: United States | W9: 160 Mins | X9: S | Y9: LMP2, GT | Z9: May 20 | AC9: R5 | AE9: 4 Hours of Imola | AF9: Imola Circuit | AG9: Italy | AH9: 4 Hours | AI9: June 24 | AL9: R5 | AN9: World GT Sprint Series at Le Mans | AO9: Circuit de la Sarthe | AP9: France | AQ9: 2 Hrs | AR9: Jun 16 | AU9: R5 | AW9: 8 Hours of Indianapolis | AX9: Indianapolis Motor Speedway RC | AY9: United States | AZ9: 8 Hours | BA9: B | BB9: Aug 27 | BE9: R5 | BG9: ASM 150 Minutes of CTMP | BH9: Canadian Tire Motorsport Park | BI9: Canada | BJ9: 150 Mins | BK9: Jul 16
H10: R6 | J10: 6 Hours of Kyalami | K10: Kyalami Circuit | L10: South Africa | M10: 6 Hours | N10: B | O10: Oct 7 | R10: R6 | T10: Sahlen's 6 Hours of The Glen | U10: Watkins Glen International | V10: United States | W10: 6 Hours | X10: E, EC | Y10: All | Z10: July 1 | AC10: R6 | AE10: 4 Hours of Aragon | AF10: Motorland Aragon | AG10: Spain | AH10: 4 Hours | AI10: Aug 5 | AL10: R6 | AN10: World GT Sprint Series at Donnington Park | AO10: Donnington Park | AP10: Great Britain | AQ10: 90 Mins | AR10: Jul 9 | AU10: R6 | AW10: 1000km of Suzuka | AX10: Suzuka Circuit | AY10: Japan | AZ10: 1000km | BA10: B | BB10: Oct 8 | BE10: R6 | BG10: ASM 150 Minutes of Charlotte | BH10: Charlotte Motor Speedway Roval | BI10: United States | BJ10: 150 Mins | BK10: Aug 13
H11: R7 | J11: 6 Hours of Fuji | K11: Fuji Speedway | L11: Japan | M11: 6 Hours | N11: B | O11: Oct 28 | R11: R7 | T11: Mosport Showdown | U11: Canadian Tire Motorsport Park | V11: Canada | W11: 160 Mins | X11: S | Y11: LMP2, GTLM | Z11: July 15 | AC11: R7 | AE11: 4 Hours of Portimao | AF11: Autodromo Internacional do Algarve | AG11: Portugal | AH11: 4 Hours | AI11: Sept 2 | AL11: R7 | AN11: World GT Sprint Series at Misano World Circuit | AO11: Misano World Circuit Marco Simoncelli | AP11: Italy | AQ11: 90 Mins | AR11: Jul 30 | AU11: R7 | AW11: 9 Hours of Kyalami | AX11: Kyalami Grand Prix Circuit | AY11: South Africa | AZ11: 9 Hours | BA11: B | BB11: Dec 3 | BE11: R7 | BG11: ASM 150 Minutes of Watkins Glen | BH11: Watkins Glen International | BI11: United States | BJ11: 150 Mins | BK11: Sep 3
H12: R8 | J12: 8 Hours of Bahrain | K12: Bahrain International Circuit | L12: Bahrain | M12: 8 Hours | N12: B | O12: Nov 18 | R12: R8 | T12: American Sportscar Classic | U12: Road America | V12: United States | W12: 6 Hours | X12: E, EC | Y12: All | Z12: Aug 5 | AC12: R8 | AE12: 4 Hours of Sepang | AF12: Sepang International Circuit | AG12: Malaysia | AH12: 4 Hours | AI12: Oct 14 | AL12: R8 | AN12: World GT Sprint Series at Portimao | AO12: Autodromo Internacional do Algarve | AP12: Portugal | AQ12: 90 Mins | AR12: Aug 27 | BE12: R8 | BG12: ASM 150 Minutes of VIR | BH12: Virginia International Raceway | BI12: United States | BJ12: 150 Mins | BK12: Oct 1
R13: R9 | T13: Grand Prix of Texas | U13: Circuit of The Americas | V13: United States | W13: 160 Mins | X13: S | Y13: All | Z13: Aug 19 | AC13: R9 | AE13: 4 Hours of Buddh | AF13: Buddh International Circuit | AG13: India | AH13: 4 Hours | AI13: Nov 4 | AL13: R9 | AN13: World GT Sprint Series in India | AO13: Buddh International Circuit | AP13: India | AQ13: 90 Mins | AR13: Oct 8 | BE13: R9 | BG13: ASM 210 Minutes of CoTA | BH13: Circuit of The Americas | BI13: United States | BJ13: 210 Mins | BK13: Oct 29
R14: R10 | T14: Motul Course de Monterey | U14: WeatherTech Raceway Laguna Seca | V14: United States | W14: 160 Mins | X14: S | Y14: DPi, GT | Z14: Sept 9 | AL14: R10 | AN14: World GT Sprint Series in Korea | AO14: Korea International Circuit | AP14: South Korea | AQ14: 90 Mins | AR14: Oct 29
R15: R11 | T15: Grand Prix of Lime Rock | U15: Lime Rock Park | V15: United States | W15: 160 Mins | X15: S | Y15: DPi, GT | Z15: Sept 30 | AL15: R11 | AN15: World GT Sprint Series at The Gold Coast | AO15: Surfers Paradise Street Circuit | AP15: Australia | AQ15: 2 Hrs | AR15: Nov 19
R16: R12 | T16: Petit Le Mans | U16: Road Atlanta | V16: United States | W16: 10 Hours | X16: E, EC | Y16: All | Z16: Oct 14

Sheet Calendars (2)
B2: Team Creator V10 - 2018 | H2: Team Creator V10 - 2018 | R2: Team Creator V10 - 2018 | AC2: Team Creator V10 - 2018 | AL2: Team Creator V10 - 2018 | AU2: Team Creator V10 - 2018 | BE2: Team Creator V10 - 2018
B3: Permitted One Off Entries | H3: Series Calendar | L3: Global Endurance Masters | R3: Series Calendar | W3: North American Sportscar Championship | AC3: Series Calendar | AG3: Eurasian Endurance Masters | AL3: Series Calendar | AP3: World GT Sprint Series | AU3: Series Calendar | AY3: World GT Masters | BE3: Series Calendar | BI3: American Sportscar Masters
B4: Rd No | C4: Title | E4: Notes | H4: Rd No | I4: Title | K4: Track | M4: Length | N4: Points | O4: Date | R4: Rd No | S4: Title | U4: Track | W4: Length | X4: Points | Y4: Classes | Z4: Date | AC4: Rd No | AD4: Title | AF4: Track | AH4: Length | AI4: Date | AL4: Rd No | AM4: Title | AO4: Track | AQ4: Length | AR4: Date | AU4: Rd No | AV4: Title | AX4: Track | AZ4: Length | BA4: Points | BB4: Date | BE4: Rd No | BF4: Title | BH4: Track | BJ4: Length | BK4: Date
B5: GEM | D5: 24 Heures du Mans | E5: Invite + Application | H5: R1 | J5: 8 Hours of Silverstone | K5: Silverstone Circuit | L5: Great Britain | M5: 8 Hours | N5: B | O5: April 15 | R5: R1 | T5: Rolex 24 at Daytona | U5: Daytona International Speedway | V5: United States | W5: 24 Hours | X5: R24, EC | Y5: All | Z5: Jan 27-28 | AC5: R1 | AE5: 4 Hours of Buriram | AF5: Buriram International Circuit | AG5: Thailand | AH5: 4 Hours | AI5: Jan 14 | AL5: R1 | AN5: World GT Sprint Series at Sepang | AO5: Sepang International Circuit | AP5: Malaysia | AQ5: 90 Mins | AR5: Mar 5 | AU5: R1 | AW5: Bathurst 12 Hours | AX5: Mount Panorama | AY5: Australia | AZ5: 12 Hours | BA5: B | BB5: Feb 5 | BE5: R1 | BG5: ASM 150 Minutes of VIR | BH5: Virginia International Raceway | BI5: United States | BJ5: 150 Mins | BK5: Apr 2
B6: NASCC | D6: Rolex 24 at Daytona | E6: Application | H6: R2 | J6: 6 Hours of Spa | K6: Circuit de Spa-Francorshamps | L6: Belgium | M6: 6 Hours | N6: B | O6: May 5 | R6: R2 | T6: 12 Hours of Sebring | U6: Sebring International Raceway | V6: United States | W6: 12 Hours | X6: E, EC | Y6: All | Z6: March 18 | AC6: R2 | AE6: 4 Hours of The Bend | AF6: The Bend Motorsports Park | AG6: Australia | AH6: 4 Hours | AI6: Feb 25 | AL6: R2 | AN6: World GT Sprint Series at Shanghai | AO6: Shanghai International Circuit | AP6: China | AQ6: 90 Mins | AR6: Mar 26 | AU6: R2 | AW6: 8 Hours of Road America | AX6: Road America | AY6: United States | AZ6: 8 Hours | BA6: B | BB6: Apr 9 | BE6: R2 | BG6: ASM 150 Minutes of Sebring | BH6: Sebring International Raceway | BI6: United States | BJ6: 150 Mins | BK6: May 7
B7: NASCC | D7: 12 Hours of Sebring | E7: Application | H7: R3 | J7: 24 Heures du Mans | K7: Circuit de la Sarthe | L7: France | M7: 24 Hours | N7: A | O7: June 16-17 | R7: R3 | T7: Acura Grand Prix of Long Beach | U7: Streets of Long Beach | V7: United States | W7: 100 Mins | X7: S | Y7: DPi, GTD | Z7: April 7 | AC7: R3 | AE7: 4 Hours of Silverstone | AF7: Silverstone Circuit | AG7: Great Britain | AH7: 4 Hours | AI7: April 14 | AL7: R3 | AN7: World GT Sprint Series at Laguna Seca | AO7: WeatherTech Raceway Laguna Seca | AP7: United States | AQ7: 90 Mins | AR7: Apr 30 | AU7: R3 | AW7: 24 Hours of The Nurburgring | AX7: Nurburgring Nordschleiffe | AY7: Germany | AZ7: 24 Hours | BA7: A | BB7: May 28 | BE7: R3 | BG7: ASM 150 Minutes of Daytona | BH7: Daytona International Speedway | BI7: United States | BJ7: 150 Mins | BK7: May 21
B8: NASCC | D8: Petit Le Mans | E8: Application | H8: R4 | J8: 8 Hours of The Nurburgring | K8: Nurburgring | L8: Germany | M8: 8 Hours | N8: B | O8: July 15 | R8: R4 | T8: Mexico City Grand Prix | U8: Autodromo Hermanos Rodriguez | V8: Mexico | W8: 160 Mins | X8: S | Y8: All | Z8: April 29 | AC8: R4 | AE8: 4 Hours of Paul Ricard | AF8: Circuit Paul Ricard | AG8: France | AH8: 4 Hours | AI8: May 13 | AL8: R4 | AN8: World GT Sprint Series at Circuit Zolder | AO8: Circuit Zolder | AP8: Netherlands | AQ8: 90 Mins | AR8: Jun 4 | AU8: R4 | AW8: 24 Hours of Spa | AX8: Circuit de Spa-Francorshamps | AY8: Belgium | AZ8: 24 Hours | BA8: A | BB8: Jul 30 | BE8: R4 | BG8: ASM 150 Minutes of Laguna Seca | BH8: WeatherTech Raceway Laguna Seca | BI8: United States | BJ8: 150 Mins | BK8: Jun 25
B9: WGTSS | D9: World GT Sprint Series at Le Mans | E9: Application | H9: R5 | J9: Lonestar Le Mans | K9: Circuit of The Americas | L9: United States | M9: 6 Hours | N9: B | O9: Sept 9 | R9: R5 | T9: Michelin Grand Prix at VIR | U9: Virginia International Raceway | V9: United States | W9: 160 Mins | X9: S | Y9: LMP2, GT | Z9: May 20 | AC9: R5 | AE9: 4 Hours of Imola | AF9: Imola Circuit | AG9: Italy | AH9: 4 Hours | AI9: June 24 | AL9: R5 | AN9: World GT Sprint Series at Le Mans | AO9: Circuit de la Sarthe | AP9: France | AQ9: 2 Hrs | AR9: Jun 16 | AU9: R5 | AW9: 8 Hours of Indianapolis | AX9: Indianapolis Motor Speedway RC | AY9: United States | AZ9: 8 Hours | BA9: B | BB9: Aug 27 | BE9: R5 | BG9: ASM 150 Minutes of CTMP | BH9: Canadian Tire Motorsport Park | BI9: Canada | BJ9: 150 Mins | BK9: Jul 16
B10: WGTM | D10: Bathurst 12 Hours | E10: Application | H10: R6 | J10: 6 Hours of Kyalami | K10: Kyalami Circuit | L10: South Africa | M10: 6 Hours | N10: B | O10: Oct 7 | R10: R6 | T10: Sahlen's 6 Hours of The Glen | U10: Watkins Glen International | V10: United States | W10: 6 Hours | X10: E, EC | Y10: All | Z10: July 1 | AC10: R6 | AE10: 4 Hours of Aragon | AF10: Motorland Aragon | AG10: Spain | AH10: 4 Hours | AI10: Aug 5 | AL10: R6 | AN10: World GT Sprint Series at Donnington Park | AO10: Donnington Park | AP10: Great Britain | AQ10: 90 Mins | AR10: Jul 9 | AU10: R6 | AW10: 1000km of Suzuka | AX10: Suzuka Circuit | AY10: Japan | AZ10: 1000km | BA10: B | BB10: Oct 8 | BE10: R6 | BG10: ASM 150 Minutes of Charlotte | BH10: Charlotte Motor Speedway Roval | BI10: United States | BJ10: 150 Mins | BK10: Aug 13
B11: WGTM | D11: 24 Hours of The Nurburgring | E11: Application | H11: R7 | J11: 6 Hours of Fuji | K11: Fuji Speedway | L11: Japan | M11: 6 Hours | N11: B | O11: Oct 28 | R11: R7 | T11: Mosport Showdown | U11: Canadian Tire Motorsport Park | V11: Canada | W11: 160 Mins | X11: S | Y11: LMP2, GTLM | Z11: July 15 | AC11: R7 | AE11: 4 Hours of Portimao | AF11: Autodromo Internacional do Algarve | AG11: Portugal | AH11: 4 Hours | AI11: Sept 2 | AL11: R7 | AN11: World GT Sprint Series at Misano World Circuit | AO11: Misano World Circuit Marco Simoncelli | AP11: Italy | AQ11: 90 Mins | AR11: Jul 30 | AU11: R7 | AW11: 9 Hours of Kyalami | AX11: Kyalami Grand Prix Circuit | AY11: South Africa | AZ11: 9 Hours | BA11: B | BB11: Dec 3 | BE11: R7 | BG11: ASM 150 Minutes of Watkins Glen | BH11: Watkins Glen International | BI11: United States | BJ11: 150 Mins | BK11: Sep 3
B12: WGTM | D12: 24 Hours of Spa | E12: Application | H12: R8 | J12: 8 Hours of Bahrain | K12: Bahrain International Circuit | L12: Bahrain | M12: 8 Hours | N12: B | O12: Nov 18 | R12: R8 | T12: American Sportscar Classic | U12: Road America | V12: United States | W12: 6 Hours | X12: E, EC | Y12: All | Z12: Aug 5 | AC12: R8 | AE12: 4 Hours of Sepang | AF12: Sepang International Circuit | AG12: Malaysia | AH12: 4 Hours | AI12: Oct 14 | AL12: R8 | AN12: World GT Sprint Series at Portimao | AO12: Autodromo Internacional do Algarve | AP12: Portugal | AQ12: 90 Mins | AR12: Aug 27 | BE12: R8 | BG12: ASM 150 Minutes of VIR | BH12: Virginia International Raceway | BI12: United States | BJ12: 150 Mins | BK12: Oct 1
B13: ASM | D13: ASM 210 Minutes of CoTA | E13: Application | R13: R9 | T13: Grand Prix of Texas | U13: Circuit of The Americas | V13: United States | W13: 160 Mins | X13: S | Y13: All | Z13: Aug 19 | AC13: R9 | AE13: 4 Hours of Buddh | AF13: Buddh International Circuit | AG13: India | AH13: 4 Hours | AI13: Nov 4 | AL13: R9 | AN13: World GT Sprint Series in India | AO13: Buddh International Circuit | AP13: India | AQ13: 90 Mins | AR13: Oct 8 | BE13: R9 | BG13: ASM 210 Minutes of CoTA | BH13: Circuit of The Americas | BI13: United States | BJ13: 210 Mins | BK13: Oct 29
R14: R10 | T14: Motul Course de Monterey | U14: WeatherTech Raceway Laguna Seca | V14: United States | W14: 160 Mins | X14: S | Y14: DPi, GT | Z14: Sept 9 | AL14: R10 | AN14: World GT Sprint Series in Korea | AO14: Korea International Circuit | AP14: South Korea | AQ14: 90 Mins | AR14: Oct 29
R15: R11 | T15: Grand Prix of Lime Rock | U15: Lime Rock Park | V15: United States | W15: 160 Mins | X15: S | Y15: DPi, GT | Z15: Sept 30 | AL15: R11 | AN15: World GT Sprint Series at The Gold Coast | AO15: Surfers Paradise Street Circuit | AP15: Australia | AQ15: 2 Hrs | AR15: Nov 19
R16: R12 | T16: Petit Le Mans | U16: Road Atlanta | V16: United States | W16: 10 Hours | X16: E, EC | Y16: All | Z16: Oct 14

Sheet Car Purchase
B2: Team Creator V10 - 2018 | H2: Team Creator V10 - 2018
B3: Car Purchase | H3: Spares Purchase
B4: Given ID | C4: Platform | D4: Model Name | E4: Notes | H4: Platform | I4: Model Name | J4: Chassis | K4: Powertrain | L4: Spares | O4: Selected Tyre Suppliers
B5: DPi_1 | C5: =IF(D5 <> "", VLOOKUP(D5, modelData, 2, FALSE), "") -> DPi | D5: Acura ARX-05 | H5: =IF(AND(I5 <> "", I5 <> 0), VLOOKUP(I5, modelData, 2, FALSE), "") -> DPi | I5: {=IF(_xlfn.UNIQUE(D5:D49, 0, FALSE) = 0, "", _xlfn.UNIQUE(D5:D49, 0, FALSE))} -> Acura ARX-05 | O5: Global Endurance Masters
B6: DPi_2 | C6: =IF(D6 <> "", VLOOKUP(D6, modelData, 2, FALSE), "") -> DPi | D6: Cadillac DPi-V.R | H6: =IF(AND(I6 <> "", I6 <> 0), VLOOKUP(I6, modelData, 2, FALSE), "") -> DPi | I6: Cadillac DPi-V.R | O6: Class | P6: Tyre Supplier
B7: DPi_3 | C7: =IF(D7 <> "", VLOOKUP(D7, modelData, 2, FALSE), "") -> DPi | D7: Mazda RT24-P | H7: =IF(AND(I7 <> "", I7 <> 0), VLOOKUP(I7, modelData, 2, FALSE), "") -> DPi | I7: Mazda RT24-P | O7: LMP1 | P7: Michelin
B8: DPi_4 | C8: =IF(D8 <> "", VLOOKUP(D8, modelData, 2, FALSE), "") -> DPi | D8: Nissan Onroak DPi | H8: =IF(AND(I8 <> "", I8 <> 0), VLOOKUP(I8, modelData, 2, FALSE), "") -> DPi | I8: Nissan Onroak DPi | O8: LMP2
B9: LMP1_1 | C9: =IF(D9 <> "", VLOOKUP(D9, modelData, 2, FALSE), "") -> LMP1-L | D9: BR Engineering BR1 | H9: =IF(AND(I9 <> "", I9 <> 0), VLOOKUP(I9, modelData, 2, FALSE), "") -> LMP1-L | I9: BR Engineering BR1 | O9: LMGTE PRO
B10: LMP1_2 | C10: =IF(D10 <> "", VLOOKUP(D10, modelData, 2, FALSE), "") -> LMP1-L | D10: ENSO CLM P1/01 | H10: =IF(AND(I10 <> "", I10 <> 0), VLOOKUP(I10, modelData, 2, FALSE), "") -> LMP1-L | I10: ENSO CLM P1/01 | O10: LMGTE AM
B11: LMP1_3 | C11: =IF(D11 <> "", VLOOKUP(D11, modelData, 2, FALSE), "") -> LMP1-L | D11: Ginetta G60-LT-P1 | H11: =IF(AND(I11 <> "", I11 <> 0), VLOOKUP(I11, modelData, 2, FALSE), "") -> LMP1-L | I11: Ginetta G60-LT-P1 | O11: NASCC
B12: LMP1_4 | C12: =IF(D12 <> "", VLOOKUP(D12, modelData, 2, FALSE), "") -> LMP1-L | D12: Rebellion R13 | H12: =IF(AND(I12 <> "", I12 <> 0), VLOOKUP(I12, modelData, 2, FALSE), "") -> LMP1-L | I12: Rebellion R13 | O12: Class | P12: Tyre Supplier
B13: LMP1_5 | C13: =IF(D13 <> "", VLOOKUP(D13, modelData, 2, FALSE), "") -> LMP1-H | D13: Porsche 919 Hybrid | H13: =IF(AND(I13 <> "", I13 <> 0), VLOOKUP(I13, modelData, 2, FALSE), "") -> LMP1-H | I13: Porsche 919 Hybrid | O13: DPi | P13: Michelin
B14: LMP1_6 | C14: =IF(D14 <> "", VLOOKUP(D14, modelData, 2, FALSE), "") -> LMP1-H | D14: Toyota TS050 - Hybrid | H14: =IF(AND(I14 <> "", I14 <> 0), VLOOKUP(I14, modelData, 2, FALSE), "") -> LMP1-H | I14: Toyota TS050 - Hybrid | O14: LMP2
C15: =IF(D15 <> "", VLOOKUP(D15, modelData, 2, FALSE), "") | H15: =IF(AND(I15 <> "", I15 <> 0), VLOOKUP(I15, modelData, 2, FALSE), "") | O15: GTLM
C16: =IF(D16 <> "", VLOOKUP(D16, modelData, 2, FALSE), "") | H16: =IF(AND(I16 <> "", I16 <> 0), VLOOKUP(I16, modelData, 2, FALSE), "") | O16: GTD
C17: =IF(D17 <> "", VLOOKUP(D17, modelData, 2, FALSE), "") | H17: =IF(AND(I17 <> "", I17 <> 0), VLOOKUP(I17, modelData, 2, FALSE), "") | O17: EuEM
C18: =IF(D18 <> "", VLOOKUP(D18, modelData, 2, FALSE), "") | H18: =IF(AND(I18 <> "", I18 <> 0), VLOOKUP(I18, modelData, 2, FALSE), "") | O18: Class | P18: Tyre Supplier
C19: =IF(D19 <> "", VLOOKUP(D19, modelData, 2, FALSE), "") | H19: =IF(AND(I19 <> "", I19 <> 0), VLOOKUP(I19, modelData, 2, FALSE), "") | O19: LMP2
C20: =IF(D20 <> "", VLOOKUP(D20, modelData, 2, FALSE), "") | H20: =IF(AND(I20 <> "", I20 <> 0), VLOOKUP(I20, modelData, 2, FALSE), "") | O20: LMP3 | P20: Michelin
C21: =IF(D21 <> "", VLOOKUP(D21, modelData, 2, FALSE), "") | H21: =IF(AND(I21 <> "", I21 <> 0), VLOOKUP(I21, modelData, 2, FALSE), "") | O21: LMGTE
C22: =IF(D22 <> "", VLOOKUP(D22, modelData, 2, FALSE), "") | H22: =IF(AND(I22 <> "", I22 <> 0), VLOOKUP(I22, modelData, 2, FALSE), "")
C23: =IF(D23 <> "", VLOOKUP(D23, modelData, 2, FALSE), "") | H23: =IF(AND(I23 <> "", I23 <> 0), VLOOKUP(I23, modelData, 2, FALSE), "")
C24: =IF(D24 <> "", VLOOKUP(D24, modelData, 2, FALSE), "") | H24: =IF(AND(I24 <> "", I24 <> 0), VLOOKUP(I24, modelData, 2, FALSE), "")
C25: =IF(D25 <> "", VLOOKUP(D25, modelData, 2, FALSE), "") | H25: =IF(AND(I25 <> "", I25 <> 0), VLOOKUP(I25, modelData, 2, FALSE), "")
C26: =IF(D26 <> "", VLOOKUP(D26, modelData, 2, FALSE), "") | H26: =IF(AND(I26 <> "", I26 <> 0), VLOOKUP(I26, modelData, 2, FALSE), "")
C27: =IF(D27 <> "", VLOOKUP(D27, modelData, 2, FALSE), "") | H27: =IF(AND(I27 <> "", I27 <> 0), VLOOKUP(I27, modelData, 2, FALSE), "")
C28: =IF(D28 <> "", VLOOKUP(D28, modelData, 2, FALSE), "") | H28: =IF(AND(I28 <> "", I28 <> 0), VLOOKUP(I28, modelData, 2, FALSE), "")
C29: =IF(D29 <> "", VLOOKUP(D29, modelData, 2, FALSE), "") | H29: =IF(AND(I29 <> "", I29 <> 0), VLOOKUP(I29, modelData, 2, FALSE), "")
C30: =IF(D30 <> "", VLOOKUP(D30, modelData, 2, FALSE), "") | H30: =IF(AND(I30 <> "", I30 <> 0), VLOOKUP(I30, modelData, 2, FALSE), "")
C31: =IF(D31 <> "", VLOOKUP(D31, modelData, 2, FALSE), "") | H31: =IF(AND(I31 <> "", I31 <> 0), VLOOKUP(I31, modelData, 2, FALSE), "")
C32: =IF(D32 <> "", VLOOKUP(D32, modelData, 2, FALSE), "") | H32: =IF(AND(I32 <> "", I32 <> 0), VLOOKUP(I32, modelData, 2, FALSE), "")
C33: =IF(D33 <> "", VLOOKUP(D33, modelData, 2, FALSE), "") | H33: =IF(AND(I33 <> "", I33 <> 0), VLOOKUP(I33, modelData, 2, FALSE), "")
... C49: =IF(D49 <> "", VLOOKUP(D49, modelData, 2, FALSE), "") | H49: =IF(AND(I49 <> "", I49 <> 0), VLOOKUP(I49, modelData, 2, FALSE), "")

Sheet Full Season Entries
B2: Team Creator V10 - 2018
B3: Full Season Entries | X3: Team Creator V10 - 2018
B4: Entry No | C4: Series Information | E4: Entry Details | H4: Car Model Details | K4: Driver Details | P4: Entrant Setup Bonuses | U4: Total Costs | X4: Full Season Entries | AA4: Car Model Fetching | AF4: Class Fetching
C5: Series Name | D5: Class | E5: Car No | F5: Team Name | G5: Tyre Supplier | H5: Model ID | I5: Platform | J5: Model Name | K5: Driver 1 | L5: Driver 2 | M5: Driver 3 | N5: Driver 4 | O5: Legality | P5: Setup | T5: Reliability | X5: Usage Guide | AA5: Platform | AB5: Model Name | AD5: Tyre Supplier | AF5: Indices | AH5: Rough | AI5: Final | AN5: Lineup Legality | AP5: Entry Costs
B6: =IF(C6 <> "", 1, "") | D6: =IF(ISERROR(AI6), "", AI6) | G6: =IF(ISERROR(AD6), "", IF(AD6 = 0, "", AD6)) | I6: =IF(ISERROR(AA6), "", AA6) | J6: =IF(ISERROR(AB6), "", AB6) | O6: =IF(ISERROR(AN6), "", AN6) | U6: =IF(ISERROR(AP6), "", AP6) | X6: Model Platform and Name will automatically fill in when given an existing Model ID set in 'Car Purchase' | AA6: =IF(H6 <> "", IF(VLOOKUP(H6, purchasedCars, 2, FALSE) = "", "", VLOOKUP(H6, purchasedCars, 2, FALSE)),"") | AB6: =IF(H6 <> "", IF(VLOOKUP(H6, purchasedCars, 3, FALSE) = "", "", VLOOKUP(H6, purchasedCars, 3, FALSE)),"") | AD6: =IF(AF6 = 1, VLOOKUP(TRIM(AI6), gemSupplier, 2, FALSE), IF(AF6 = 2, VLOOKUP(TRIM(AI6), nasccSupplier, 2, FALSE), IF(AF6 = 2.1, VLOOKUP(TRIM(AI6), nasccSupplier, 2, FALSE), IF(AF6 = 2.2, VLOOKUP(TRIM(AI6), nasccSupplier, 2, FALSE), IF(AF6 = 3, VLOOKUP(TRIM(AI6), euemSupplier, 2, FALSE), IF(AF6 = 4, VLOOKUP(TRIM(AI6), wgtssSupplier, 2, FALSE), IF(AF6 = 5, VLOOKUP(TRIM(AI6), wgtmSupplier, 2, FALSE), IF(AF6 = 7, VLOOKUP(TRIM(AI6), asmSupplier, 2, FALSE), "")))))))) | AF6: =IF(C6 <> "", VLOOKUP(C6, seriesClasses, 2, FALSE), 0) -> 0 | AG6: =IF(AI6 <> "", VLOOKUP(AI6, classIndexes, 2, FALSE), 0) -> 0 | AH6: =IF(AF6 = 0, "", IF(AF6 = 1, VLOOKUP(I6, gemClasses, 2, FALSE), IF(AF6 = 2, VLOOKUP(I6, nasccClasses, 2, FALSE), IF(AF6 = 2.1, VLOOKUP(I6, nasccClasses, 2, FALSE), IF(AF6 = 2.2, VLOOKUP(I6, nasccClasses, 2, FALSE), IF(AF6 = 3, VLOOKUP(I6, euemClasses, 2, FALSE), IF(AF6 = 4, VLOOKUP(I6, wgtssClasses, 2, FALSE), IF(AF6 = 5, VLOOKUP(I6, wgtmClasses, 2, FALSE), IF(AF6 = 6, VLOOKUP(I6, wpcClasses, 2, FALSE), IF(AF6 = 7, VLOOKUP(I6, asmClasses, 2, FALSE), "")))))))))) | AI6: =IF(AF6 = 1, AK6, IF(AF6 = 5, AL6, AH6)) | AK6: =IF(AND(IF(AH6 = "LMGTE PRO", TRUE, FALSE), IF(M6 = "Bronze", TRUE, FALSE)), "LMGTE AM", AH6) | AL6: =IF(AND(IF(AH6 = "GT3-P", TRUE, FALSE), IF(M6 = "Bronze", TRUE, FALSE)), "GT3-A", AH6) | AN6: ='Lineup Legality - FS'!L5 | AP6: =IF(H6 <> "", CONCATENATE("$", ROUND(SUM('Total Costs'!M5:V5), 3), " Million"), "")
B7: =IF(C7 <> "", B6 + 1, "") | D7: =IF(ISERROR(AI7), "", AI7) | G7: =IF(ISERROR(AD7), "", IF(AD7 = 0, "", AD7)) | I7: =IF(ISERROR(AA7), "", AA7) | J7: =IF(ISERROR(AB7), "", AB7) | O7: =IF(ISERROR(AN7), "", AN7) | U7: =IF(ISERROR(AP7), "", AP7) | AA7: =IF(H7 <> "", IF(VLOOKUP(H7, purchasedCars, 2, FALSE) = "", "", VLOOKUP(H7, purchasedCars, 2, FALSE)),"") | AB7: =IF(H7 <> "", IF(VLOOKUP(H7, purchasedCars, 3, FALSE) = "", "", VLOOKUP(H7, purchasedCars, 3, FALSE)),"") | AD7: =IF(AF7 = 1, VLOOKUP(TRIM(AI7), gemSupplier, 2, FALSE), IF(AF7 = 2, VLOOKUP(TRIM(AI7), nasccSupplier, 2, FALSE), IF(AF7 = 2.1, VLOOKUP(TRIM(AI7), nasccSupplier, 2, FALSE), IF(AF7 = 2.2, VLOOKUP(TRIM(AI7), nasccSupplier, 2, FALSE), IF(AF7 = 3, VLOOKUP(TRIM(AI7), euemSupplier, 2, FALSE), IF(AF7 = 4, VLOOKUP(TRIM(AI7), wgtssSupplier, 2, FALSE), IF(AF7 = 5, VLOOKUP(TRIM(AI7), wgtmSupplier, 2, FALSE), IF(AF7 = 7, VLOOKUP(TRIM(AI7), asmSupplier, 2, FALSE), "")))))))) | AF7: =IF(C7 <> "", VLOOKUP(C7, seriesClasses, 2, FALSE), 0) -> 0 | AG7: =IF(AI7 <> "", VLOOKUP(AI7, classIndexes, 2, FALSE), 0) -> 0 | AH7: =IF(AF7 = 0, "", IF(AF7 = 1, VLOOKUP(I7, gemClasses, 2, FALSE), IF(AF7 = 2, VLOOKUP(I7, nasccClasses, 2, FALSE), IF(AF7 = 2.1, VLOOKUP(I7, nasccClasses, 2, FALSE), IF(AF7 = 2.2, VLOOKUP(I7, nasccClasses, 2, FALSE), IF(AF7 = 3, VLOOKUP(I7, euemClasses, 2, FALSE), IF(AF7 = 4, VLOOKUP(I7, wgtssClasses, 2, FALSE), IF(AF7 = 5, VLOOKUP(I7, wgtmClasses, 2, FALSE), IF(AF7 = 6, VLOOKUP(I7, wpcClasses, 2, FALSE), IF(AF7 = 7, VLOOKUP(I7, asmClasses, 2, FALSE), "")))))))))) | AI7: =IF(AF7 = 1, AK7, IF(AF7 = 5, AL7, AH7)) | AK7: =IF(AND(IF(AH7 = "LMGTE PRO", TRUE, FALSE), IF(M7 = "Bronze", TRUE, FALSE)), "LMGTE AM", AH7) | AL7: =IF(AND(IF(AH7 = "GT3-P", TRUE, FALSE), IF(M7 = "Bronze", TRUE, FALSE)), "GT3-A", AH7) | AN7: ='Lineup Legality - FS'!L9 | AP7: =IF(H7 <> "", CONCATENATE("$", ROUND(SUM('Total Costs'!M6:V6), 3), " Million"), "")
B8: =IF(C8 <> "", B7 + 1, "") | D8: =IF(ISERROR(AI8), "", AI8) | G8: =IF(ISERROR(AD8), "", IF(AD8 = 0, "", AD8)) | I8: =IF(ISERROR(AA8), "", AA8) | J8: =IF(ISERROR(AB8), "", AB8) | O8: =IF(ISERROR(AN8), "", AN8) | U8: =IF(ISERROR(AP8), "", AP8) | AA8: =IF(H8 <> "", IF(VLOOKUP(H8, purchasedCars, 2, FALSE) = "", "", VLOOKUP(H8, purchasedCars, 2, FALSE)),"") | AB8: =IF(H8 <> "", IF(VLOOKUP(H8, purchasedCars, 3, FALSE) = "", "", VLOOKUP(H8, purchasedCars, 3, FALSE)),"") | AD8: =IF(AF8 = 1, VLOOKUP(TRIM(AI8), gemSupplier, 2, FALSE), IF(AF8 = 2, VLOOKUP(TRIM(AI8), nasccSupplier, 2, FALSE), IF(AF8 = 2.1, VLOOKUP(TRIM(AI8), nasccSupplier, 2, FALSE), IF(AF8 = 2.2, VLOOKUP(TRIM(AI8), nasccSupplier, 2, FALSE), IF(AF8 = 3, VLOOKUP(TRIM(AI8), euemSupplier, 2, FALSE), IF(AF8 = 4, VLOOKUP(TRIM(AI8), wgtssSupplier, 2, FALSE), IF(AF8 = 5, VLOOKUP(TRIM(AI8), wgtmSupplier, 2, FALSE), IF(AF8 = 7, VLOOKUP(TRIM(AI8), asmSupplier, 2, FALSE), "")))))))) | AF8: =IF(C8 <> "", VLOOKUP(C8, seriesClasses, 2, FALSE), 0) -> 0 | AG8: =IF(AI8 <> "", VLOOKUP(AI8, classIndexes, 2, FALSE), 0) -> 0 | AH8: =IF(AF8 = 0, "", IF(AF8 = 1, VLOOKUP(I8, gemClasses, 2, FALSE), IF(AF8 = 2, VLOOKUP(I8, nasccClasses, 2, FALSE), IF(AF8 = 2.1, VLOOKUP(I8, nasccClasses, 2, FALSE), IF(AF8 = 2.2, VLOOKUP(I8, nasccClasses, 2, FALSE), IF(AF8 = 3, VLOOKUP(I8, euemClasses, 2, FALSE), IF(AF8 = 4, VLOOKUP(I8, wgtssClasses, 2, FALSE), IF(AF8 = 5, VLOOKUP(I8, wgtmClasses, 2, FALSE), IF(AF8 = 6, VLOOKUP(I8, wpcClasses, 2, FALSE), IF(AF8 = 7, VLOOKUP(I8, asmClasses, 2, FALSE), "")))))))))) | AI8: =IF(AF8 = 1, AK8, IF(AF8 = 5, AL8, AH8)) | AK8: =IF(AND(IF(AH8 = "LMGTE PRO", TRUE, FALSE), IF(M8 = "Bronze", TRUE, FALSE)), "LMGTE AM", AH8) | AL8: =IF(AND(IF(AH8 = "GT3-P", TRUE, FALSE), IF(M8 = "Bronze", TRUE, FALSE)), "GT3-A", AH8) | AN8: ='Lineup Legality - FS'!L13 | AP8: =IF(H8 <> "", CONCATENATE("$", ROUND(SUM('Total Costs'!M7:V7), 3), " Million"), "")
B9: =IF(C9 <> "", B8 + 1, "") | D9: =IF(ISERROR(AI9), "", AI9) | G9: =IF(ISERROR(AD9), "", IF(AD9 = 0, "", AD9)) | I9: =IF(ISERROR(AA9), "", AA9) | J9: =IF(ISERROR(AB9), "", AB9) | O9: =IF(ISERROR(AN9), "", AN9) | U9: =IF(ISERROR(AP9), "", AP9) | X9: Class Field will Automatically fill in based on the Series and Desired Car Model Provided | AA9: =IF(H9 <> "", IF(VLOOKUP(H9, purchasedCars, 2, FALSE) = "", "", VLOOKUP(H9, purchasedCars, 2, FALSE)),"") | AB9: =IF(H9 <> "", IF(VLOOKUP(H9, purchasedCars, 3, FALSE) = "", "", VLOOKUP(H9, purchasedCars, 3, FALSE)),"") | AD9: =IF(AF9 = 1, VLOOKUP(TRIM(AI9), gemSupplier, 2, FALSE), IF(AF9 = 2, VLOOKUP(TRIM(AI9), nasccSupplier, 2, FALSE), IF(AF9 = 2.1, VLOOKUP(TRIM(AI9), nasccSupplier, 2, FALSE), IF(AF9 = 2.2, VLOOKUP(TRIM(AI9), nasccSupplier, 2, FALSE), IF(AF9 = 3, VLOOKUP(TRIM(AI9), euemSupplier, 2, FALSE), IF(AF9 = 4, VLOOKUP(TRIM(AI9), wgtssSupplier, 2, FALSE), IF(AF9 = 5, VLOOKUP(TRIM(AI9), wgtmSupplier, 2, FALSE), IF(AF9 = 7, VLOOKUP(TRIM(AI9), asmSupplier, 2, FALSE), "")))))))) | AF9: =IF(C9 <> "", VLOOKUP(C9, seriesClasses, 2, FALSE), 0) -> 0 | AG9: =IF(AI9 <> "", VLOOKUP(AI9, classIndexes, 2, FALSE), 0) -> 0 | AH9: =IF(AF9 = 0, "", IF(AF9 = 1, VLOOKUP(I9, gemClasses, 2, FALSE), IF(AF9 = 2, VLOOKUP(I9, nasccClasses, 2, FALSE), IF(AF9 = 2.1, VLOOKUP(I9, nasccClasses, 2, FALSE), IF(AF9 = 2.2, VLOOKUP(I9, nasccClasses, 2, FALSE), IF(AF9 = 3, VLOOKUP(I9, euemClasses, 2, FALSE), IF(AF9 = 4, VLOOKUP(I9, wgtssClasses, 2, FALSE), IF(AF9 = 5, VLOOKUP(I9, wgtmClasses, 2, FALSE), IF(AF9 = 6, VLOOKUP(I9, wpcClasses, 2, FALSE), IF(AF9 = 7, VLOOKUP(I9, asmClasses, 2, FALSE), "")))))))))) | AI9: =IF(AF9 = 1, AK9, IF(AF9 = 5, AL9, AH9)) | AK9: =IF(AND(IF(AH9 = "LMGTE PRO", TRUE, FALSE), IF(M9 = "Bronze", TRUE, FALSE)), "LMGTE AM", AH9) | AL9: =IF(AND(IF(AH9 = "GT3-P", TRUE, FALSE), IF(M9 = "Bronze", TRUE, FALSE)), "GT3-A", AH9) | AN9: ='Lineup Legality - FS'!L17 | AP9: =IF(H9 <> "", CONCATENATE("$", ROUND(SUM('Total Costs'!M8:V8), 3), " Million"), "")
B10: =IF(C10 <> "", B9 + 1, "") | D10: =IF(ISERROR(AI10), "", AI10) | G10: =IF(ISERROR(AD10), "", IF(AD10 = 0, "", AD10)) | I10: =IF(ISERROR(AA10), "", AA10) | J10: =IF(ISERROR(AB10), "", AB10) | O10: =IF(ISERROR(AN10), "", AN10) | U10: =IF(ISERROR(AP10), "", AP10) | AA10: =IF(H10 <> "", IF(VLOOKUP(H10, purchasedCars, 2, FALSE) = "", "", VLOOKUP(H10, purchasedCars, 2, FALSE)),"") | AB10: =IF(H10 <> "", IF(VLOOKUP(H10, purchasedCars, 3, FALSE) = "", "", VLOOKUP(H10, purchasedCars, 3, FALSE)),"") | AD10: =IF(AF10 = 1, VLOOKUP(TRIM(AI10), gemSupplier, 2, FALSE), IF(AF10 = 2, VLOOKUP(TRIM(AI10), nasccSupplier, 2, FALSE), IF(AF10 = 2.1, VLOOKUP(TRIM(AI10), nasccSupplier, 2, FALSE), IF(AF10 = 2.2, VLOOKUP(TRIM(AI10), nasccSupplier, 2, FALSE), IF(AF10 = 3, VLOOKUP(TRIM(AI10), euemSupplier, 2, FALSE), IF(AF10 = 4, VLOOKUP(TRIM(AI10), wgtssSupplier, 2, FALSE), IF(AF10 = 5, VLOOKUP(TRIM(AI10), wgtmSupplier, 2, FALSE), IF(AF10 = 7, VLOOKUP(TRIM(AI10), asmSupplier, 2, FALSE), "")))))))) | AF10: =IF(C10 <> "", VLOOKUP(C10, seriesClasses, 2, FALSE), 0) -> 0 | AG10: =IF(AI10 <> "", VLOOKUP(AI10, classIndexes, 2, FALSE), 0) -> 0 | AH10: =IF(AF10 = 0, "", IF(AF10 = 1, VLOOKUP(I10, gemClasses, 2, FALSE), IF(AF10 = 2, VLOOKUP(I10, nasccClasses, 2, FALSE), IF(AF10 = 2.1, VLOOKUP(I10, nasccClasses, 2, FALSE), IF(AF10 = 2.2, VLOOKUP(I10, nasccClasses, 2, FALSE), IF(AF10 = 3, VLOOKUP(I10, euemClasses, 2, FALSE), IF(AF10 = 4, VLOOKUP(I10, wgtssClasses, 2, FALSE), IF(AF10 = 5, VLOOKUP(I10, wgtmClasses, 2, FALSE), IF(AF10 = 6, VLOOKUP(I10, wpcClasses, 2, FALSE), IF(AF10 = 7, VLOOKUP(I10, asmClasses, 2, FALSE), "")))))))))) | AI10: =IF(AF10 = 1, AK10, IF(AF10 = 5, AL10, AH10)) | AK10: =IF(AND(IF(AH10 = "LMGTE PRO", TRUE, FALSE), IF(M10 = "Bronze", TRUE, FALSE)), "LMGTE AM", AH10) | AL10: =IF(AND(IF(AH10 = "GT3-P", TRUE, FALSE), IF(M10 = "Bronze", TRUE, FALSE)), "GT3-A", AH10) | AN10: ='Lineup Legality - FS'!L21 | AP10: =IF(H10 <> "", CONCATENATE("$", ROUND(SUM('Total Costs'!M9:V9), 3), " Million"), "")
B11: =IF(C11 <> "", B10 + 1, "") | D11: =IF(ISERROR(AI11), "", AI11) | G11: =IF(ISERROR(AD11), "", IF(AD11 = 0, "", AD11)) | I11: =IF(ISERROR(AA11), "", AA11) | J11: =IF(ISERROR(AB11), "", AB11) | O11: =IF(ISERROR(AN11), "", AN11) | U11: =IF(ISERROR(AP11), "", AP11) | AA11: =IF(H11 <> "", IF(VLOOKUP(H11, purchasedCars, 2, FALSE) = "", "", VLOOKUP(H11, purchasedCars, 2, FALSE)),"") | AB11: =IF(H11 <> "", IF(VLOOKUP(H11, purchasedCars, 3, FALSE) = "", "", VLOOKUP(H11, purchasedCars, 3, FALSE)),"") | AD11: =IF(AF11 = 1, VLOOKUP(TRIM(AI11), gemSupplier, 2, FALSE), IF(AF11 = 2, VLOOKUP(TRIM(AI11), nasccSupplier, 2, FALSE), IF(AF11 = 2.1, VLOOKUP(TRIM(AI11), nasccSupplier, 2, FALSE), IF(AF11 = 2.2, VLOOKUP(TRIM(AI11), nasccSupplier, 2, FALSE), IF(AF11 = 3, VLOOKUP(TRIM(AI11), euemSupplier, 2, FALSE), IF(AF11 = 4, VLOOKUP(TRIM(AI11), wgtssSupplier, 2, FALSE), IF(AF11 = 5, VLOOKUP(TRIM(AI11), wgtmSupplier, 2, FALSE), IF(AF11 = 7, VLOOKUP(TRIM(AI11), asmSupplier, 2, FALSE), "")))))))) | AF11: =IF(C11 <> "", VLOOKUP(C11, seriesClasses, 2, FALSE), 0) -> 0 | AG11: =IF(AI11 <> "", VLOOKUP(AI11, classIndexes, 2, FALSE), 0) -> 0 | AH11: =IF(AF11 = 0, "", IF(AF11 = 1, VLOOKUP(I11, gemClasses, 2, FALSE), IF(AF11 = 2, VLOOKUP(I11, nasccClasses, 2, FALSE), IF(AF11 = 2.1, VLOOKUP(I11, nasccClasses, 2, FALSE), IF(AF11 = 2.2, VLOOKUP(I11, nasccClasses, 2, FALSE), IF(AF11 = 3, VLOOKUP(I11, euemClasses, 2, FALSE), IF(AF11 = 4, VLOOKUP(I11, wgtssClasses, 2, FALSE), IF(AF11 = 5, VLOOKUP(I11, wgtmClasses, 2, FALSE), IF(AF11 = 6, VLOOKUP(I11, wpcClasses, 2, FALSE), IF(AF11 = 7, VLOOKUP(I11, asmClasses, 2, FALSE), "")))))))))) | AI11: =IF(AF11 = 1, AK11, IF(AF11 = 5, AL11, AH11)) | AK11: =IF(AND(IF(AH11 = "LMGTE PRO", TRUE, FALSE), IF(M11 = "Bronze", TRUE, FALSE)), "LMGTE AM", AH11) | AL11: =IF(AND(IF(AH11 = "GT3-P", TRUE, FALSE), IF(M11 = "Bronze", TRUE, FALSE)), "GT3-A", AH11) | AN11: ='Lineup Legality - FS'!L25 | AP11: =IF(H11 <> "", CONCATENATE("$", ROUND(SUM('Total Costs'!M10:V10), 3), " Million"), "")
B12: =IF(C12 <> "", B11 + 1, "") | D12: =IF(ISERROR(AI12), "", AI12) | G12: =IF(ISERROR(AD12), "", IF(AD12 = 0, "", AD12)) | I12: =IF(ISERROR(AA12), "", AA12) | J12: =IF(ISERROR(AB12), "", AB12) | O12: =IF(ISERROR(AN12), "", AN12) | U12: =IF(ISERROR(AP12), "", AP12) | X12: Only Driver Rankings can be entered in the Driver Details Columns, Real Driver Names will not be accepted | AA12: =IF(H12 <> "", IF(VLOOKUP(H12, purchasedCars, 2, FALSE) = "", "", VLOOKUP(H12, purchasedCars, 2, FALSE)),"") | AB12: =IF(H12 <> "", IF(VLOOKUP(H12, purchasedCars, 3, FALSE) = "", "", VLOOKUP(H12, purchasedCars, 3, FALSE)),"") | AD12: =IF(AF12 = 1, VLOOKUP(TRIM(AI12), gemSupplier, 2, FALSE), IF(AF12 = 2, VLOOKUP(TRIM(AI12), nasccSupplier, 2, FALSE), IF(AF12 = 2.1, VLOOKUP(TRIM(AI12), nasccSupplier, 2, FALSE), IF(AF12 = 2.2, VLOOKUP(TRIM(AI12), nasccSupplier, 2, FALSE), IF(AF12 = 3, VLOOKUP(TRIM(AI12), euemSupplier, 2, FALSE), IF(AF12 = 4, VLOOKUP(TRIM(AI12), wgtssSupplier, 2, FALSE), IF(AF12 = 5, VLOOKUP(TRIM(AI12), wgtmSupplier, 2, FALSE), IF(AF12 = 7, VLOOKUP(TRIM(AI12), asmSupplier, 2, FALSE), "")))))))) | AF12: =IF(C12 <> "", VLOOKUP(C12, seriesClasses, 2, FALSE), 0) -> 0 | AG12: =IF(AI12 <> "", VLOOKUP(AI12, classIndexes, 2, FALSE), 0) -> 0 | AH12: =IF(AF12 = 0, "", IF(AF12 = 1, VLOOKUP(I12, gemClasses, 2, FALSE), IF(AF12 = 2, VLOOKUP(I12, nasccClasses, 2, FALSE), IF(AF12 = 2.1, VLOOKUP(I12, nasccClasses, 2, FALSE), IF(AF12 = 2.2, VLOOKUP(I12, nasccClasses, 2, FALSE), IF(AF12 = 3, VLOOKUP(I12, euemClasses, 2, FALSE), IF(AF12 = 4, VLOOKUP(I12, wgtssClasses, 2, FALSE), IF(AF12 = 5, VLOOKUP(I12, wgtmClasses, 2, FALSE), IF(AF12 = 6, VLOOKUP(I12, wpcClasses, 2, FALSE), IF(AF12 = 7, VLOOKUP(I12, asmClasses, 2, FALSE), "")))))))))) | AI12: =IF(AF12 = 1, AK12, IF(AF12 = 5, AL12, AH12)) | AK12: =IF(AND(IF(AH12 = "LMGTE PRO", TRUE, FALSE), IF(M12 = "Bronze", TRUE, FALSE)), "LMGTE AM", AH12) | AL12: =IF(AND(IF(AH12 = "GT3-P", TRUE, FALSE), IF(M12 = "Bronze", TRUE, FALSE)), "GT3-A", AH12) | AN12: ='Lineup Legality - FS'!L29 | AP12: =IF(H12 <> "", CONCATENATE("$", ROUND(SUM('Total Costs'!M11:V11), 3), " Million"), "")
B13: =IF(C13 <> "", B12 + 1, "") | D13: =IF(ISERROR(AI13), "", AI13) | G13: =IF(ISERROR(AD13), "", IF(AD13 = 0, "", AD13)) | I13: =IF(ISERROR(AA13), "", AA13) | J13: =IF(ISERROR(AB13), "", AB13) | O13: =IF(ISERROR(AN13), "", AN13) | U13: =IF(ISERROR(AP13), "", AP13) | AA13: =IF(H13 <> "", IF(VLOOKUP(H13, purchasedCars, 2, FALSE) = "", "", VLOOKUP(H13, purchasedCars, 2, FALSE)),"") | AB13: =IF(H13 <> "", IF(VLOOKUP(H13, purchasedCars, 3, FALSE) = "", "", VLOOKUP(H13, purchasedCars, 3, FALSE)),"") | AD13: =IF(AF13 = 1, VLOOKUP(TRIM(AI13), gemSupplier, 2, FALSE), IF(AF13 = 2, VLOOKUP(TRIM(AI13), nasccSupplier, 2, FALSE), IF(AF13 = 2.1, VLOOKUP(TRIM(AI13), nasccSupplier, 2, FALSE), IF(AF13 = 2.2, VLOOKUP(TRIM(AI13), nasccSupplier, 2, FALSE), IF(AF13 = 3, VLOOKUP(TRIM(AI13), euemSupplier, 2, FALSE), IF(AF13 = 4, VLOOKUP(TRIM(AI13), wgtssSupplier, 2, FALSE), IF(AF13 = 5, VLOOKUP(TRIM(AI13), wgtmSupplier, 2, FALSE), IF(AF13 = 7, VLOOKUP(TRIM(AI13), asmSupplier, 2, FALSE), "")))))))) | AF13: =IF(C13 <> "", VLOOKUP(C13, seriesClasses, 2, FALSE), 0) -> 0 | AG13: =IF(AI13 <> "", VLOOKUP(AI13, classIndexes, 2, FALSE), 0) -> 0 | AH13: =IF(AF13 = 0, "", IF(AF13 = 1, VLOOKUP(I13, gemClasses, 2, FALSE), IF(AF13 = 2, VLOOKUP(I13, nasccClasses, 2, FALSE), IF(AF13 = 2.1, VLOOKUP(I13, nasccClasses, 2, FALSE), IF(AF13 = 2.2, VLOOKUP(I13, nasccClasses, 2, FALSE), IF(AF13 = 3, VLOOKUP(I13, euemClasses, 2, FALSE), IF(AF13 = 4, VLOOKUP(I13, wgtssClasses, 2, FALSE), IF(AF13 = 5, VLOOKUP(I13, wgtmClasses, 2, FALSE), IF(AF13 = 6, VLOOKUP(I13, wpcClasses, 2, FALSE), IF(AF13 = 7, VLOOKUP(I13, asmClasses, 2, FALSE), "")))))))))) | AI13: =IF(AF13 = 1, AK13, IF(AF13 = 5, AL13, AH13)) | AK13: =IF(AND(IF(AH13 = "LMGTE PRO", TRUE, FALSE), IF(M13 = "Bronze", TRUE, FALSE)), "LMGTE AM", AH13) | AL13: =IF(AND(IF(AH13 = "GT3-P", TRUE, FALSE), IF(M13 = "Bronze", TRUE, FALSE)), "GT3-A", AH13) | AN13: ='Lineup Legality - FS'!L33 | AP13: =IF(H13 <> "", CONCATENATE("$", ROUND(SUM('Total Costs'!M12:V12), 3), " Million"), "")
B14: =IF(C14 <> "", B13 + 1, "") | D14: =IF(ISERROR(AI14), "", AI14) | G14: =IF(ISERROR(AD14), "", IF(AD14 = 0, "", AD14)) | I14: =IF(ISERROR(AA14), "", AA14) | J14: =IF(ISERROR(AB14), "", AB14) | O14: =IF(ISERROR(AN14), "", AN14) | U14: =IF(ISERROR(AP14), "", AP14) | AA14: =IF(H14 <> "", IF(VLOOKUP(H14, purchasedCars, 2, FALSE) = "", "", VLOOKUP(H14, purchasedCars, 2, FALSE)),"") | AB14: =IF(H14 <> "", IF(VLOOKUP(H14, purchasedCars, 3, FALSE) = "", "", VLOOKUP(H14, purchasedCars, 3, FALSE)),"") | AD14: =IF(AF14 = 1, VLOOKUP(TRIM(AI14), gemSupplier, 2, FALSE), IF(AF14 = 2, VLOOKUP(TRIM(AI14), nasccSupplier, 2, FALSE), IF(AF14 = 2.1, VLOOKUP(TRIM(AI14), nasccSupplier, 2, FALSE), IF(AF14 = 2.2, VLOOKUP(TRIM(AI14), nasccSupplier, 2, FALSE), IF(AF14 = 3, VLOOKUP(TRIM(AI14), euemSupplier, 2, FALSE), IF(AF14 = 4, VLOOKUP(TRIM(AI14), wgtssSupplier, 2, FALSE), IF(AF14 = 5, VLOOKUP(TRIM(AI14), wgtmSupplier, 2, FALSE), IF(AF14 = 7, VLOOKUP(TRIM(AI14), asmSupplier, 2, FALSE), "")))))))) | AF14: =IF(C14 <> "", VLOOKUP(C14, seriesClasses, 2, FALSE), 0) -> 0 | AG14: =IF(AI14 <> "", VLOOKUP(AI14, classIndexes, 2, FALSE), 0) -> 0 | AH14: =IF(AF14 = 0, "", IF(AF14 = 1, VLOOKUP(I14, gemClasses, 2, FALSE), IF(AF14 = 2, VLOOKUP(I14, nasccClasses, 2, FALSE), IF(AF14 = 2.1, VLOOKUP(I14, nasccClasses, 2, FALSE), IF(AF14 = 2.2, VLOOKUP(I14, nasccClasses, 2, FALSE), IF(AF14 = 3, VLOOKUP(I14, euemClasses, 2, FALSE), IF(AF14 = 4, VLOOKUP(I14, wgtssClasses, 2, FALSE), IF(AF14 = 5, VLOOKUP(I14, wgtmClasses, 2, FALSE), IF(AF14 = 6, VLOOKUP(I14, wpcClasses, 2, FALSE), IF(AF14 = 7, VLOOKUP(I14, asmClasses, 2, FALSE), "")))))))))) | AI14: =IF(AF14 = 1, AK14, IF(AF14 = 5, AL14, AH14)) | AK14: =IF(AND(IF(AH14 = "LMGTE PRO", TRUE, FALSE), IF(M14 = "Bronze", TRUE, FALSE)), "LMGTE AM", AH14) | AL14: =IF(AND(IF(AH14 = "GT3-P", TRUE, FALSE), IF(M14 = "Bronze", TRUE, FALSE)), "GT3-A", AH14) | AN14: ='Lineup Legality - FS'!L37 | AP14: =IF(H14 <> "", CONCATENATE("$", ROUND(SUM('Total Costs'!M13:V13), 3), " Million"), "")
B15: =IF(C15 <> "", B14 + 1, "") | D15: =IF(ISERROR(AI15), "", AI15) | G15: =IF(ISERROR(AD15), "", IF(AD15 = 0, "", AD15)) | I15: =IF(ISERROR(AA15), "", AA15) | J15: =IF(ISERROR(AB15), "", AB15) | O15: =IF(ISERROR(AN15), "", AN15) | U15: =IF(ISERROR(AP15), "", AP15) | X15: Please Enter Setup Bonus Areas as their names listed in 'Setup Bonuses' | AA15: =IF(H15 <> "", IF(VLOOKUP(H15, purchasedCars, 2, FALSE) = "", "", VLOOKUP(H15, purchasedCars, 2, FALSE)),"") | AB15: =IF(H15 <> "", IF(VLOOKUP(H15, purchasedCars, 3, FALSE) = "", "", VLOOKUP(H15, purchasedCars, 3, FALSE)),"") | AD15: =IF(AF15 = 1, VLOOKUP(TRIM(AI15), gemSupplier, 2, FALSE), IF(AF15 = 2, VLOOKUP(TRIM(AI15), nasccSupplier, 2, FALSE), IF(AF15 = 2.1, VLOOKUP(TRIM(AI15), nasccSupplier, 2, FALSE), IF(AF15 = 2.2, VLOOKUP(TRIM(AI15), nasccSupplier, 2, FALSE), IF(AF15 = 3, VLOOKUP(TRIM(AI15), euemSupplier, 2, FALSE), IF(AF15 = 4, VLOOKUP(TRIM(AI15), wgtssSupplier, 2, FALSE), IF(AF15 = 5, VLOOKUP(TRIM(AI15), wgtmSupplier, 2, FALSE), IF(AF15 = 7, VLOOKUP(TRIM(AI15), asmSupplier, 2, FALSE), "")))))))) | AF15: =IF(C15 <> "", VLOOKUP(C15, seriesClasses, 2, FALSE), 0) -> 0 | AG15: =IF(AI15 <> "", VLOOKUP(AI15, classIndexes, 2, FALSE), 0) -> 0 | AH15: =IF(AF15 = 0, "", IF(AF15 = 1, VLOOKUP(I15, gemClasses, 2, FALSE), IF(AF15 = 2, VLOOKUP(I15, nasccClasses, 2, FALSE), IF(AF15 = 2.1, VLOOKUP(I15, nasccClasses, 2, FALSE), IF(AF15 = 2.2, VLOOKUP(I15, nasccClasses, 2, FALSE), IF(AF15 = 3, VLOOKUP(I15, euemClasses, 2, FALSE), IF(AF15 = 4, VLOOKUP(I15, wgtssClasses, 2, FALSE), IF(AF15 = 5, VLOOKUP(I15, wgtmClasses, 2, FALSE), IF(AF15 = 6, VLOOKUP(I15, wpcClasses, 2, FALSE), IF(AF15 = 7, VLOOKUP(I15, asmClasses, 2, FALSE), "")))))))))) | AI15: =IF(AF15 = 1, AK15, IF(AF15 = 5, AL15, AH15)) | AK15: =IF(AND(IF(AH15 = "LMGTE PRO", TRUE, FALSE), IF(M15 = "Bronze", TRUE, FALSE)), "LMGTE AM", AH15) | AL15: =IF(AND(IF(AH15 = "GT3-P", TRUE, FALSE), IF(M15 = "Bronze", TRUE, FALSE)), "GT3-A", AH15) | AN15: ='Lineup Legality - FS'!L41 | AP15: =IF(H15 <> "", CONCATENATE("$", ROUND(SUM('Total Costs'!M14:V14), 3), " Million"), "")
B16: =IF(C16 <> "", B15 + 1, "") | D16: =IF(ISERROR(AI16), "", AI16) | G16: =IF(ISERROR(AD16), "", IF(AD16 = 0, "", AD16)) | I16: =IF(ISERROR(AA16), "", AA16) | J16: =IF(ISERROR(AB16), "", AB16) | O16: =IF(ISERROR(AN16), "", AN16) | U16: =IF(ISERROR(AP16), "", AP16) | AA16: =IF(H16 <> "", IF(VLOOKUP(H16, purchasedCars, 2, FALSE) = "", "", VLOOKUP(H16, purchasedCars, 2, FALSE)),"") | AB16: =IF(H16 <> "", IF(VLOOKUP(H16, purchasedCars, 3, FALSE) = "", "", VLOOKUP(H16, purchasedCars, 3, FALSE)),"") | AD16: =IF(AF16 = 1, VLOOKUP(TRIM(AI16), gemSupplier, 2, FALSE), IF(AF16 = 2, VLOOKUP(TRIM(AI16), nasccSupplier, 2, FALSE), IF(AF16 = 2.1, VLOOKUP(TRIM(AI16), nasccSupplier, 2, FALSE), IF(AF16 = 2.2, VLOOKUP(TRIM(AI16), nasccSupplier, 2, FALSE), IF(AF16 = 3, VLOOKUP(TRIM(AI16), euemSupplier, 2, FALSE), IF(AF16 = 4, VLOOKUP(TRIM(AI16), wgtssSupplier, 2, FALSE), IF(AF16 = 5, VLOOKUP(TRIM(AI16), wgtmSupplier, 2, FALSE), IF(AF16 = 7, VLOOKUP(TRIM(AI16), asmSupplier, 2, FALSE), "")))))))) | AF16: =IF(C16 <> "", VLOOKUP(C16, seriesClasses, 2, FALSE), 0) -> 0 | AG16: =IF(AI16 <> "", VLOOKUP(AI16, classIndexes, 2, FALSE), 0) -> 0 | AH16: =IF(AF16 = 0, "", IF(AF16 = 1, VLOOKUP(I16, gemClasses, 2, FALSE), IF(AF16 = 2, VLOOKUP(I16, nasccClasses, 2, FALSE), IF(AF16 = 2.1, VLOOKUP(I16, nasccClasses, 2, FALSE), IF(AF16 = 2.2, VLOOKUP(I16, nasccClasses, 2, FALSE), IF(AF16 = 3, VLOOKUP(I16, euemClasses, 2, FALSE), IF(AF16 = 4, VLOOKUP(I16, wgtssClasses, 2, FALSE), IF(AF16 = 5, VLOOKUP(I16, wgtmClasses, 2, FALSE), IF(AF16 = 6, VLOOKUP(I16, wpcClasses, 2, FALSE), IF(AF16 = 7, VLOOKUP(I16, asmClasses, 2, FALSE), "")))))))))) | AI16: =IF(AF16 = 1, AK16, IF(AF16 = 5, AL16, AH16)) | AK16: =IF(AND(IF(AH16 = "LMGTE PRO", TRUE, FALSE), IF(M16 = "Bronze", TRUE, FALSE)), "LMGTE AM", AH16) | AL16: =IF(AND(IF(AH16 = "GT3-P", TRUE, FALSE), IF(M16 = "Bronze", TRUE, FALSE)), "GT3-A", AH16) | AN16: ='Lineup Legality - FS'!L45 | AP16: =IF(H16 <> "", CONCATENATE("$", ROUND(SUM('Total Costs'!M15:V15), 3), " Million"), "")
B17: =IF(C17 <> "", B16 + 1, "") | D17: =IF(ISERROR(AI17), "", AI17) | G17: =IF(ISERROR(AD17), "", IF(AD17 = 0, "", AD17)) | I17: =IF(ISERROR(AA17), "", AA17) | J17: =IF(ISERROR(AB17), "", AB17) | O17: =IF(ISERROR(AN17), "", AN17) | U17: =IF(ISERROR(AP17), "", AP17) | X17: Enter Bonus Levels as "LX", where X is the Level Number (ie L2 for Level 2) | AA17: =IF(H17 <> "", IF(VLOOKUP(H17, purchasedCars, 2, FALSE) = "", "", VLOOKUP(H17, purchasedCars, 2, FALSE)),"") | AB17: =IF(H17 <> "", IF(VLOOKUP(H17, purchasedCars, 3, FALSE) = "", "", VLOOKUP(H17, purchasedCars, 3, FALSE)),"") | AD17: =IF(AF17 = 1, VLOOKUP(TRIM(AI17), gemSupplier, 2, FALSE), IF(AF17 = 2, VLOOKUP(TRIM(AI17), nasccSupplier, 2, FALSE), IF(AF17 = 2.1, VLOOKUP(TRIM(AI17), nasccSupplier, 2, FALSE), IF(AF17 = 2.2, VLOOKUP(TRIM(AI17), nasccSupplier, 2, FALSE), IF(AF17 = 3, VLOOKUP(TRIM(AI17), euemSupplier, 2, FALSE), IF(AF17 = 4, VLOOKUP(TRIM(AI17), wgtssSupplier, 2, FALSE), IF(AF17 = 5, VLOOKUP(TRIM(AI17), wgtmSupplier, 2, FALSE), IF(AF17 = 7, VLOOKUP(TRIM(AI17), asmSupplier, 2, FALSE), "")))))))) | AF17: =IF(C17 <> "", VLOOKUP(C17, seriesClasses, 2, FALSE), 0) -> 0 | AG17: =IF(AI17 <> "", VLOOKUP(AI17, classIndexes, 2, FALSE), 0) -> 0 | AH17: =IF(AF17 = 0, "", IF(AF17 = 1, VLOOKUP(I17, gemClasses, 2, FALSE), IF(AF17 = 2, VLOOKUP(I17, nasccClasses, 2, FALSE), IF(AF17 = 2.1, VLOOKUP(I17, nasccClasses, 2, FALSE), IF(AF17 = 2.2, VLOOKUP(I17, nasccClasses, 2, FALSE), IF(AF17 = 3, VLOOKUP(I17, euemClasses, 2, FALSE), IF(AF17 = 4, VLOOKUP(I17, wgtssClasses, 2, FALSE), IF(AF17 = 5, VLOOKUP(I17, wgtmClasses, 2, FALSE), IF(AF17 = 6, VLOOKUP(I17, wpcClasses, 2, FALSE), IF(AF17 = 7, VLOOKUP(I17, asmClasses, 2, FALSE), "")))))))))) | AI17: =IF(AF17 = 1, AK17, IF(AF17 = 5, AL17, AH17)) | AK17: =IF(AND(IF(AH17 = "LMGTE PRO", TRUE, FALSE), IF(M17 = "Bronze", TRUE, FALSE)), "LMGTE AM", AH17) | AL17: =IF(AND(IF(AH17 = "GT3-P", TRUE, FALSE), IF(M17 = "Bronze", TRUE, FALSE)), "GT3-A", AH17) | AN17: ='Lineup Legality - FS'!L49 | AP17: =IF(H17 <> "", CONCATENATE("$", ROUND(SUM('Total Costs'!M16:V16), 3), " Million"), "")
B18: =IF(C18 <> "", B17 + 1, "") | D18: =IF(ISERROR(AI18), "", AI18) | G18: =IF(ISERROR(AD18), "", IF(AD18 = 0, "", AD18)) | I18: =IF(ISERROR(AA18), "", AA18) | J18: =IF(ISERROR(AB18), "", AB18) | O18: =IF(ISERROR(AN18), "", AN18) | U18: =IF(ISERROR(AP18), "", AP18) | AA18: =IF(H18 <> "", IF(VLOOKUP(H18, purchasedCars, 2, FALSE) = "", "", VLOOKUP(H18, purchasedCars, 2, FALSE)),"") | AB18: =IF(H18 <> "", IF(VLOOKUP(H18, purchasedCars, 3, FALSE) = "", "", VLOOKUP(H18, purchasedCars, 3, FALSE)),"") | AD18: =IF(AF18 = 1, VLOOKUP(TRIM(AI18), gemSupplier, 2, FALSE), IF(AF18 = 2, VLOOKUP(TRIM(AI18), nasccSupplier, 2, FALSE), IF(AF18 = 2.1, VLOOKUP(TRIM(AI18), nasccSupplier, 2, FALSE), IF(AF18 = 2.2, VLOOKUP(TRIM(AI18), nasccSupplier, 2, FALSE), IF(AF18 = 3, VLOOKUP(TRIM(AI18), euemSupplier, 2, FALSE), IF(AF18 = 4, VLOOKUP(TRIM(AI18), wgtssSupplier, 2, FALSE), IF(AF18 = 5, VLOOKUP(TRIM(AI18), wgtmSupplier, 2, FALSE), IF(AF18 = 7, VLOOKUP(TRIM(AI18), asmSupplier, 2, FALSE), "")))))))) | AF18: =IF(C18 <> "", VLOOKUP(C18, seriesClasses, 2, FALSE), 0) -> 0 | AG18: =IF(AI18 <> "", VLOOKUP(AI18, classIndexes, 2, FALSE), 0) -> 0 | AH18: =IF(AF18 = 0, "", IF(AF18 = 1, VLOOKUP(I18, gemClasses, 2, FALSE), IF(AF18 = 2, VLOOKUP(I18, nasccClasses, 2, FALSE), IF(AF18 = 2.1, VLOOKUP(I18, nasccClasses, 2, FALSE), IF(AF18 = 2.2, VLOOKUP(I18, nasccClasses, 2, FALSE), IF(AF18 = 3, VLOOKUP(I18, euemClasses, 2, FALSE), IF(AF18 = 4, VLOOKUP(I18, wgtssClasses, 2, FALSE), IF(AF18 = 5, VLOOKUP(I18, wgtmClasses, 2, FALSE), IF(AF18 = 6, VLOOKUP(I18, wpcClasses, 2, FALSE), IF(AF18 = 7, VLOOKUP(I18, asmClasses, 2, FALSE), "")))))))))) | AI18: =IF(AF18 = 1, AK18, IF(AF18 = 5, AL18, AH18)) | AK18: =IF(AND(IF(AH18 = "LMGTE PRO", TRUE, FALSE), IF(M18 = "Bronze", TRUE, FALSE)), "LMGTE AM", AH18) | AL18: =IF(AND(IF(AH18 = "GT3-P", TRUE, FALSE), IF(M18 = "Bronze", TRUE, FALSE)), "GT3-A", AH18) | AN18: ='Lineup Legality - FS'!L53 | AP18: =IF(H18 <> "", CONCATENATE("$", ROUND(SUM('Total Costs'!M17:V17), 3), " Million"), "")
B19: =IF(C19 <> "", B18 + 1, "") | D19: =IF(ISERROR(AI19), "", AI19) | G19: =IF(ISERROR(AD19), "", IF(AD19 = 0, "", AD19)) | I19: =IF(ISERROR(AA19), "", AA19) | J19: =IF(ISERROR(AB19), "", AB19) | O19: =IF(ISERROR(AN19), "", AN19) | U19: =IF(ISERROR(AP19), "", AP19) | X19: Reliability Bonuses must be entered as the full Level Name (ie Level 2) | AA19: =IF(H19 <> "", IF(VLOOKUP(H19, purchasedCars, 2, FALSE) = "", "", VLOOKUP(H19, purchasedCars, 2, FALSE)),"") | AB19: =IF(H19 <> "", IF(VLOOKUP(H19, purchasedCars, 3, FALSE) = "", "", VLOOKUP(H19, purchasedCars, 3, FALSE)),"") | AD19: =IF(AF19 = 1, VLOOKUP(TRIM(AI19), gemSupplier, 2, FALSE), IF(AF19 = 2, VLOOKUP(TRIM(AI19), nasccSupplier, 2, FALSE), IF(AF19 = 2.1, VLOOKUP(TRIM(AI19), nasccSupplier, 2, FALSE), IF(AF19 = 2.2, VLOOKUP(TRIM(AI19), nasccSupplier, 2, FALSE), IF(AF19 = 3, VLOOKUP(TRIM(AI19), euemSupplier, 2, FALSE), IF(AF19 = 4, VLOOKUP(TRIM(AI19), wgtssSupplier, 2, FALSE), IF(AF19 = 5, VLOOKUP(TRIM(AI19), wgtmSupplier, 2, FALSE), IF(AF19 = 7, VLOOKUP(TRIM(AI19), asmSupplier, 2, FALSE), "")))))))) | AF19: =IF(C19 <> "", VLOOKUP(C19, seriesClasses, 2, FALSE), 0) -> 0 | AG19: =IF(AI19 <> "", VLOOKUP(AI19, classIndexes, 2, FALSE), 0) -> 0 | AH19: =IF(AF19 = 0, "", IF(AF19 = 1, VLOOKUP(I19, gemClasses, 2, FALSE), IF(AF19 = 2, VLOOKUP(I19, nasccClasses, 2, FALSE), IF(AF19 = 2.1, VLOOKUP(I19, nasccClasses, 2, FALSE), IF(AF19 = 2.2, VLOOKUP(I19, nasccClasses, 2, FALSE), IF(AF19 = 3, VLOOKUP(I19, euemClasses, 2, FALSE), IF(AF19 = 4, VLOOKUP(I19, wgtssClasses, 2, FALSE), IF(AF19 = 5, VLOOKUP(I19, wgtmClasses, 2, FALSE), IF(AF19 = 6, VLOOKUP(I19, wpcClasses, 2, FALSE), IF(AF19 = 7, VLOOKUP(I19, asmClasses, 2, FALSE), "")))))))))) | AI19: =IF(AF19 = 1, AK19, IF(AF19 = 5, AL19, AH19)) | AK19: =IF(AND(IF(AH19 = "LMGTE PRO", TRUE, FALSE), IF(M19 = "Bronze", TRUE, FALSE)), "LMGTE AM", AH19) | AL19: =IF(AND(IF(AH19 = "GT3-P", TRUE, FALSE), IF(M19 = "Bronze", TRUE, FALSE)), "GT3-A", AH19) | AN19: ='Lineup Legality - FS'!L57 | AP19: =IF(H19 <> "", CONCATENATE("$", ROUND(SUM('Total Costs'!M18:V18), 3), " Million"), "")
B20: =IF(C20 <> "", B19 + 1, "") | D20: =IF(ISERROR(AI20), "", AI20) | G20: =IF(ISERROR(AD20), "", IF(AD20 = 0, "", AD20)) | I20: =IF(ISERROR(AA20), "", AA20) | J20: =IF(ISERROR(AB20), "", AB20) | O20: =IF(ISERROR(AN20), "", AN20) | U20: =IF(ISERROR(AP20), "", AP20) | AA20: =IF(H20 <> "", IF(VLOOKUP(H20, purchasedCars, 2, FALSE) = "", "", VLOOKUP(H20, purchasedCars, 2, FALSE)),"") | AB20: =IF(H20 <> "", IF(VLOOKUP(H20, purchasedCars, 3, FALSE) = "", "", VLOOKUP(H20, purchasedCars, 3, FALSE)),"") | AD20: =IF(AF20 = 1, VLOOKUP(TRIM(AI20), gemSupplier, 2, FALSE), IF(AF20 = 2, VLOOKUP(TRIM(AI20), nasccSupplier, 2, FALSE), IF(AF20 = 2.1, VLOOKUP(TRIM(AI20), nasccSupplier, 2, FALSE), IF(AF20 = 2.2, VLOOKUP(TRIM(AI20), nasccSupplier, 2, FALSE), IF(AF20 = 3, VLOOKUP(TRIM(AI20), euemSupplier, 2, FALSE), IF(AF20 = 4, VLOOKUP(TRIM(AI20), wgtssSupplier, 2, FALSE), IF(AF20 = 5, VLOOKUP(TRIM(AI20), wgtmSupplier, 2, FALSE), IF(AF20 = 7, VLOOKUP(TRIM(AI20), asmSupplier, 2, FALSE), "")))))))) | AF20: =IF(C20 <> "", VLOOKUP(C20, seriesClasses, 2, FALSE), 0) -> 0 | AG20: =IF(AI20 <> "", VLOOKUP(AI20, classIndexes, 2, FALSE), 0) -> 0 | AH20: =IF(AF20 = 0, "", IF(AF20 = 1, VLOOKUP(I20, gemClasses, 2, FALSE), IF(AF20 = 2, VLOOKUP(I20, nasccClasses, 2, FALSE), IF(AF20 = 2.1, VLOOKUP(I20, nasccClasses, 2, FALSE), IF(AF20 = 2.2, VLOOKUP(I20, nasccClasses, 2, FALSE), IF(AF20 = 3, VLOOKUP(I20, euemClasses, 2, FALSE), IF(AF20 = 4, VLOOKUP(I20, wgtssClasses, 2, FALSE), IF(AF20 = 5, VLOOKUP(I20, wgtmClasses, 2, FALSE), IF(AF20 = 6, VLOOKUP(I20, wpcClasses, 2, FALSE), IF(AF20 = 7, VLOOKUP(I20, asmClasses, 2, FALSE), "")))))))))) | AI20: =IF(AF20 = 1, AK20, IF(AF20 = 5, AL20, AH20)) | AK20: =IF(AND(IF(AH20 = "LMGTE PRO", TRUE, FALSE), IF(M20 = "Bronze", TRUE, FALSE)), "LMGTE AM", AH20) | AL20: =IF(AND(IF(AH20 = "GT3-P", TRUE, FALSE), IF(M20 = "Bronze", TRUE, FALSE)), "GT3-A", AH20) | AN20: ='Lineup Legality - FS'!L61 | AP20: =IF(H20 <> "", CONCATENATE("$", ROUND(SUM('Total Costs'!M19:V19), 3), " Million"), "")
B21: =IF(C21 <> "", B20 + 1, "") | D21: =IF(ISERROR(AI21), "", AI21) | G21: =IF(ISERROR(AD21), "", IF(AD21 = 0, "", AD21)) | I21: =IF(ISERROR(AA21), "", AA21) | J21: =IF(ISERROR(AB21), "", AB21) | O21: =IF(ISERROR(AN21), "", AN21) | U21: =IF(ISERROR(AP21), "", AP21) | X21: Entry Costs are Automatically Calculated and displayed | AA21: =IF(H21 <> "", IF(VLOOKUP(H21, purchasedCars, 2, FALSE) = "", "", VLOOKUP(H21, purchasedCars, 2, FALSE)),"") | AB21: =IF(H21 <> "", IF(VLOOKUP(H21, purchasedCars, 3, FALSE) = "", "", VLOOKUP(H21, purchasedCars, 3, FALSE)),"") | AD21: =IF(AF21 = 1, VLOOKUP(TRIM(AI21), gemSupplier, 2, FALSE), IF(AF21 = 2, VLOOKUP(TRIM(AI21), nasccSupplier, 2, FALSE), IF(AF21 = 2.1, VLOOKUP(TRIM(AI21), nasccSupplier, 2, FALSE), IF(AF21 = 2.2, VLOOKUP(TRIM(AI21), nasccSupplier, 2, FALSE), IF(AF21 = 3, VLOOKUP(TRIM(AI21), euemSupplier, 2, FALSE), IF(AF21 = 4, VLOOKUP(TRIM(AI21), wgtssSupplier, 2, FALSE), IF(AF21 = 5, VLOOKUP(TRIM(AI21), wgtmSupplier, 2, FALSE), IF(AF21 = 7, VLOOKUP(TRIM(AI21), asmSupplier, 2, FALSE), "")))))))) | AF21: =IF(C21 <> "", VLOOKUP(C21, seriesClasses, 2, FALSE), 0) -> 0 | AG21: =IF(AI21 <> "", VLOOKUP(AI21, classIndexes, 2, FALSE), 0) -> 0 | AH21: =IF(AF21 = 0, "", IF(AF21 = 1, VLOOKUP(I21, gemClasses, 2, FALSE), IF(AF21 = 2, VLOOKUP(I21, nasccClasses, 2, FALSE), IF(AF21 = 2.1, VLOOKUP(I21, nasccClasses, 2, FALSE), IF(AF21 = 2.2, VLOOKUP(I21, nasccClasses, 2, FALSE), IF(AF21 = 3, VLOOKUP(I21, euemClasses, 2, FALSE), IF(AF21 = 4, VLOOKUP(I21, wgtssClasses, 2, FALSE), IF(AF21 = 5, VLOOKUP(I21, wgtmClasses, 2, FALSE), IF(AF21 = 6, VLOOKUP(I21, wpcClasses, 2, FALSE), IF(AF21 = 7, VLOOKUP(I21, asmClasses, 2, FALSE), "")))))))))) | AI21: =IF(AF21 = 1, AK21, IF(AF21 = 5, AL21, AH21)) | AK21: =IF(AND(IF(AH21 = "LMGTE PRO", TRUE, FALSE), IF(M21 = "Bronze", TRUE, FALSE)), "LMGTE AM", AH21) | AL21: =IF(AND(IF(AH21 = "GT3-P", TRUE, FALSE), IF(M21 = "Bronze", TRUE, FALSE)), "GT3-A", AH21) | AN21: ='Lineup Legality - FS'!L65 | AP21: =IF(H21 <> "", CONCATENATE("$", ROUND(SUM('Total Costs'!M20:V20), 3), " Million"), "")
B22: =IF(C22 <> "", B21 + 1, "") | D22: =IF(ISERROR(AI22), "", AI22) | G22: =IF(ISERROR(AD22), "", IF(AD22 = 0, "", AD22)) | I22: =IF(ISERROR(AA22), "", AA22) | J22: =IF(ISERROR(AB22), "", AB22) | O22: =IF(ISERROR(AN22), "", AN22) | U22: =IF(ISERROR(AP22), "", AP22) | AA22: =IF(H22 <> "", IF(VLOOKUP(H22, purchasedCars, 2, FALSE) = "", "", VLOOKUP(H22, purchasedCars, 2, FALSE)),"") | AB22: =IF(H22 <> "", IF(VLOOKUP(H22, purchasedCars, 3, FALSE) = "", "", VLOOKUP(H22, purchasedCars, 3, FALSE)),"") | AD22: =IF(AF22 = 1, VLOOKUP(TRIM(AI22), gemSupplier, 2, FALSE), IF(AF22 = 2, VLOOKUP(TRIM(AI22), nasccSupplier, 2, FALSE), IF(AF22 = 2.1, VLOOKUP(TRIM(AI22), nasccSupplier, 2, FALSE), IF(AF22 = 2.2, VLOOKUP(TRIM(AI22), nasccSupplier, 2, FALSE), IF(AF22 = 3, VLOOKUP(TRIM(AI22), euemSupplier, 2, FALSE), IF(AF22 = 4, VLOOKUP(TRIM(AI22), wgtssSupplier, 2, FALSE), IF(AF22 = 5, VLOOKUP(TRIM(AI22), wgtmSupplier, 2, FALSE), IF(AF22 = 7, VLOOKUP(TRIM(AI22), asmSupplier, 2, FALSE), "")))))))) | AF22: =IF(C22 <> "", VLOOKUP(C22, seriesClasses, 2, FALSE), 0) -> 0 | AG22: =IF(AI22 <> "", VLOOKUP(AI22, classIndexes, 2, FALSE), 0) -> 0 | AH22: =IF(AF22 = 0, "", IF(AF22 = 1, VLOOKUP(I22, gemClasses, 2, FALSE), IF(AF22 = 2, VLOOKUP(I22, nasccClasses, 2, FALSE), IF(AF22 = 2.1, VLOOKUP(I22, nasccClasses, 2, FALSE), IF(AF22 = 2.2, VLOOKUP(I22, nasccClasses, 2, FALSE), IF(AF22 = 3, VLOOKUP(I22, euemClasses, 2, FALSE), IF(AF22 = 4, VLOOKUP(I22, wgtssClasses, 2, FALSE), IF(AF22 = 5, VLOOKUP(I22, wgtmClasses, 2, FALSE), IF(AF22 = 6, VLOOKUP(I22, wpcClasses, 2, FALSE), IF(AF22 = 7, VLOOKUP(I22, asmClasses, 2, FALSE), "")))))))))) | AI22: =IF(AF22 = 1, AK22, IF(AF22 = 5, AL22, AH22)) | AK22: =IF(AND(IF(AH22 = "LMGTE PRO", TRUE, FALSE), IF(M22 = "Bronze", TRUE, FALSE)), "LMGTE AM", AH22) | AL22: =IF(AND(IF(AH22 = "GT3-P", TRUE, FALSE), IF(M22 = "Bronze", TRUE, FALSE)), "GT3-A", AH22) | AN22: ='Lineup Legality - FS'!L69 | AP22: =IF(H22 <> "", CONCATENATE("$", ROUND(SUM('Total Costs'!M21:V21), 3), " Million"), "")
B23: =IF(C23 <> "", B22 + 1, "") | D23: =IF(ISERROR(AI23), "", AI23) | G23: =IF(ISERROR(AD23), "", IF(AD23 = 0, "", AD23)) | I23: =IF(ISERROR(AA23), "", AA23) | J23: =IF(ISERROR(AB23), "", AB23) | O23: =IF(ISERROR(AN23), "", AN23) | U23: =IF(ISERROR(AP23), "", AP23) | AA23: =IF(H23 <> "", IF(VLOOKUP(H23, purchasedCars, 2, FALSE) = "", "", VLOOKUP(H23, purchasedCars, 2, FALSE)),"") | AB23: =IF(H23 <> "", IF(VLOOKUP(H23, purchasedCars, 3, FALSE) = "", "", VLOOKUP(H23, purchasedCars, 3, FALSE)),"") | AD23: =IF(AF23 = 1, VLOOKUP(TRIM(AI23), gemSupplier, 2, FALSE), IF(AF23 = 2, VLOOKUP(TRIM(AI23), nasccSupplier, 2, FALSE), IF(AF23 = 2.1, VLOOKUP(TRIM(AI23), nasccSupplier, 2, FALSE), IF(AF23 = 2.2, VLOOKUP(TRIM(AI23), nasccSupplier, 2, FALSE), IF(AF23 = 3, VLOOKUP(TRIM(AI23), euemSupplier, 2, FALSE), IF(AF23 = 4, VLOOKUP(TRIM(AI23), wgtssSupplier, 2, FALSE), IF(AF23 = 5, VLOOKUP(TRIM(AI23), wgtmSupplier, 2, FALSE), IF(AF23 = 7, VLOOKUP(TRIM(AI23), asmSupplier, 2, FALSE), "")))))))) | AF23: =IF(C23 <> "", VLOOKUP(C23, seriesClasses, 2, FALSE), 0) -> 0 | AG23: =IF(AI23 <> "", VLOOKUP(AI23, classIndexes, 2, FALSE), 0) -> 0 | AH23: =IF(AF23 = 0, "", IF(AF23 = 1, VLOOKUP(I23, gemClasses, 2, FALSE), IF(AF23 = 2, VLOOKUP(I23, nasccClasses, 2, FALSE), IF(AF23 = 2.1, VLOOKUP(I23, nasccClasses, 2, FALSE), IF(AF23 = 2.2, VLOOKUP(I23, nasccClasses, 2, FALSE), IF(AF23 = 3, VLOOKUP(I23, euemClasses, 2, FALSE), IF(AF23 = 4, VLOOKUP(I23, wgtssClasses, 2, FALSE), IF(AF23 = 5, VLOOKUP(I23, wgtmClasses, 2, FALSE), IF(AF23 = 6, VLOOKUP(I23, wpcClasses, 2, FALSE), IF(AF23 = 7, VLOOKUP(I23, asmClasses, 2, FALSE), "")))))))))) | AI23: =IF(AF23 = 1, AK23, IF(AF23 = 5, AL23, AH23)) | AK23: =IF(AND(IF(AH23 = "LMGTE PRO", TRUE, FALSE), IF(M23 = "Bronze", TRUE, FALSE)), "LMGTE AM", AH23) | AL23: =IF(AND(IF(AH23 = "GT3-P", TRUE, FALSE), IF(M23 = "Bronze", TRUE, FALSE)), "GT3-A", AH23) | AN23: ='Lineup Legality - FS'!L73 | AP23: =IF(H23 <> "", CONCATENATE("$", ROUND(SUM('Total Costs'!M22:V22), 3), " Million"), "")
B24: =IF(C24 <> "", B23 + 1, "") | D24: =IF(ISERROR(AI24), "", AI24) | G24: =IF(ISERROR(AD24), "", IF(AD24 = 0, "", AD24)) | I24: =IF(ISERROR(AA24), "", AA24) | J24: =IF(ISERROR(AB24), "", AB24) | O24: =IF(ISERROR(AN24), "", AN24) | U24: =IF(ISERROR(AP24), "", AP24) | AA24: =IF(H24 <> "", IF(VLOOKUP(H24, purchasedCars, 2, FALSE) = "", "", VLOOKUP(H24, purchasedCars, 2, FALSE)),"") | AB24: =IF(H24 <> "", IF(VLOOKUP(H24, purchasedCars, 3, FALSE) = "", "", VLOOKUP(H24, purchasedCars, 3, FALSE)),"") | AD24: =IF(AF24 = 1, VLOOKUP(TRIM(AI24), gemSupplier, 2, FALSE), IF(AF24 = 2, VLOOKUP(TRIM(AI24), nasccSupplier, 2, FALSE), IF(AF24 = 2.1, VLOOKUP(TRIM(AI24), nasccSupplier, 2, FALSE), IF(AF24 = 2.2, VLOOKUP(TRIM(AI24), nasccSupplier, 2, FALSE), IF(AF24 = 3, VLOOKUP(TRIM(AI24), euemSupplier, 2, FALSE), IF(AF24 = 4, VLOOKUP(TRIM(AI24), wgtssSupplier, 2, FALSE), IF(AF24 = 5, VLOOKUP(TRIM(AI24), wgtmSupplier, 2, FALSE), IF(AF24 = 7, VLOOKUP(TRIM(AI24), asmSupplier, 2, FALSE), "")))))))) | AF24: =IF(C24 <> "", VLOOKUP(C24, seriesClasses, 2, FALSE), 0) -> 0 | AG24: =IF(AI24 <> "", VLOOKUP(AI24, classIndexes, 2, FALSE), 0) -> 0 | AH24: =IF(AF24 = 0, "", IF(AF24 = 1, VLOOKUP(I24, gemClasses, 2, FALSE), IF(AF24 = 2, VLOOKUP(I24, nasccClasses, 2, FALSE), IF(AF24 = 2.1, VLOOKUP(I24, nasccClasses, 2, FALSE), IF(AF24 = 2.2, VLOOKUP(I24, nasccClasses, 2, FALSE), IF(AF24 = 3, VLOOKUP(I24, euemClasses, 2, FALSE), IF(AF24 = 4, VLOOKUP(I24, wgtssClasses, 2, FALSE), IF(AF24 = 5, VLOOKUP(I24, wgtmClasses, 2, FALSE), IF(AF24 = 6, VLOOKUP(I24, wpcClasses, 2, FALSE), IF(AF24 = 7, VLOOKUP(I24, asmClasses, 2, FALSE), "")))))))))) | AI24: =IF(AF24 = 1, AK24, IF(AF24 = 5, AL24, AH24)) | AK24: =IF(AND(IF(AH24 = "LMGTE PRO", TRUE, FALSE), IF(M24 = "Bronze", TRUE, FALSE)), "LMGTE AM", AH24) | AL24: =IF(AND(IF(AH24 = "GT3-P", TRUE, FALSE), IF(M24 = "Bronze", TRUE, FALSE)), "GT3-A", AH24) | AN24: ='Lineup Legality - FS'!L77 | AP24: =IF(H24 <> "", CONCATENATE("$", ROUND(SUM('Total Costs'!M23:V23), 3), " Million"), "")
B25: =IF(C25 <> "", B24 + 1, "") | D25: =IF(ISERROR(AI25), "", AI25) | G25: =IF(ISERROR(AD25), "", IF(AD25 = 0, "", AD25)) | I25: =IF(ISERROR(AA25), "", AA25) | J25: =IF(ISERROR(AB25), "", AB25) | O25: =IF(ISERROR(AN25), "", AN25) | U25: =IF(ISERROR(AP25), "", AP25) | AA25: =IF(H25 <> "", IF(VLOOKUP(H25, purchasedCars, 2, FALSE) = "", "", VLOOKUP(H25, purchasedCars, 2, FALSE)),"") | AB25: =IF(H25 <> "", IF(VLOOKUP(H25, purchasedCars, 3, FALSE) = "", "", VLOOKUP(H25, purchasedCars, 3, FALSE)),"") | AD25: =IF(AF25 = 1, VLOOKUP(TRIM(AI25), gemSupplier, 2, FALSE), IF(AF25 = 2, VLOOKUP(TRIM(AI25), nasccSupplier, 2, FALSE), IF(AF25 = 2.1, VLOOKUP(TRIM(AI25), nasccSupplier, 2, FALSE), IF(AF25 = 2.2, VLOOKUP(TRIM(AI25), nasccSupplier, 2, FALSE), IF(AF25 = 3, VLOOKUP(TRIM(AI25), euemSupplier, 2, FALSE), IF(AF25 = 4, VLOOKUP(TRIM(AI25), wgtssSupplier, 2, FALSE), IF(AF25 = 5, VLOOKUP(TRIM(AI25), wgtmSupplier, 2, FALSE), IF(AF25 = 7, VLOOKUP(TRIM(AI25), asmSupplier, 2, FALSE), "")))))))) | AF25: =IF(C25 <> "", VLOOKUP(C25, seriesClasses, 2, FALSE), 0) -> 0 | AG25: =IF(AI25 <> "", VLOOKUP(AI25, classIndexes, 2, FALSE), 0) -> 0 | AH25: =IF(AF25 = 0, "", IF(AF25 = 1, VLOOKUP(I25, gemClasses, 2, FALSE), IF(AF25 = 2, VLOOKUP(I25, nasccClasses, 2, FALSE), IF(AF25 = 2.1, VLOOKUP(I25, nasccClasses, 2, FALSE), IF(AF25 = 2.2, VLOOKUP(I25, nasccClasses, 2, FALSE), IF(AF25 = 3, VLOOKUP(I25, euemClasses, 2, FALSE), IF(AF25 = 4, VLOOKUP(I25, wgtssClasses, 2, FALSE), IF(AF25 = 5, VLOOKUP(I25, wgtmClasses, 2, FALSE), IF(AF25 = 6, VLOOKUP(I25, wpcClasses, 2, FALSE), IF(AF25 = 7, VLOOKUP(I25, asmClasses, 2, FALSE), "")))))))))) | AI25: =IF(AF25 = 1, AK25, IF(AF25 = 5, AL25, AH25)) | AK25: =IF(AND(IF(AH25 = "LMGTE PRO", TRUE, FALSE), IF(M25 = "Bronze", TRUE, FALSE)), "LMGTE AM", AH25) | AL25: =IF(AND(IF(AH25 = "GT3-P", TRUE, FALSE), IF(M25 = "Bronze", TRUE, FALSE)), "GT3-A", AH25) | AN25: ='Lineup Legality - FS'!L81 | AP25: =IF(H25 <> "", CONCATENATE("$", ROUND(SUM('Total Costs'!M24:V24), 3), " Million"), "")
B26: =IF(C26 <> "", B25 + 1, "") | D26: =IF(ISERROR(AI26), "", AI26) | G26: =IF(ISERROR(AD26), "", IF(AD26 = 0, "", AD26)) | I26: =IF(ISERROR(AA26), "", AA26) | J26: =IF(ISERROR(AB26), "", AB26) | O26: =IF(ISERROR(AN26), "", AN26) | U26: =IF(ISERROR(AP26), "", AP26) | AA26: =IF(H26 <> "", IF(VLOOKUP(H26, purchasedCars, 2, FALSE) = "", "", VLOOKUP(H26, purchasedCars, 2, FALSE)),"") | AB26: =IF(H26 <> "", IF(VLOOKUP(H26, purchasedCars, 3, FALSE) = "", "", VLOOKUP(H26, purchasedCars, 3, FALSE)),"") | AD26: =IF(AF26 = 1, VLOOKUP(TRIM(AI26), gemSupplier, 2, FALSE), IF(AF26 = 2, VLOOKUP(TRIM(AI26), nasccSupplier, 2, FALSE), IF(AF26 = 2.1, VLOOKUP(TRIM(AI26), nasccSupplier, 2, FALSE), IF(AF26 = 2.2, VLOOKUP(TRIM(AI26), nasccSupplier, 2, FALSE), IF(AF26 = 3, VLOOKUP(TRIM(AI26), euemSupplier, 2, FALSE), IF(AF26 = 4, VLOOKUP(TRIM(AI26), wgtssSupplier, 2, FALSE), IF(AF26 = 5, VLOOKUP(TRIM(AI26), wgtmSupplier, 2, FALSE), IF(AF26 = 7, VLOOKUP(TRIM(AI26), asmSupplier, 2, FALSE), "")))))))) | AF26: =IF(C26 <> "", VLOOKUP(C26, seriesClasses, 2, FALSE), 0) -> 0 | AG26: =IF(AI26 <> "", VLOOKUP(AI26, classIndexes, 2, FALSE), 0) -> 0 | AH26: =IF(AF26 = 0, "", IF(AF26 = 1, VLOOKUP(I26, gemClasses, 2, FALSE), IF(AF26 = 2, VLOOKUP(I26, nasccClasses, 2, FALSE), IF(AF26 = 2.1, VLOOKUP(I26, nasccClasses, 2, FALSE), IF(AF26 = 2.2, VLOOKUP(I26, nasccClasses, 2, FALSE), IF(AF26 = 3, VLOOKUP(I26, euemClasses, 2, FALSE), IF(AF26 = 4, VLOOKUP(I26, wgtssClasses, 2, FALSE), IF(AF26 = 5, VLOOKUP(I26, wgtmClasses, 2, FALSE), IF(AF26 = 6, VLOOKUP(I26, wpcClasses, 2, FALSE), IF(AF26 = 7, VLOOKUP(I26, asmClasses, 2, FALSE), "")))))))))) | AI26: =IF(AF26 = 1, AK26, IF(AF26 = 5, AL26, AH26)) | AK26: =IF(AND(IF(AH26 = "LMGTE PRO", TRUE, FALSE), IF(M26 = "Bronze", TRUE, FALSE)), "LMGTE AM", AH26) | AL26: =IF(AND(IF(AH26 = "GT3-P", TRUE, FALSE), IF(M26 = "Bronze", TRUE, FALSE)), "GT3-A", AH26) | AN26: ='Lineup Legality - FS'!L85 | AP26: =IF(H26 <> "", CONCATENATE("$", ROUND(SUM('Total Costs'!M25:V25), 3), " Million"), "")
B27: =IF(C27 <> "", B26 + 1, "") | D27: =IF(ISERROR(AI27), "", AI27) | G27: =IF(ISERROR(AD27), "", IF(AD27 = 0, "", AD27)) | I27: =IF(ISERROR(AA27), "", AA27) | J27: =IF(ISERROR(AB27), "", AB27) | O27: =IF(ISERROR(AN27), "", AN27) | U27: =IF(ISERROR(AP27), "", AP27) | AA27: =IF(H27 <> "", IF(VLOOKUP(H27, purchasedCars, 2, FALSE) = "", "", VLOOKUP(H27, purchasedCars, 2, FALSE)),"") | AB27: =IF(H27 <> "", IF(VLOOKUP(H27, purchasedCars, 3, FALSE) = "", "", VLOOKUP(H27, purchasedCars, 3, FALSE)),"") | AD27: =IF(AF27 = 1, VLOOKUP(TRIM(AI27), gemSupplier, 2, FALSE), IF(AF27 = 2, VLOOKUP(TRIM(AI27), nasccSupplier, 2, FALSE), IF(AF27 = 2.1, VLOOKUP(TRIM(AI27), nasccSupplier, 2, FALSE), IF(AF27 = 2.2, VLOOKUP(TRIM(AI27), nasccSupplier, 2, FALSE), IF(AF27 = 3, VLOOKUP(TRIM(AI27), euemSupplier, 2, FALSE), IF(AF27 = 4, VLOOKUP(TRIM(AI27), wgtssSupplier, 2, FALSE), IF(AF27 = 5, VLOOKUP(TRIM(AI27), wgtmSupplier, 2, FALSE), IF(AF27 = 7, VLOOKUP(TRIM(AI27), asmSupplier, 2, FALSE), "")))))))) | AF27: =IF(C27 <> "", VLOOKUP(C27, seriesClasses, 2, FALSE), 0) -> 0 | AG27: =IF(AI27 <> "", VLOOKUP(AI27, classIndexes, 2, FALSE), 0) -> 0 | AH27: =IF(AF27 = 0, "", IF(AF27 = 1, VLOOKUP(I27, gemClasses, 2, FALSE), IF(AF27 = 2, VLOOKUP(I27, nasccClasses, 2, FALSE), IF(AF27 = 2.1, VLOOKUP(I27, nasccClasses, 2, FALSE), IF(AF27 = 2.2, VLOOKUP(I27, nasccClasses, 2, FALSE), IF(AF27 = 3, VLOOKUP(I27, euemClasses, 2, FALSE), IF(AF27 = 4, VLOOKUP(I27, wgtssClasses, 2, FALSE), IF(AF27 = 5, VLOOKUP(I27, wgtmClasses, 2, FALSE), IF(AF27 = 6, VLOOKUP(I27, wpcClasses, 2, FALSE), IF(AF27 = 7, VLOOKUP(I27, asmClasses, 2, FALSE), "")))))))))) | AI27: =IF(AF27 = 1, AK27, IF(AF27 = 5, AL27, AH27)) | AK27: =IF(AND(IF(AH27 = "LMGTE PRO", TRUE, FALSE), IF(M27 = "Bronze", TRUE, FALSE)), "LMGTE AM", AH27) | AL27: =IF(AND(IF(AH27 = "GT3-P", TRUE, FALSE), IF(M27 = "Bronze", TRUE, FALSE)), "GT3-A", AH27) | AN27: ='Lineup Legality - FS'!L89 | AP27: =IF(H27 <> "", CONCATENATE("$", ROUND(SUM('Total Costs'!M26:V26), 3), " Million"), "")
B28: =IF(C28 <> "", B27 + 1, "") | D28: =IF(ISERROR(AI28), "", AI28) | G28: =IF(ISERROR(AD28), "", IF(AD28 = 0, "", AD28)) | I28: =IF(ISERROR(AA28), "", AA28) | J28: =IF(ISERROR(AB28), "", AB28) | O28: =IF(ISERROR(AN28), "", AN28) | U28: =IF(ISERROR(AP28), "", AP28) | AA28: =IF(H28 <> "", IF(VLOOKUP(H28, purchasedCars, 2, FALSE) = "", "", VLOOKUP(H28, purchasedCars, 2, FALSE)),"") | AB28: =IF(H28 <> "", IF(VLOOKUP(H28, purchasedCars, 3, FALSE) = "", "", VLOOKUP(H28, purchasedCars, 3, FALSE)),"") | AD28: =IF(AF28 = 1, VLOOKUP(TRIM(AI28), gemSupplier, 2, FALSE), IF(AF28 = 2, VLOOKUP(TRIM(AI28), nasccSupplier, 2, FALSE), IF(AF28 = 2.1, VLOOKUP(TRIM(AI28), nasccSupplier, 2, FALSE), IF(AF28 = 2.2, VLOOKUP(TRIM(AI28), nasccSupplier, 2, FALSE), IF(AF28 = 3, VLOOKUP(TRIM(AI28), euemSupplier, 2, FALSE), IF(AF28 = 4, VLOOKUP(TRIM(AI28), wgtssSupplier, 2, FALSE), IF(AF28 = 5, VLOOKUP(TRIM(AI28), wgtmSupplier, 2, FALSE), IF(AF28 = 7, VLOOKUP(TRIM(AI28), asmSupplier, 2, FALSE), "")))))))) | AF28: =IF(C28 <> "", VLOOKUP(C28, seriesClasses, 2, FALSE), 0) -> 0 | AG28: =IF(AI28 <> "", VLOOKUP(AI28, classIndexes, 2, FALSE), 0) -> 0 | AH28: =IF(AF28 = 0, "", IF(AF28 = 1, VLOOKUP(I28, gemClasses, 2, FALSE), IF(AF28 = 2, VLOOKUP(I28, nasccClasses, 2, FALSE), IF(AF28 = 2.1, VLOOKUP(I28, nasccClasses, 2, FALSE), IF(AF28 = 2.2, VLOOKUP(I28, nasccClasses, 2, FALSE), IF(AF28 = 3, VLOOKUP(I28, euemClasses, 2, FALSE), IF(AF28 = 4, VLOOKUP(I28, wgtssClasses, 2, FALSE), IF(AF28 = 5, VLOOKUP(I28, wgtmClasses, 2, FALSE), IF(AF28 = 6, VLOOKUP(I28, wpcClasses, 2, FALSE), IF(AF28 = 7, VLOOKUP(I28, asmClasses, 2, FALSE), "")))))))))) | AI28: =IF(AF28 = 1, AK28, IF(AF28 = 5, AL28, AH28)) | AK28: =IF(AND(IF(AH28 = "LMGTE PRO", TRUE, FALSE), IF(M28 = "Bronze", TRUE, FALSE)), "LMGTE AM", AH28) | AL28: =IF(AND(IF(AH28 = "GT3-P", TRUE, FALSE), IF(M28 = "Bronze", TRUE, FALSE)), "GT3-A", AH28) | AN28: ='Lineup Legality - FS'!L93 | AP28: =IF(H28 <> "", CONCATENATE("$", ROUND(SUM('Total Costs'!M27:V27), 3), " Million"), "")
B29: =IF(C29 <> "", B28 + 1, "") | D29: =IF(ISERROR(AI29), "", AI29) | G29: =IF(ISERROR(AD29), "", IF(AD29 = 0, "", AD29)) | I29: =IF(ISERROR(AA29), "", AA29) | J29: =IF(ISERROR(AB29), "", AB29) | O29: =IF(ISERROR(AN29), "", AN29) | U29: =IF(ISERROR(AP29), "", AP29) | AA29: =IF(H29 <> "", IF(VLOOKUP(H29, purchasedCars, 2, FALSE) = "", "", VLOOKUP(H29, purchasedCars, 2, FALSE)),"") | AB29: =IF(H29 <> "", IF(VLOOKUP(H29, purchasedCars, 3, FALSE) = "", "", VLOOKUP(H29, purchasedCars, 3, FALSE)),"") | AD29: =IF(AF29 = 1, VLOOKUP(TRIM(AI29), gemSupplier, 2, FALSE), IF(AF29 = 2, VLOOKUP(TRIM(AI29), nasccSupplier, 2, FALSE), IF(AF29 = 2.1, VLOOKUP(TRIM(AI29), nasccSupplier, 2, FALSE), IF(AF29 = 2.2, VLOOKUP(TRIM(AI29), nasccSupplier, 2, FALSE), IF(AF29 = 3, VLOOKUP(TRIM(AI29), euemSupplier, 2, FALSE), IF(AF29 = 4, VLOOKUP(TRIM(AI29), wgtssSupplier, 2, FALSE), IF(AF29 = 5, VLOOKUP(TRIM(AI29), wgtmSupplier, 2, FALSE), IF(AF29 = 7, VLOOKUP(TRIM(AI29), asmSupplier, 2, FALSE), "")))))))) | AF29: =IF(C29 <> "", VLOOKUP(C29, seriesClasses, 2, FALSE), 0) -> 0 | AG29: =IF(AI29 <> "", VLOOKUP(AI29, classIndexes, 2, FALSE), 0) -> 0 | AH29: =IF(AF29 = 0, "", IF(AF29 = 1, VLOOKUP(I29, gemClasses, 2, FALSE), IF(AF29 = 2, VLOOKUP(I29, nasccClasses, 2, FALSE), IF(AF29 = 2.1, VLOOKUP(I29, nasccClasses, 2, FALSE), IF(AF29 = 2.2, VLOOKUP(I29, nasccClasses, 2, FALSE), IF(AF29 = 3, VLOOKUP(I29, euemClasses, 2, FALSE), IF(AF29 = 4, VLOOKUP(I29, wgtssClasses, 2, FALSE), IF(AF29 = 5, VLOOKUP(I29, wgtmClasses, 2, FALSE), IF(AF29 = 6, VLOOKUP(I29, wpcClasses, 2, FALSE), IF(AF29 = 7, VLOOKUP(I29, asmClasses, 2, FALSE), "")))))))))) | AI29: =IF(AF29 = 1, AK29, IF(AF29 = 5, AL29, AH29)) | AK29: =IF(AND(IF(AH29 = "LMGTE PRO", TRUE, FALSE), IF(M29 = "Bronze", TRUE, FALSE)), "LMGTE AM", AH29) | AL29: =IF(AND(IF(AH29 = "GT3-P", TRUE, FALSE), IF(M29 = "Bronze", TRUE, FALSE)), "GT3-A", AH29) | AN29: ='Lineup Legality - FS'!L97 | AP29: =IF(H29 <> "", CONCATENATE("$", ROUND(SUM('Total Costs'!M28:V28), 3), " Million"), "")
B30: =IF(C30 <> "", B29 + 1, "") | D30: =IF(ISERROR(AI30), "", AI30) | G30: =IF(ISERROR(AD30), "", IF(AD30 = 0, "", AD30)) | I30: =IF(ISERROR(AA30), "", AA30) | J30: =IF(ISERROR(AB30), "", AB30) | O30: =IF(ISERROR(AN30), "", AN30) | U30: =IF(ISERROR(AP30), "", AP30) | AA30: =IF(H30 <> "", IF(VLOOKUP(H30, purchasedCars, 2, FALSE) = "", "", VLOOKUP(H30, purchasedCars, 2, FALSE)),"") | AB30: =IF(H30 <> "", IF(VLOOKUP(H30, purchasedCars, 3, FALSE) = "", "", VLOOKUP(H30, purchasedCars, 3, FALSE)),"") | AD30: =IF(AF30 = 1, VLOOKUP(TRIM(AI30), gemSupplier, 2, FALSE), IF(AF30 = 2, VLOOKUP(TRIM(AI30), nasccSupplier, 2, FALSE), IF(AF30 = 2.1, VLOOKUP(TRIM(AI30), nasccSupplier, 2, FALSE), IF(AF30 = 2.2, VLOOKUP(TRIM(AI30), nasccSupplier, 2, FALSE), IF(AF30 = 3, VLOOKUP(TRIM(AI30), euemSupplier, 2, FALSE), IF(AF30 = 4, VLOOKUP(TRIM(AI30), wgtssSupplier, 2, FALSE), IF(AF30 = 5, VLOOKUP(TRIM(AI30), wgtmSupplier, 2, FALSE), IF(AF30 = 7, VLOOKUP(TRIM(AI30), asmSupplier, 2, FALSE), "")))))))) | AF30: =IF(C30 <> "", VLOOKUP(C30, seriesClasses, 2, FALSE), 0) -> 0 | AG30: =IF(AI30 <> "", VLOOKUP(AI30, classIndexes, 2, FALSE), 0) -> 0 | AH30: =IF(AF30 = 0, "", IF(AF30 = 1, VLOOKUP(I30, gemClasses, 2, FALSE), IF(AF30 = 2, VLOOKUP(I30, nasccClasses, 2, FALSE), IF(AF30 = 2.1, VLOOKUP(I30, nasccClasses, 2, FALSE), IF(AF30 = 2.2, VLOOKUP(I30, nasccClasses, 2, FALSE), IF(AF30 = 3, VLOOKUP(I30, euemClasses, 2, FALSE), IF(AF30 = 4, VLOOKUP(I30, wgtssClasses, 2, FALSE), IF(AF30 = 5, VLOOKUP(I30, wgtmClasses, 2, FALSE), IF(AF30 = 6, VLOOKUP(I30, wpcClasses, 2, FALSE), IF(AF30 = 7, VLOOKUP(I30, asmClasses, 2, FALSE), "")))))))))) | AI30: =IF(AF30 = 1, AK30, IF(AF30 = 5, AL30, AH30)) | AK30: =IF(AND(IF(AH30 = "LMGTE PRO", TRUE, FALSE), IF(M30 = "Bronze", TRUE, FALSE)), "LMGTE AM", AH30) | AL30: =IF(AND(IF(AH30 = "GT3-P", TRUE, FALSE), IF(M30 = "Bronze", TRUE, FALSE)), "GT3-A", AH30) | AN30: ='Lineup Legality - FS'!L101 | AP30: =IF(H30 <> "", CONCATENATE("$", ROUND(SUM('Total Costs'!M29:V29), 3), " Million"), "")
B31: =IF(C31 <> "", B30 + 1, "") | D31: =IF(ISERROR(AI31), "", AI31) | G31: =IF(ISERROR(AD31), "", IF(AD31 = 0, "", AD31)) | I31: =IF(ISERROR(AA31), "", AA31) | J31: =IF(ISERROR(AB31), "", AB31) | O31: =IF(ISERROR(AN31), "", AN31) | U31: =IF(ISERROR(AP31), "", AP31) | AA31: =IF(H31 <> "", IF(VLOOKUP(H31, purchasedCars, 2, FALSE) = "", "", VLOOKUP(H31, purchasedCars, 2, FALSE)),"") | AB31: =IF(H31 <> "", IF(VLOOKUP(H31, purchasedCars, 3, FALSE) = "", "", VLOOKUP(H31, purchasedCars, 3, FALSE)),"") | AD31: =IF(AF31 = 1, VLOOKUP(TRIM(AI31), gemSupplier, 2, FALSE), IF(AF31 = 2, VLOOKUP(TRIM(AI31), nasccSupplier, 2, FALSE), IF(AF31 = 2.1, VLOOKUP(TRIM(AI31), nasccSupplier, 2, FALSE), IF(AF31 = 2.2, VLOOKUP(TRIM(AI31), nasccSupplier, 2, FALSE), IF(AF31 = 3, VLOOKUP(TRIM(AI31), euemSupplier, 2, FALSE), IF(AF31 = 4, VLOOKUP(TRIM(AI31), wgtssSupplier, 2, FALSE), IF(AF31 = 5, VLOOKUP(TRIM(AI31), wgtmSupplier, 2, FALSE), IF(AF31 = 7, VLOOKUP(TRIM(AI31), asmSupplier, 2, FALSE), "")))))))) | AF31: =IF(C31 <> "", VLOOKUP(C31, seriesClasses, 2, FALSE), 0) -> 0 | AG31: =IF(AI31 <> "", VLOOKUP(AI31, classIndexes, 2, FALSE), 0) -> 0 | AH31: =IF(AF31 = 0, "", IF(AF31 = 1, VLOOKUP(I31, gemClasses, 2, FALSE), IF(AF31 = 2, VLOOKUP(I31, nasccClasses, 2, FALSE), IF(AF31 = 2.1, VLOOKUP(I31, nasccClasses, 2, FALSE), IF(AF31 = 2.2, VLOOKUP(I31, nasccClasses, 2, FALSE), IF(AF31 = 3, VLOOKUP(I31, euemClasses, 2, FALSE), IF(AF31 = 4, VLOOKUP(I31, wgtssClasses, 2, FALSE), IF(AF31 = 5, VLOOKUP(I31, wgtmClasses, 2, FALSE), IF(AF31 = 6, VLOOKUP(I31, wpcClasses, 2, FALSE), IF(AF31 = 7, VLOOKUP(I31, asmClasses, 2, FALSE), "")))))))))) | AI31: =IF(AF31 = 1, AK31, IF(AF31 = 5, AL31, AH31)) | AK31: =IF(AND(IF(AH31 = "LMGTE PRO", TRUE, FALSE), IF(M31 = "Bronze", TRUE, FALSE)), "LMGTE AM", AH31) | AL31: =IF(AND(IF(AH31 = "GT3-P", TRUE, FALSE), IF(M31 = "Bronze", TRUE, FALSE)), "GT3-A", AH31) | AN31: ='Lineup Legality - FS'!L105 | AP31: =IF(H31 <> "", CONCATENATE("$", ROUND(SUM('Total Costs'!M30:V30), 3), " Million"), "")
B32: =IF(C32 <> "", B31 + 1, "") | D32: =IF(ISERROR(AI32), "", AI32) | G32: =IF(ISERROR(AD32), "", IF(AD32 = 0, "", AD32)) | I32: =IF(ISERROR(AA32), "", AA32) | J32: =IF(ISERROR(AB32), "", AB32) | O32: =IF(ISERROR(AN32), "", AN32) | U32: =IF(ISERROR(AP32), "", AP32) | AA32: =IF(H32 <> "", IF(VLOOKUP(H32, purchasedCars, 2, FALSE) = "", "", VLOOKUP(H32, purchasedCars, 2, FALSE)),"") | AB32: =IF(H32 <> "", IF(VLOOKUP(H32, purchasedCars, 3, FALSE) = "", "", VLOOKUP(H32, purchasedCars, 3, FALSE)),"") | AD32: =IF(AF32 = 1, VLOOKUP(TRIM(AI32), gemSupplier, 2, FALSE), IF(AF32 = 2, VLOOKUP(TRIM(AI32), nasccSupplier, 2, FALSE), IF(AF32 = 2.1, VLOOKUP(TRIM(AI32), nasccSupplier, 2, FALSE), IF(AF32 = 2.2, VLOOKUP(TRIM(AI32), nasccSupplier, 2, FALSE), IF(AF32 = 3, VLOOKUP(TRIM(AI32), euemSupplier, 2, FALSE), IF(AF32 = 4, VLOOKUP(TRIM(AI32), wgtssSupplier, 2, FALSE), IF(AF32 = 5, VLOOKUP(TRIM(AI32), wgtmSupplier, 2, FALSE), IF(AF32 = 7, VLOOKUP(TRIM(AI32), asmSupplier, 2, FALSE), "")))))))) | AF32: =IF(C32 <> "", VLOOKUP(C32, seriesClasses, 2, FALSE), 0) -> 0 | AG32: =IF(AI32 <> "", VLOOKUP(AI32, classIndexes, 2, FALSE), 0) -> 0 | AH32: =IF(AF32 = 0, "", IF(AF32 = 1, VLOOKUP(I32, gemClasses, 2, FALSE), IF(AF32 = 2, VLOOKUP(I32, nasccClasses, 2, FALSE), IF(AF32 = 2.1, VLOOKUP(I32, nasccClasses, 2, FALSE), IF(AF32 = 2.2, VLOOKUP(I32, nasccClasses, 2, FALSE), IF(AF32 = 3, VLOOKUP(I32, euemClasses, 2, FALSE), IF(AF32 = 4, VLOOKUP(I32, wgtssClasses, 2, FALSE), IF(AF32 = 5, VLOOKUP(I32, wgtmClasses, 2, FALSE), IF(AF32 = 6, VLOOKUP(I32, wpcClasses, 2, FALSE), IF(AF32 = 7, VLOOKUP(I32, asmClasses, 2, FALSE), "")))))))))) | AI32: =IF(AF32 = 1, AK32, IF(AF32 = 5, AL32, AH32)) | AK32: =IF(AND(IF(AH32 = "LMGTE PRO", TRUE, FALSE), IF(M32 = "Bronze", TRUE, FALSE)), "LMGTE AM", AH32) | AL32: =IF(AND(IF(AH32 = "GT3-P", TRUE, FALSE), IF(M32 = "Bronze", TRUE, FALSE)), "GT3-A", AH32) | AN32: ='Lineup Legality - FS'!L109 | AP32: =IF(H32 <> "", CONCATENATE("$", ROUND(SUM('Total Costs'!M31:V31), 3), " Million"), "")
B33: =IF(C33 <> "", B32 + 1, "") | D33: =IF(ISERROR(AI33), "", AI33) | G33: =IF(ISERROR(AD33), "", IF(AD33 = 0, "", AD33)) | I33: =IF(ISERROR(AA33), "", AA33) | J33: =IF(ISERROR(AB33), "", AB33) | O33: =IF(ISERROR(AN33), "", AN33) | U33: =IF(ISERROR(AP33), "", AP33) | AA33: =IF(H33 <> "", IF(VLOOKUP(H33, purchasedCars, 2, FALSE) = "", "", VLOOKUP(H33, purchasedCars, 2, FALSE)),"") | AB33: =IF(H33 <> "", IF(VLOOKUP(H33, purchasedCars, 3, FALSE) = "", "", VLOOKUP(H33, purchasedCars, 3, FALSE)),"") | AD33: =IF(AF33 = 1, VLOOKUP(TRIM(AI33), gemSupplier, 2, FALSE), IF(AF33 = 2, VLOOKUP(TRIM(AI33), nasccSupplier, 2, FALSE), IF(AF33 = 2.1, VLOOKUP(TRIM(AI33), nasccSupplier, 2, FALSE), IF(AF33 = 2.2, VLOOKUP(TRIM(AI33), nasccSupplier, 2, FALSE), IF(AF33 = 3, VLOOKUP(TRIM(AI33), euemSupplier, 2, FALSE), IF(AF33 = 4, VLOOKUP(TRIM(AI33), wgtssSupplier, 2, FALSE), IF(AF33 = 5, VLOOKUP(TRIM(AI33), wgtmSupplier, 2, FALSE), IF(AF33 = 7, VLOOKUP(TRIM(AI33), asmSupplier, 2, FALSE), "")))))))) | AF33: =IF(C33 <> "", VLOOKUP(C33, seriesClasses, 2, FALSE), 0) -> 0 | AG33: =IF(AI33 <> "", VLOOKUP(AI33, classIndexes, 2, FALSE), 0) -> 0 | AH33: =IF(AF33 = 0, "", IF(AF33 = 1, VLOOKUP(I33, gemClasses, 2, FALSE), IF(AF33 = 2, VLOOKUP(I33, nasccClasses, 2, FALSE), IF(AF33 = 2.1, VLOOKUP(I33, nasccClasses, 2, FALSE), IF(AF33 = 2.2, VLOOKUP(I33, nasccClasses, 2, FALSE), IF(AF33 = 3, VLOOKUP(I33, euemClasses, 2, FALSE), IF(AF33 = 4, VLOOKUP(I33, wgtssClasses, 2, FALSE), IF(AF33 = 5, VLOOKUP(I33, wgtmClasses, 2, FALSE), IF(AF33 = 6, VLOOKUP(I33, wpcClasses, 2, FALSE), IF(AF33 = 7, VLOOKUP(I33, asmClasses, 2, FALSE), "")))))))))) | AI33: =IF(AF33 = 1, AK33, IF(AF33 = 5, AL33, AH33)) | AK33: =IF(AND(IF(AH33 = "LMGTE PRO", TRUE, FALSE), IF(M33 = "Bronze", TRUE, FALSE)), "LMGTE AM", AH33) | AL33: =IF(AND(IF(AH33 = "GT3-P", TRUE, FALSE), IF(M33 = "Bronze", TRUE, FALSE)), "GT3-A", AH33) | AN33: ='Lineup Legality - FS'!L113 | AP33: =IF(H33 <> "", CONCATENATE("$", ROUND(SUM('Total Costs'!M32:V32), 3), " Million"), "")
B34: =IF(C34 <> "", B33 + 1, "") | D34: =IF(ISERROR(AI34), "", AI34) | G34: =IF(ISERROR(AD34), "", IF(AD34 = 0, "", AD34)) | I34: =IF(ISERROR(AA34), "", AA34) | J34: =IF(ISERROR(AB34), "", AB34) | O34: =IF(ISERROR(AN34), "", AN34) | U34: =IF(ISERROR(AP34), "", AP34) | AA34: =IF(H34 <> "", IF(VLOOKUP(H34, purchasedCars, 2, FALSE) = "", "", VLOOKUP(H34, purchasedCars, 2, FALSE)),"") | AB34: =IF(H34 <> "", IF(VLOOKUP(H34, purchasedCars, 3, FALSE) = "", "", VLOOKUP(H34, purchasedCars, 3, FALSE)),"") | AD34: =IF(AF34 = 1, VLOOKUP(TRIM(AI34), gemSupplier, 2, FALSE), IF(AF34 = 2, VLOOKUP(TRIM(AI34), nasccSupplier, 2, FALSE), IF(AF34 = 2.1, VLOOKUP(TRIM(AI34), nasccSupplier, 2, FALSE), IF(AF34 = 2.2, VLOOKUP(TRIM(AI34), nasccSupplier, 2, FALSE), IF(AF34 = 3, VLOOKUP(TRIM(AI34), euemSupplier, 2, FALSE), IF(AF34 = 4, VLOOKUP(TRIM(AI34), wgtssSupplier, 2, FALSE), IF(AF34 = 5, VLOOKUP(TRIM(AI34), wgtmSupplier, 2, FALSE), IF(AF34 = 7, VLOOKUP(TRIM(AI34), asmSupplier, 2, FALSE), "")))))))) | AF34: =IF(C34 <> "", VLOOKUP(C34, seriesClasses, 2, FALSE), 0) -> 0 | AG34: =IF(AI34 <> "", VLOOKUP(AI34, classIndexes, 2, FALSE), 0) -> 0 | AH34: =IF(AF34 = 0, "", IF(AF34 = 1, VLOOKUP(I34, gemClasses, 2, FALSE), IF(AF34 = 2, VLOOKUP(I34, nasccClasses, 2, FALSE), IF(AF34 = 2.1, VLOOKUP(I34, nasccClasses, 2, FALSE), IF(AF34 = 2.2, VLOOKUP(I34, nasccClasses, 2, FALSE), IF(AF34 = 3, VLOOKUP(I34, euemClasses, 2, FALSE), IF(AF34 = 4, VLOOKUP(I34, wgtssClasses, 2, FALSE), IF(AF34 = 5, VLOOKUP(I34, wgtmClasses, 2, FALSE), IF(AF34 = 6, VLOOKUP(I34, wpcClasses, 2, FALSE), IF(AF34 = 7, VLOOKUP(I34, asmClasses, 2, FALSE), "")))))))))) | AI34: =IF(AF34 = 1, AK34, IF(AF34 = 5, AL34, AH34)) | AK34: =IF(AND(IF(AH34 = "LMGTE PRO", TRUE, FALSE), IF(M34 = "Bronze", TRUE, FALSE)), "LMGTE AM", AH34) | AL34: =IF(AND(IF(AH34 = "GT3-P", TRUE, FALSE), IF(M34 = "Bronze", TRUE, FALSE)), "GT3-A", AH34) | AN34: ='Lineup Legality - FS'!L117 | AP34: =IF(H34 <> "", CONCATENATE("$", ROUND(SUM('Total Costs'!M33:V33), 3), " Million"), "")
B35: =IF(C35 <> "", B34 + 1, "") | D35: =IF(ISERROR(AI35), "", AI35) | G35: =IF(ISERROR(AD35), "", IF(AD35 = 0, "", AD35)) | I35: =IF(ISERROR(AA35), "", AA35) | J35: =IF(ISERROR(AB35), "", AB35) | O35: =IF(ISERROR(AN35), "", AN35) | U35: =IF(ISERROR(AP35), "", AP35) | AA35: =IF(H35 <> "", IF(VLOOKUP(H35, purchasedCars, 2, FALSE) = "", "", VLOOKUP(H35, purchasedCars, 2, FALSE)),"") | AB35: =IF(H35 <> "", IF(VLOOKUP(H35, purchasedCars, 3, FALSE) = "", "", VLOOKUP(H35, purchasedCars, 3, FALSE)),"") | AD35: =IF(AF35 = 1, VLOOKUP(TRIM(AI35), gemSupplier, 2, FALSE), IF(AF35 = 2, VLOOKUP(TRIM(AI35), nasccSupplier, 2, FALSE), IF(AF35 = 2.1, VLOOKUP(TRIM(AI35), nasccSupplier, 2, FALSE), IF(AF35 = 2.2, VLOOKUP(TRIM(AI35), nasccSupplier, 2, FALSE), IF(AF35 = 3, VLOOKUP(TRIM(AI35), euemSupplier, 2, FALSE), IF(AF35 = 4, VLOOKUP(TRIM(AI35), wgtssSupplier, 2, FALSE), IF(AF35 = 5, VLOOKUP(TRIM(AI35), wgtmSupplier, 2, FALSE), IF(AF35 = 7, VLOOKUP(TRIM(AI35), asmSupplier, 2, FALSE), "")))))))) | AF35: =IF(C35 <> "", VLOOKUP(C35, seriesClasses, 2, FALSE), 0) -> 0 | AG35: =IF(AI35 <> "", VLOOKUP(AI35, classIndexes, 2, FALSE), 0) -> 0 | AH35: =IF(AF35 = 0, "", IF(AF35 = 1, VLOOKUP(I35, gemClasses, 2, FALSE), IF(AF35 = 2, VLOOKUP(I35, nasccClasses, 2, FALSE), IF(AF35 = 2.1, VLOOKUP(I35, nasccClasses, 2, FALSE), IF(AF35 = 2.2, VLOOKUP(I35, nasccClasses, 2, FALSE), IF(AF35 = 3, VLOOKUP(I35, euemClasses, 2, FALSE), IF(AF35 = 4, VLOOKUP(I35, wgtssClasses, 2, FALSE), IF(AF35 = 5, VLOOKUP(I35, wgtmClasses, 2, FALSE), IF(AF35 = 6, VLOOKUP(I35, wpcClasses, 2, FALSE), IF(AF35 = 7, VLOOKUP(I35, asmClasses, 2, FALSE), "")))))))))) | AI35: =IF(AF35 = 1, AK35, IF(AF35 = 5, AL35, AH35)) | AK35: =IF(AND(IF(AH35 = "LMGTE PRO", TRUE, FALSE), IF(M35 = "Bronze", TRUE, FALSE)), "LMGTE AM", AH35) | AL35: =IF(AND(IF(AH35 = "GT3-P", TRUE, FALSE), IF(M35 = "Bronze", TRUE, FALSE)), "GT3-A", AH35) | AN35: ='Lineup Legality - FS'!L121 | AP35: =IF(H35 <> "", CONCATENATE("$", ROUND(SUM('Total Costs'!M34:V34), 3), " Million"), "")
B36: =IF(C36 <> "", B35 + 1, "") | D36: =IF(ISERROR(AI36), "", AI36) | G36: =IF(ISERROR(AD36), "", IF(AD36 = 0, "", AD36)) | I36: =IF(ISERROR(AA36), "", AA36) | J36: =IF(ISERROR(AB36), "", AB36) | O36: =IF(ISERROR(AN36), "", AN36) | U36: =IF(ISERROR(AP36), "", AP36) | AA36: =IF(H36 <> "", IF(VLOOKUP(H36, purchasedCars, 2, FALSE) = "", "", VLOOKUP(H36, purchasedCars, 2, FALSE)),"") | AB36: =IF(H36 <> "", IF(VLOOKUP(H36, purchasedCars, 3, FALSE) = "", "", VLOOKUP(H36, purchasedCars, 3, FALSE)),"") | AD36: =IF(AF36 = 1, VLOOKUP(TRIM(AI36), gemSupplier, 2, FALSE), IF(AF36 = 2, VLOOKUP(TRIM(AI36), nasccSupplier, 2, FALSE), IF(AF36 = 2.1, VLOOKUP(TRIM(AI36), nasccSupplier, 2, FALSE), IF(AF36 = 2.2, VLOOKUP(TRIM(AI36), nasccSupplier, 2, FALSE), IF(AF36 = 3, VLOOKUP(TRIM(AI36), euemSupplier, 2, FALSE), IF(AF36 = 4, VLOOKUP(TRIM(AI36), wgtssSupplier, 2, FALSE), IF(AF36 = 5, VLOOKUP(TRIM(AI36), wgtmSupplier, 2, FALSE), IF(AF36 = 7, VLOOKUP(TRIM(AI36), asmSupplier, 2, FALSE), "")))))))) | AF36: =IF(C36 <> "", VLOOKUP(C36, seriesClasses, 2, FALSE), 0) -> 0 | AG36: =IF(AI36 <> "", VLOOKUP(AI36, classIndexes, 2, FALSE), 0) -> 0 | AH36: =IF(AF36 = 0, "", IF(AF36 = 1, VLOOKUP(I36, gemClasses, 2, FALSE), IF(AF36 = 2, VLOOKUP(I36, nasccClasses, 2, FALSE), IF(AF36 = 2.1, VLOOKUP(I36, nasccClasses, 2, FALSE), IF(AF36 = 2.2, VLOOKUP(I36, nasccClasses, 2, FALSE), IF(AF36 = 3, VLOOKUP(I36, euemClasses, 2, FALSE), IF(AF36 = 4, VLOOKUP(I36, wgtssClasses, 2, FALSE), IF(AF36 = 5, VLOOKUP(I36, wgtmClasses, 2, FALSE), IF(AF36 = 6, VLOOKUP(I36, wpcClasses, 2, FALSE), IF(AF36 = 7, VLOOKUP(I36, asmClasses, 2, FALSE), "")))))))))) | AI36: =IF(AF36 = 1, AK36, IF(AF36 = 5, AL36, AH36)) | AK36: =IF(AND(IF(AH36 = "LMGTE PRO", TRUE, FALSE), IF(M36 = "Bronze", TRUE, FALSE)), "LMGTE AM", AH36) | AL36: =IF(AND(IF(AH36 = "GT3-P", TRUE, FALSE), IF(M36 = "Bronze", TRUE, FALSE)), "GT3-A", AH36) | AN36: ='Lineup Legality - FS'!L125 | AP36: =IF(H36 <> "", CONCATENATE("$", ROUND(SUM('Total Costs'!M35:V35), 3), " Million"), "")
B37: =IF(C37 <> "", B36 + 1, "") | D37: =IF(ISERROR(AI37), "", AI37) | G37: =IF(ISERROR(AD37), "", IF(AD37 = 0, "", AD37)) | I37: =IF(ISERROR(AA37), "", AA37) | J37: =IF(ISERROR(AB37), "", AB37) | O37: =IF(ISERROR(AN37), "", AN37) | U37: =IF(ISERROR(AP37), "", AP37) | AA37: =IF(H37 <> "", IF(VLOOKUP(H37, purchasedCars, 2, FALSE) = "", "", VLOOKUP(H37, purchasedCars, 2, FALSE)),"") | AB37: =IF(H37 <> "", IF(VLOOKUP(H37, purchasedCars, 3, FALSE) = "", "", VLOOKUP(H37, purchasedCars, 3, FALSE)),"") | AD37: =IF(AF37 = 1, VLOOKUP(TRIM(AI37), gemSupplier, 2, FALSE), IF(AF37 = 2, VLOOKUP(TRIM(AI37), nasccSupplier, 2, FALSE), IF(AF37 = 2.1, VLOOKUP(TRIM(AI37), nasccSupplier, 2, FALSE), IF(AF37 = 2.2, VLOOKUP(TRIM(AI37), nasccSupplier, 2, FALSE), IF(AF37 = 3, VLOOKUP(TRIM(AI37), euemSupplier, 2, FALSE), IF(AF37 = 4, VLOOKUP(TRIM(AI37), wgtssSupplier, 2, FALSE), IF(AF37 = 5, VLOOKUP(TRIM(AI37), wgtmSupplier, 2, FALSE), IF(AF37 = 7, VLOOKUP(TRIM(AI37), asmSupplier, 2, FALSE), "")))))))) | AF37: =IF(C37 <> "", VLOOKUP(C37, seriesClasses, 2, FALSE), 0) -> 0 | AG37: =IF(AI37 <> "", VLOOKUP(AI37, classIndexes, 2, FALSE), 0) -> 0 | AH37: =IF(AF37 = 0, "", IF(AF37 = 1, VLOOKUP(I37, gemClasses, 2, FALSE), IF(AF37 = 2, VLOOKUP(I37, nasccClasses, 2, FALSE), IF(AF37 = 2.1, VLOOKUP(I37, nasccClasses, 2, FALSE), IF(AF37 = 2.2, VLOOKUP(I37, nasccClasses, 2, FALSE), IF(AF37 = 3, VLOOKUP(I37, euemClasses, 2, FALSE), IF(AF37 = 4, VLOOKUP(I37, wgtssClasses, 2, FALSE), IF(AF37 = 5, VLOOKUP(I37, wgtmClasses, 2, FALSE), IF(AF37 = 6, VLOOKUP(I37, wpcClasses, 2, FALSE), IF(AF37 = 7, VLOOKUP(I37, asmClasses, 2, FALSE), "")))))))))) | AI37: =IF(AF37 = 1, AK37, IF(AF37 = 5, AL37, AH37)) | AK37: =IF(AND(IF(AH37 = "LMGTE PRO", TRUE, FALSE), IF(M37 = "Bronze", TRUE, FALSE)), "LMGTE AM", AH37) | AL37: =IF(AND(IF(AH37 = "GT3-P", TRUE, FALSE), IF(M37 = "Bronze", TRUE, FALSE)), "GT3-A", AH37) | AN37: ='Lineup Legality - FS'!L129 | AP37: =IF(H37 <> "", CONCATENATE("$", ROUND(SUM('Total Costs'!M36:V36), 3), " Million"), "")
B38: =IF(C38 <> "", B37 + 1, "") | D38: =IF(ISERROR(AI38), "", AI38) | G38: =IF(ISERROR(AD38), "", IF(AD38 = 0, "", AD38)) | I38: =IF(ISERROR(AA38), "", AA38) | J38: =IF(ISERROR(AB38), "", AB38) | O38: =IF(ISERROR(AN38), "", AN38) | U38: =IF(ISERROR(AP38), "", AP38) | AA38: =IF(H38 <> "", IF(VLOOKUP(H38, purchasedCars, 2, FALSE) = "", "", VLOOKUP(H38, purchasedCars, 2, FALSE)),"") | AB38: =IF(H38 <> "", IF(VLOOKUP(H38, purchasedCars, 3, FALSE) = "", "", VLOOKUP(H38, purchasedCars, 3, FALSE)),"") | AD38: =IF(AF38 = 1, VLOOKUP(TRIM(AI38), gemSupplier, 2, FALSE), IF(AF38 = 2, VLOOKUP(TRIM(AI38), nasccSupplier, 2, FALSE), IF(AF38 = 2.1, VLOOKUP(TRIM(AI38), nasccSupplier, 2, FALSE), IF(AF38 = 2.2, VLOOKUP(TRIM(AI38), nasccSupplier, 2, FALSE), IF(AF38 = 3, VLOOKUP(TRIM(AI38), euemSupplier, 2, FALSE), IF(AF38 = 4, VLOOKUP(TRIM(AI38), wgtssSupplier, 2, FALSE), IF(AF38 = 5, VLOOKUP(TRIM(AI38), wgtmSupplier, 2, FALSE), IF(AF38 = 7, VLOOKUP(TRIM(AI38), asmSupplier, 2, FALSE), "")))))))) | AF38: =IF(C38 <> "", VLOOKUP(C38, seriesClasses, 2, FALSE), 0) -> 0 | AG38: =IF(AI38 <> "", VLOOKUP(AI38, classIndexes, 2, FALSE), 0) -> 0 | AH38: =IF(AF38 = 0, "", IF(AF38 = 1, VLOOKUP(I38, gemClasses, 2, FALSE), IF(AF38 = 2, VLOOKUP(I38, nasccClasses, 2, FALSE), IF(AF38 = 2.1, VLOOKUP(I38, nasccClasses, 2, FALSE), IF(AF38 = 2.2, VLOOKUP(I38, nasccClasses, 2, FALSE), IF(AF38 = 3, VLOOKUP(I38, euemClasses, 2, FALSE), IF(AF38 = 4, VLOOKUP(I38, wgtssClasses, 2, FALSE), IF(AF38 = 5, VLOOKUP(I38, wgtmClasses, 2, FALSE), IF(AF38 = 6, VLOOKUP(I38, wpcClasses, 2, FALSE), IF(AF38 = 7, VLOOKUP(I38, asmClasses, 2, FALSE), "")))))))))) | AI38: =IF(AF38 = 1, AK38, IF(AF38 = 5, AL38, AH38)) | AK38: =IF(AND(IF(AH38 = "LMGTE PRO", TRUE, FALSE), IF(M38 = "Bronze", TRUE, FALSE)), "LMGTE AM", AH38) | AL38: =IF(AND(IF(AH38 = "GT3-P", TRUE, FALSE), IF(M38 = "Bronze", TRUE, FALSE)), "GT3-A", AH38) | AN38: ='Lineup Legality - FS'!L133 | AP38: =IF(H38 <> "", CONCATENATE("$", ROUND(SUM('Total Costs'!M37:V37), 3), " Million"), "")
B39: =IF(C39 <> "", B38 + 1, "") | D39: =IF(ISERROR(AI39), "", AI39) | G39: =IF(ISERROR(AD39), "", IF(AD39 = 0, "", AD39)) | I39: =IF(ISERROR(AA39), "", AA39) | J39: =IF(ISERROR(AB39), "", AB39) | O39: =IF(ISERROR(AN39), "", AN39) | U39: =IF(ISERROR(AP39), "", AP39) | AA39: =IF(H39 <> "", IF(VLOOKUP(H39, purchasedCars, 2, FALSE) = "", "", VLOOKUP(H39, purchasedCars, 2, FALSE)),"") | AB39: =IF(H39 <> "", IF(VLOOKUP(H39, purchasedCars, 3, FALSE) = "", "", VLOOKUP(H39, purchasedCars, 3, FALSE)),"") | AD39: =IF(AF39 = 1, VLOOKUP(TRIM(AI39), gemSupplier, 2, FALSE), IF(AF39 = 2, VLOOKUP(TRIM(AI39), nasccSupplier, 2, FALSE), IF(AF39 = 2.1, VLOOKUP(TRIM(AI39), nasccSupplier, 2, FALSE), IF(AF39 = 2.2, VLOOKUP(TRIM(AI39), nasccSupplier, 2, FALSE), IF(AF39 = 3, VLOOKUP(TRIM(AI39), euemSupplier, 2, FALSE), IF(AF39 = 4, VLOOKUP(TRIM(AI39), wgtssSupplier, 2, FALSE), IF(AF39 = 5, VLOOKUP(TRIM(AI39), wgtmSupplier, 2, FALSE), IF(AF39 = 7, VLOOKUP(TRIM(AI39), asmSupplier, 2, FALSE), "")))))))) | AF39: =IF(C39 <> "", VLOOKUP(C39, seriesClasses, 2, FALSE), 0) -> 0 | AG39: =IF(AI39 <> "", VLOOKUP(AI39, classIndexes, 2, FALSE), 0) -> 0 | AH39: =IF(AF39 = 0, "", IF(AF39 = 1, VLOOKUP(I39, gemClasses, 2, FALSE), IF(AF39 = 2, VLOOKUP(I39, nasccClasses, 2, FALSE), IF(AF39 = 2.1, VLOOKUP(I39, nasccClasses, 2, FALSE), IF(AF39 = 2.2, VLOOKUP(I39, nasccClasses, 2, FALSE), IF(AF39 = 3, VLOOKUP(I39, euemClasses, 2, FALSE), IF(AF39 = 4, VLOOKUP(I39, wgtssClasses, 2, FALSE), IF(AF39 = 5, VLOOKUP(I39, wgtmClasses, 2, FALSE), IF(AF39 = 6, VLOOKUP(I39, wpcClasses, 2, FALSE), IF(AF39 = 7, VLOOKUP(I39, asmClasses, 2, FALSE), "")))))))))) | AI39: =IF(AF39 = 1, AK39, IF(AF39 = 5, AL39, AH39)) | AK39: =IF(AND(IF(AH39 = "LMGTE PRO", TRUE, FALSE), IF(M39 = "Bronze", TRUE, FALSE)), "LMGTE AM", AH39) | AL39: =IF(AND(IF(AH39 = "GT3-P", TRUE, FALSE), IF(M39 = "Bronze", TRUE, FALSE)), "GT3-A", AH39) | AN39: ='Lineup Legality - FS'!L137 | AP39: =IF(H39 <> "", CONCATENATE("$", ROUND(SUM('Total Costs'!M38:V38), 3), " Million"), "")
B40: =IF(C40 <> "", B39 + 1, "") | D40: =IF(ISERROR(AI40), "", AI40) | G40: =IF(ISERROR(AD40), "", IF(AD40 = 0, "", AD40)) | I40: =IF(ISERROR(AA40), "", AA40) | J40: =IF(ISERROR(AB40), "", AB40) | O40: =IF(ISERROR(AN40), "", AN40) | U40: =IF(ISERROR(AP40), "", AP40) | AA40: =IF(H40 <> "", IF(VLOOKUP(H40, purchasedCars, 2, FALSE) = "", "", VLOOKUP(H40, purchasedCars, 2, FALSE)),"") | AB40: =IF(H40 <> "", IF(VLOOKUP(H40, purchasedCars, 3, FALSE) = "", "", VLOOKUP(H40, purchasedCars, 3, FALSE)),"") | AD40: =IF(AF40 = 1, VLOOKUP(TRIM(AI40), gemSupplier, 2, FALSE), IF(AF40 = 2, VLOOKUP(TRIM(AI40), nasccSupplier, 2, FALSE), IF(AF40 = 2.1, VLOOKUP(TRIM(AI40), nasccSupplier, 2, FALSE), IF(AF40 = 2.2, VLOOKUP(TRIM(AI40), nasccSupplier, 2, FALSE), IF(AF40 = 3, VLOOKUP(TRIM(AI40), euemSupplier, 2, FALSE), IF(AF40 = 4, VLOOKUP(TRIM(AI40), wgtssSupplier, 2, FALSE), IF(AF40 = 5, VLOOKUP(TRIM(AI40), wgtmSupplier, 2, FALSE), IF(AF40 = 7, VLOOKUP(TRIM(AI40), asmSupplier, 2, FALSE), "")))))))) | AF40: =IF(C40 <> "", VLOOKUP(C40, seriesClasses, 2, FALSE), 0) -> 0 | AG40: =IF(AI40 <> "", VLOOKUP(AI40, classIndexes, 2, FALSE), 0) -> 0 | AH40: =IF(AF40 = 0, "", IF(AF40 = 1, VLOOKUP(I40, gemClasses, 2, FALSE), IF(AF40 = 2, VLOOKUP(I40, nasccClasses, 2, FALSE), IF(AF40 = 2.1, VLOOKUP(I40, nasccClasses, 2, FALSE), IF(AF40 = 2.2, VLOOKUP(I40, nasccClasses, 2, FALSE), IF(AF40 = 3, VLOOKUP(I40, euemClasses, 2, FALSE), IF(AF40 = 4, VLOOKUP(I40, wgtssClasses, 2, FALSE), IF(AF40 = 5, VLOOKUP(I40, wgtmClasses, 2, FALSE), IF(AF40 = 6, VLOOKUP(I40, wpcClasses, 2, FALSE), IF(AF40 = 7, VLOOKUP(I40, asmClasses, 2, FALSE), "")))))))))) | AI40: =IF(AF40 = 1, AK40, IF(AF40 = 5, AL40, AH40)) | AK40: =IF(AND(IF(AH40 = "LMGTE PRO", TRUE, FALSE), IF(M40 = "Bronze", TRUE, FALSE)), "LMGTE AM", AH40) | AL40: =IF(AND(IF(AH40 = "GT3-P", TRUE, FALSE), IF(M40 = "Bronze", TRUE, FALSE)), "GT3-A", AH40) | AN40: ='Lineup Legality - FS'!L141 | AP40: =IF(H40 <> "", CONCATENATE("$", ROUND(SUM('Total Costs'!M39:V39), 3), " Million"), "")

Sheet One-Off Entries
B2: Team Creator V10 - 2018
B3: One-Off Entries | Z3: Team Creator V10
B4: Entry No | C4: Series Information | F4: Entry Details | J4: Car Model Details | M4: Driver Details | R4: Entrant Setup Bonuses | W4: Total Costs | Z4: Full Season Entries | AC4: Car Model Fetching | AH4: Class Fetching
C5: Event | D5: Abbreviation | E5: Class | F5: Car No | G5: Team Name | H5: Tyre Supplier | I5: Invited | J5: Model ID | K5: Platform | L5: Model Name | M5: Driver 1 | N5: Driver 2 | O5: Driver 3 | P5: Driver 4 | Q5: Legality | R5: Setup | V5: Reliability | Z5: Usage Guide | AC5: Platform | AD5: Model Name | AF5: Tyre Supplier | AH5: Series | AI5: Indices | AK5: Rough | AL5: Final | AQ5: Lineup Legality | AS5: Entry Costs
B6: =IF(D6 <> "", 1, "") | D6: =IF(ISERROR(AH6), "", AH6) | E6: =IF(ISERROR(AL6), "", AL6) | H6: =IF(ISERROR(AF6), "", IF(AF6 = 0, "", AF6)) | K6: =IF(ISERROR(AC6), "", AC6) | L6: =IF(ISERROR(AD6), "", AD6) | Q6: =IF(ISERROR(AQ6), "", AQ6) | W6: =IF(ISERROR(AS6), "", AS6) | Z6: Model Platform and Name will automatically fill in when given an existing Model ID set in 'Car Purchase' | AC6: =IF(J6 <> "", IF(VLOOKUP(J6, purchasedCars, 2, FALSE) = "", "", VLOOKUP(J6, purchasedCars, 2, FALSE)),"") | AD6: =IF(J6 <> "", IF(VLOOKUP(J6, purchasedCars, 3, FALSE) = "", "", VLOOKUP(J6, purchasedCars, 3, FALSE)),"") | AF6: =IF(AI6 = 1, VLOOKUP(TRIM(AL6), gemSupplier, 2, FALSE), IF(AI6 = 2, VLOOKUP(TRIM(AL6), nasccSupplier, 2, FALSE), IF(AI6 = 2.1, VLOOKUP(TRIM(AL6), nasccSupplier, 2, FALSE), IF(AI6 = 2.2, VLOOKUP(TRIM(AL6), nasccSupplier, 2, FALSE), IF(AI6 = 3, VLOOKUP(TRIM(AL6), euemSupplier, 2, FALSE), IF(AI6 = 4, VLOOKUP(TRIM(AL6), wgtssSupplier, 2, FALSE), IF(AI6 = 5, VLOOKUP(TRIM(AL6), wgtmSupplier, 2, FALSE), IF(AI6 = 7, VLOOKUP(TRIM(AL6), asmSupplier, 2, FALSE), "")))))))) | AH6: =IF(C6 <> "", VLOOKUP(C6, oneOffs, 2, FALSE), "") | AI6: =IF(D6 <> "", VLOOKUP(D6, seriesCodeClasses, 2, FALSE), 0) -> 0 | AJ6: =IF(AL6 <> "", VLOOKUP(AL6, classIndexes, 2, FALSE), 0) -> 0 | AK6: =IF(AI6 = 0, "", IF(AI6 = 1, VLOOKUP(K6, gemClasses, 2, FALSE), IF(AI6 = 2, VLOOKUP(K6, nasccClasses, 2, FALSE), IF(AI6 = 2.1, VLOOKUP(K6, nasccClasses, 2, FALSE), IF(AI6 = 2.2, VLOOKUP(K6, nasccClasses, 2, FALSE), IF(AI6 = 3, VLOOKUP(K6, euemClasses, 2, FALSE), IF(AI6 = 4, VLOOKUP(K6, wgtssClasses, 2, FALSE), IF(AI6 = 5, VLOOKUP(K6, wgtmClasses, 2, FALSE), IF(AI6 = 6, VLOOKUP(K6, wpcClasses, 2, FALSE), IF(AI6 = 7, VLOOKUP(K6, asmClasses, 2, FALSE), "")))))))))) | AL6: =IF(AI6 = 1, AN6, IF(AI6 = 5, AO6, AK6)) | AN6: =IF(AND(IF(AK6 = "LMGTE PRO", TRUE, FALSE), IF(O6 = "Bronze", TRUE, FALSE)), "LMGTE AM", AK6) | AO6: =IF(AND(IF(AK6 = "GT3-P", TRUE, FALSE), IF(O6 = "Bronze", TRUE, FALSE)), "GT3-A", AK6) | AQ6: ='Lineup Legality - OOE'!L5 | AS6: =IF(J6 <> "", CONCATENATE("$", ROUND(SUM('Total Costs'!AZ5:BI5), 3), " Million"), "")
B7: =IF(D7 <> "", B6 + 1, "") | D7: =IF(ISERROR(AH7), "", AH7) | E7: =IF(ISERROR(AL7), "", AL7) | H7: =IF(ISERROR(AF7), "", IF(AF7 = 0, "", AF7)) | K7: =IF(ISERROR(AC7), "", AC7) | L7: =IF(ISERROR(AD7), "", AD7) | Q7: ='Lineup Legality - OOE'!L9 | W7: =IF(ISERROR(AS7), "", AS7) | AC7: =IF(J7 <> "", IF(VLOOKUP(J7, purchasedCars, 2, FALSE) = "", "", VLOOKUP(J7, purchasedCars, 2, FALSE)),"") | AD7: =IF(J7 <> "", IF(VLOOKUP(J7, purchasedCars, 3, FALSE) = "", "", VLOOKUP(J7, purchasedCars, 3, FALSE)),"") | AF7: =IF(AI7 = 1, VLOOKUP(TRIM(AL7), gemSupplier, 2, FALSE), IF(AI7 = 2, VLOOKUP(TRIM(AL7), nasccSupplier, 2, FALSE), IF(AI7 = 2.1, VLOOKUP(TRIM(AL7), nasccSupplier, 2, FALSE), IF(AI7 = 2.2, VLOOKUP(TRIM(AL7), nasccSupplier, 2, FALSE), IF(AI7 = 3, VLOOKUP(TRIM(AL7), euemSupplier, 2, FALSE), IF(AI7 = 4, VLOOKUP(TRIM(AL7), wgtssSupplier, 2, FALSE), IF(AI7 = 5, VLOOKUP(TRIM(AL7), wgtmSupplier, 2, FALSE), IF(AI7 = 7, VLOOKUP(TRIM(AL7), asmSupplier, 2, FALSE), "")))))))) | AH7: =IF(C7 <> "", VLOOKUP(C7, oneOffs, 2, FALSE), "") | AI7: =IF(D7 <> "", VLOOKUP(D7, seriesCodeClasses, 2, FALSE), 0) -> 0 | AJ7: =IF(AL7 <> "", VLOOKUP(AL7, classIndexes, 2, FALSE), 0) -> 0 | AK7: =IF(AI7 = 0, "", IF(AI7 = 1, VLOOKUP(K7, gemClasses, 2, FALSE), IF(AI7 = 2, VLOOKUP(K7, nasccClasses, 2, FALSE), IF(AI7 = 2.1, VLOOKUP(K7, nasccClasses, 2, FALSE), IF(AI7 = 2.2, VLOOKUP(K7, nasccClasses, 2, FALSE), IF(AI7 = 3, VLOOKUP(K7, euemClasses, 2, FALSE), IF(AI7 = 4, VLOOKUP(K7, wgtssClasses, 2, FALSE), IF(AI7 = 5, VLOOKUP(K7, wgtmClasses, 2, FALSE), IF(AI7 = 6, VLOOKUP(K7, wpcClasses, 2, FALSE), IF(AI7 = 7, VLOOKUP(K7, asmClasses, 2, FALSE), "")))))))))) | AL7: =IF(AI7 = 1, AN7, IF(AI7 = 5, AO7, AK7)) | AN7: =IF(AND(IF(AK7 = "LMGTE PRO", TRUE, FALSE), IF(O7 = "Bronze", TRUE, FALSE)), "LMGTE AM", AK7) | AO7: =IF(AND(IF(AK7 = "GT3-P", TRUE, FALSE), IF(O7 = "Bronze", TRUE, FALSE)), "GT3-A", AK7) | AQ7: ='Lineup Legality - OOE'!L9 | AS7: =IF(J7 <> "", CONCATENATE("$", ROUND(SUM('Total Costs'!AZ6:BI6), 3), " Million"), "")
B8: =IF(D8 <> "", B7 + 1, "") | D8: =IF(ISERROR(AH8), "", AH8) | E8: =IF(ISERROR(AL8), "", AL8) | H8: =IF(ISERROR(AF8), "", IF(AF8 = 0, "", AF8)) | K8: =IF(ISERROR(AC8), "", AC8) | L8: =IF(ISERROR(AD8), "", AD8) | Q8: ='Lineup Legality - OOE'!L13 | W8: =IF(ISERROR(AS8), "", AS8) | AC8: =IF(J8 <> "", IF(VLOOKUP(J8, purchasedCars, 2, FALSE) = "", "", VLOOKUP(J8, purchasedCars, 2, FALSE)),"") | AD8: =IF(J8 <> "", IF(VLOOKUP(J8, purchasedCars, 3, FALSE) = "", "", VLOOKUP(J8, purchasedCars, 3, FALSE)),"") | AF8: =IF(AI8 = 1, VLOOKUP(TRIM(AL8), gemSupplier, 2, FALSE), IF(AI8 = 2, VLOOKUP(TRIM(AL8), nasccSupplier, 2, FALSE), IF(AI8 = 2.1, VLOOKUP(TRIM(AL8), nasccSupplier, 2, FALSE), IF(AI8 = 2.2, VLOOKUP(TRIM(AL8), nasccSupplier, 2, FALSE), IF(AI8 = 3, VLOOKUP(TRIM(AL8), euemSupplier, 2, FALSE), IF(AI8 = 4, VLOOKUP(TRIM(AL8), wgtssSupplier, 2, FALSE), IF(AI8 = 5, VLOOKUP(TRIM(AL8), wgtmSupplier, 2, FALSE), IF(AI8 = 7, VLOOKUP(TRIM(AL8), asmSupplier, 2, FALSE), "")))))))) | AH8: =IF(C8 <> "", VLOOKUP(C8, oneOffs, 2, FALSE), "") | AI8: =IF(D8 <> "", VLOOKUP(D8, seriesCodeClasses, 2, FALSE), 0) -> 0 | AJ8: =IF(AL8 <> "", VLOOKUP(AL8, classIndexes, 2, FALSE), 0) -> 0 | AK8: =IF(AI8 = 0, "", IF(AI8 = 1, VLOOKUP(K8, gemClasses, 2, FALSE), IF(AI8 = 2, VLOOKUP(K8, nasccClasses, 2, FALSE), IF(AI8 = 2.1, VLOOKUP(K8, nasccClasses, 2, FALSE), IF(AI8 = 2.2, VLOOKUP(K8, nasccClasses, 2, FALSE), IF(AI8 = 3, VLOOKUP(K8, euemClasses, 2, FALSE), IF(AI8 = 4, VLOOKUP(K8, wgtssClasses, 2, FALSE), IF(AI8 = 5, VLOOKUP(K8, wgtmClasses, 2, FALSE), IF(AI8 = 6, VLOOKUP(K8, wpcClasses, 2, FALSE), IF(AI8 = 7, VLOOKUP(K8, asmClasses, 2, FALSE), "")))))))))) | AL8: =IF(AI8 = 1, AN8, IF(AI8 = 5, AO8, AK8)) | AN8: =IF(AND(IF(AK8 = "LMGTE PRO", TRUE, FALSE), IF(O8 = "Bronze", TRUE, FALSE)), "LMGTE AM", AK8) | AO8: =IF(AND(IF(AK8 = "GT3-P", TRUE, FALSE), IF(O8 = "Bronze", TRUE, FALSE)), "GT3-A", AK8) | AQ8: ='Lineup Legality - OOE'!L13 | AS8: =IF(J8 <> "", CONCATENATE("$", ROUND(SUM('Total Costs'!AZ7:BI7), 3), " Million"), "")
B9: =IF(D9 <> "", B8 + 1, "") | D9: =IF(ISERROR(AH9), "", AH9) | E9: =IF(ISERROR(AL9), "", AL9) | H9: =IF(ISERROR(AF9), "", IF(AF9 = 0, "", AF9)) | K9: =IF(ISERROR(AC9), "", AC9) | L9: =IF(ISERROR(AD9), "", AD9) | Q9: ='Lineup Legality - OOE'!L17 | W9: =IF(ISERROR(AS9), "", AS9) | Z9: Class Field will Automatically fill in based on the Series and Desired Car Model Provided | AC9: =IF(J9 <> "", IF(VLOOKUP(J9, purchasedCars, 2, FALSE) = "", "", VLOOKUP(J9, purchasedCars, 2, FALSE)),"") | AD9: =IF(J9 <> "", IF(VLOOKUP(J9, purchasedCars, 3, FALSE) = "", "", VLOOKUP(J9, purchasedCars, 3, FALSE)),"") | AF9: =IF(AI9 = 1, VLOOKUP(TRIM(AL9), gemSupplier, 2, FALSE), IF(AI9 = 2, VLOOKUP(TRIM(AL9), nasccSupplier, 2, FALSE), IF(AI9 = 2.1, VLOOKUP(TRIM(AL9), nasccSupplier, 2, FALSE), IF(AI9 = 2.2, VLOOKUP(TRIM(AL9), nasccSupplier, 2, FALSE), IF(AI9 = 3, VLOOKUP(TRIM(AL9), euemSupplier, 2, FALSE), IF(AI9 = 4, VLOOKUP(TRIM(AL9), wgtssSupplier, 2, FALSE), IF(AI9 = 5, VLOOKUP(TRIM(AL9), wgtmSupplier, 2, FALSE), IF(AI9 = 7, VLOOKUP(TRIM(AL9), asmSupplier, 2, FALSE), "")))))))) | AH9: =IF(C9 <> "", VLOOKUP(C9, oneOffs, 2, FALSE), "") | AI9: =IF(D9 <> "", VLOOKUP(D9, seriesCodeClasses, 2, FALSE), 0) -> 0 | AJ9: =IF(AL9 <> "", VLOOKUP(AL9, classIndexes, 2, FALSE), 0) -> 0 | AK9: =IF(AI9 = 0, "", IF(AI9 = 1, VLOOKUP(K9, gemClasses, 2, FALSE), IF(AI9 = 2, VLOOKUP(K9, nasccClasses, 2, FALSE), IF(AI9 = 2.1, VLOOKUP(K9, nasccClasses, 2, FALSE), IF(AI9 = 2.2, VLOOKUP(K9, nasccClasses, 2, FALSE), IF(AI9 = 3, VLOOKUP(K9, euemClasses, 2, FALSE), IF(AI9 = 4, VLOOKUP(K9, wgtssClasses, 2, FALSE), IF(AI9 = 5, VLOOKUP(K9, wgtmClasses, 2, FALSE), IF(AI9 = 6, VLOOKUP(K9, wpcClasses, 2, FALSE), IF(AI9 = 7, VLOOKUP(K9, asmClasses, 2, FALSE), "")))))))))) | AL9: =IF(AI9 = 1, AN9, IF(AI9 = 5, AO9, AK9)) | AN9: =IF(AND(IF(AK9 = "LMGTE PRO", TRUE, FALSE), IF(O9 = "Bronze", TRUE, FALSE)), "LMGTE AM", AK9) | AO9: =IF(AND(IF(AK9 = "GT3-P", TRUE, FALSE), IF(O9 = "Bronze", TRUE, FALSE)), "GT3-A", AK9) | AQ9: ='Lineup Legality - OOE'!L17 | AS9: =IF(J9 <> "", CONCATENATE("$", ROUND(SUM('Total Costs'!AZ8:BI8), 3), " Million"), "")
B10: =IF(D10 <> "", B9 + 1, "") | D10: =IF(ISERROR(AH10), "", AH10) | E10: =IF(ISERROR(AL10), "", AL10) | H10: =IF(ISERROR(AF10), "", IF(AF10 = 0, "", AF10)) | K10: =IF(ISERROR(AC10), "", AC10) | L10: =IF(ISERROR(AD10), "", AD10) | Q10: ='Lineup Legality - OOE'!L21 | W10: =IF(ISERROR(AS10), "", AS10) | AC10: =IF(J10 <> "", IF(VLOOKUP(J10, purchasedCars, 2, FALSE) = "", "", VLOOKUP(J10, purchasedCars, 2, FALSE)),"") | AD10: =IF(J10 <> "", IF(VLOOKUP(J10, purchasedCars, 3, FALSE) = "", "", VLOOKUP(J10, purchasedCars, 3, FALSE)),"") | AF10: =IF(AI10 = 1, VLOOKUP(TRIM(AL10), gemSupplier, 2, FALSE), IF(AI10 = 2, VLOOKUP(TRIM(AL10), nasccSupplier, 2, FALSE), IF(AI10 = 2.1, VLOOKUP(TRIM(AL10), nasccSupplier, 2, FALSE), IF(AI10 = 2.2, VLOOKUP(TRIM(AL10), nasccSupplier, 2, FALSE), IF(AI10 = 3, VLOOKUP(TRIM(AL10), euemSupplier, 2, FALSE), IF(AI10 = 4, VLOOKUP(TRIM(AL10), wgtssSupplier, 2, FALSE), IF(AI10 = 5, VLOOKUP(TRIM(AL10), wgtmSupplier, 2, FALSE), IF(AI10 = 7, VLOOKUP(TRIM(AL10), asmSupplier, 2, FALSE), "")))))))) | AH10: =IF(C10 <> "", VLOOKUP(C10, oneOffs, 2, FALSE), "") | AI10: =IF(D10 <> "", VLOOKUP(D10, seriesCodeClasses, 2, FALSE), 0) -> 0 | AJ10: =IF(AL10 <> "", VLOOKUP(AL10, classIndexes, 2, FALSE), 0) -> 0 | AK10: =IF(AI10 = 0, "", IF(AI10 = 1, VLOOKUP(K10, gemClasses, 2, FALSE), IF(AI10 = 2, VLOOKUP(K10, nasccClasses, 2, FALSE), IF(AI10 = 2.1, VLOOKUP(K10, nasccClasses, 2, FALSE), IF(AI10 = 2.2, VLOOKUP(K10, nasccClasses, 2, FALSE), IF(AI10 = 3, VLOOKUP(K10, euemClasses, 2, FALSE), IF(AI10 = 4, VLOOKUP(K10, wgtssClasses, 2, FALSE), IF(AI10 = 5, VLOOKUP(K10, wgtmClasses, 2, FALSE), IF(AI10 = 6, VLOOKUP(K10, wpcClasses, 2, FALSE), IF(AI10 = 7, VLOOKUP(K10, asmClasses, 2, FALSE), "")))))))))) | AL10: =IF(AI10 = 1, AN10, IF(AI10 = 5, AO10, AK10)) | AN10: =IF(AND(IF(AK10 = "LMGTE PRO", TRUE, FALSE), IF(O10 = "Bronze", TRUE, FALSE)), "LMGTE AM", AK10) | AO10: =IF(AND(IF(AK10 = "GT3-P", TRUE, FALSE), IF(O10 = "Bronze", TRUE, FALSE)), "GT3-A", AK10) | AQ10: ='Lineup Legality - OOE'!L21 | AS10: =IF(J10 <> "", CONCATENATE("$", ROUND(SUM('Total Costs'!AZ9:BI9), 3), " Million"), "")
B11: =IF(D11 <> "", B10 + 1, "") | D11: =IF(ISERROR(AH11), "", AH11) | E11: =IF(ISERROR(AL11), "", AL11) | H11: =IF(ISERROR(AF11), "", IF(AF11 = 0, "", AF11)) | K11: =IF(ISERROR(AC11), "", AC11) | L11: =IF(ISERROR(AD11), "", AD11) | Q11: ='Lineup Legality - OOE'!L25 | W11: =IF(ISERROR(AS11), "", AS11) | AC11: =IF(J11 <> "", IF(VLOOKUP(J11, purchasedCars, 2, FALSE) = "", "", VLOOKUP(J11, purchasedCars, 2, FALSE)),"") | AD11: =IF(J11 <> "", IF(VLOOKUP(J11, purchasedCars, 3, FALSE) = "", "", VLOOKUP(J11, purchasedCars, 3, FALSE)),"") | AF11: =IF(AI11 = 1, VLOOKUP(TRIM(AL11), gemSupplier, 2, FALSE), IF(AI11 = 2, VLOOKUP(TRIM(AL11), nasccSupplier, 2, FALSE), IF(AI11 = 2.1, VLOOKUP(TRIM(AL11), nasccSupplier, 2, FALSE), IF(AI11 = 2.2, VLOOKUP(TRIM(AL11), nasccSupplier, 2, FALSE), IF(AI11 = 3, VLOOKUP(TRIM(AL11), euemSupplier, 2, FALSE), IF(AI11 = 4, VLOOKUP(TRIM(AL11), wgtssSupplier, 2, FALSE), IF(AI11 = 5, VLOOKUP(TRIM(AL11), wgtmSupplier, 2, FALSE), IF(AI11 = 7, VLOOKUP(TRIM(AL11), asmSupplier, 2, FALSE), "")))))))) | AH11: =IF(C11 <> "", VLOOKUP(C11, oneOffs, 2, FALSE), "") | AI11: =IF(D11 <> "", VLOOKUP(D11, seriesCodeClasses, 2, FALSE), 0) -> 0 | AJ11: =IF(AL11 <> "", VLOOKUP(AL11, classIndexes, 2, FALSE), 0) -> 0 | AK11: =IF(AI11 = 0, "", IF(AI11 = 1, VLOOKUP(K11, gemClasses, 2, FALSE), IF(AI11 = 2, VLOOKUP(K11, nasccClasses, 2, FALSE), IF(AI11 = 2.1, VLOOKUP(K11, nasccClasses, 2, FALSE), IF(AI11 = 2.2, VLOOKUP(K11, nasccClasses, 2, FALSE), IF(AI11 = 3, VLOOKUP(K11, euemClasses, 2, FALSE), IF(AI11 = 4, VLOOKUP(K11, wgtssClasses, 2, FALSE), IF(AI11 = 5, VLOOKUP(K11, wgtmClasses, 2, FALSE), IF(AI11 = 6, VLOOKUP(K11, wpcClasses, 2, FALSE), IF(AI11 = 7, VLOOKUP(K11, asmClasses, 2, FALSE), "")))))))))) | AL11: =IF(AI11 = 1, AN11, IF(AI11 = 5, AO11, AK11)) | AN11: =IF(AND(IF(AK11 = "LMGTE PRO", TRUE, FALSE), IF(O11 = "Bronze", TRUE, FALSE)), "LMGTE AM", AK11) | AO11: =IF(AND(IF(AK11 = "GT3-P", TRUE, FALSE), IF(O11 = "Bronze", TRUE, FALSE)), "GT3-A", AK11) | AQ11: ='Lineup Legality - OOE'!L25 | AS11: =IF(J11 <> "", CONCATENATE("$", ROUND(SUM('Total Costs'!AZ10:BI10), 3), " Million"), "")
B12: =IF(D12 <> "", B11 + 1, "") | D12: =IF(ISERROR(AH12), "", AH12) | E12: =IF(ISERROR(AL12), "", AL12) | H12: =IF(ISERROR(AF12), "", IF(AF12 = 0, "", AF12)) | K12: =IF(ISERROR(AC12), "", AC12) | L12: =IF(ISERROR(AD12), "", AD12) | Q12: ='Lineup Legality - OOE'!L29 | W12: =IF(ISERROR(AS12), "", AS12) | Z12: Only Driver Rankings can be entered in the Driver Details Columns, Real Driver Names will not be accepted | AC12: =IF(J12 <> "", IF(VLOOKUP(J12, purchasedCars, 2, FALSE) = "", "", VLOOKUP(J12, purchasedCars, 2, FALSE)),"") | AD12: =IF(J12 <> "", IF(VLOOKUP(J12, purchasedCars, 3, FALSE) = "", "", VLOOKUP(J12, purchasedCars, 3, FALSE)),"") | AF12: =IF(AI12 = 1, VLOOKUP(TRIM(AL12), gemSupplier, 2, FALSE), IF(AI12 = 2, VLOOKUP(TRIM(AL12), nasccSupplier, 2, FALSE), IF(AI12 = 2.1, VLOOKUP(TRIM(AL12), nasccSupplier, 2, FALSE), IF(AI12 = 2.2, VLOOKUP(TRIM(AL12), nasccSupplier, 2, FALSE), IF(AI12 = 3, VLOOKUP(TRIM(AL12), euemSupplier, 2, FALSE), IF(AI12 = 4, VLOOKUP(TRIM(AL12), wgtssSupplier, 2, FALSE), IF(AI12 = 5, VLOOKUP(TRIM(AL12), wgtmSupplier, 2, FALSE), IF(AI12 = 7, VLOOKUP(TRIM(AL12), asmSupplier, 2, FALSE), "")))))))) | AH12: =IF(C12 <> "", VLOOKUP(C12, oneOffs, 2, FALSE), "") | AI12: =IF(D12 <> "", VLOOKUP(D12, seriesCodeClasses, 2, FALSE), 0) -> 0 | AJ12: =IF(AL12 <> "", VLOOKUP(AL12, classIndexes, 2, FALSE), 0) -> 0 | AK12: =IF(AI12 = 0, "", IF(AI12 = 1, VLOOKUP(K12, gemClasses, 2, FALSE), IF(AI12 = 2, VLOOKUP(K12, nasccClasses, 2, FALSE), IF(AI12 = 2.1, VLOOKUP(K12, nasccClasses, 2, FALSE), IF(AI12 = 2.2, VLOOKUP(K12, nasccClasses, 2, FALSE), IF(AI12 = 3, VLOOKUP(K12, euemClasses, 2, FALSE), IF(AI12 = 4, VLOOKUP(K12, wgtssClasses, 2, FALSE), IF(AI12 = 5, VLOOKUP(K12, wgtmClasses, 2, FALSE), IF(AI12 = 6, VLOOKUP(K12, wpcClasses, 2, FALSE), IF(AI12 = 7, VLOOKUP(K12, asmClasses, 2, FALSE), "")))))))))) | AL12: =IF(AI12 = 1, AN12, IF(AI12 = 5, AO12, AK12)) | AN12: =IF(AND(IF(AK12 = "LMGTE PRO", TRUE, FALSE), IF(O12 = "Bronze", TRUE, FALSE)), "LMGTE AM", AK12) | AO12: =IF(AND(IF(AK12 = "GT3-P", TRUE, FALSE), IF(O12 = "Bronze", TRUE, FALSE)), "GT3-A", AK12) | AQ12: ='Lineup Legality - OOE'!L29 | AS12: =IF(J12 <> "", CONCATENATE("$", ROUND(SUM('Total Costs'!AZ11:BI11), 3), " Million"), "")
B13: =IF(D13 <> "", B12 + 1, "") | D13: =IF(ISERROR(AH13), "", AH13) | E13: =IF(ISERROR(AL13), "", AL13) | H13: =IF(ISERROR(AF13), "", IF(AF13 = 0, "", AF13)) | K13: =IF(ISERROR(AC13), "", AC13) | L13: =IF(ISERROR(AD13), "", AD13) | Q13: ='Lineup Legality - OOE'!L33 | W13: =IF(ISERROR(AS13), "", AS13) | AC13: =IF(J13 <> "", IF(VLOOKUP(J13, purchasedCars, 2, FALSE) = "", "", VLOOKUP(J13, purchasedCars, 2, FALSE)),"") | AD13: =IF(J13 <> "", IF(VLOOKUP(J13, purchasedCars, 3, FALSE) = "", "", VLOOKUP(J13, purchasedCars, 3, FALSE)),"") | AF13: =IF(AI13 = 1, VLOOKUP(TRIM(AL13), gemSupplier, 2, FALSE), IF(AI13 = 2, VLOOKUP(TRIM(AL13), nasccSupplier, 2, FALSE), IF(AI13 = 2.1, VLOOKUP(TRIM(AL13), nasccSupplier, 2, FALSE), IF(AI13 = 2.2, VLOOKUP(TRIM(AL13), nasccSupplier, 2, FALSE), IF(AI13 = 3, VLOOKUP(TRIM(AL13), euemSupplier, 2, FALSE), IF(AI13 = 4, VLOOKUP(TRIM(AL13), wgtssSupplier, 2, FALSE), IF(AI13 = 5, VLOOKUP(TRIM(AL13), wgtmSupplier, 2, FALSE), IF(AI13 = 7, VLOOKUP(TRIM(AL13), asmSupplier, 2, FALSE), "")))))))) | AH13: =IF(C13 <> "", VLOOKUP(C13, oneOffs, 2, FALSE), "") | AI13: =IF(D13 <> "", VLOOKUP(D13, seriesCodeClasses, 2, FALSE), 0) -> 0 | AJ13: =IF(AL13 <> "", VLOOKUP(AL13, classIndexes, 2, FALSE), 0) -> 0 | AK13: =IF(AI13 = 0, "", IF(AI13 = 1, VLOOKUP(K13, gemClasses, 2, FALSE), IF(AI13 = 2, VLOOKUP(K13, nasccClasses, 2, FALSE), IF(AI13 = 2.1, VLOOKUP(K13, nasccClasses, 2, FALSE), IF(AI13 = 2.2, VLOOKUP(K13, nasccClasses, 2, FALSE), IF(AI13 = 3, VLOOKUP(K13, euemClasses, 2, FALSE), IF(AI13 = 4, VLOOKUP(K13, wgtssClasses, 2, FALSE), IF(AI13 = 5, VLOOKUP(K13, wgtmClasses, 2, FALSE), IF(AI13 = 6, VLOOKUP(K13, wpcClasses, 2, FALSE), IF(AI13 = 7, VLOOKUP(K13, asmClasses, 2, FALSE), "")))))))))) | AL13: =IF(AI13 = 1, AN13, IF(AI13 = 5, AO13, AK13)) | AN13: =IF(AND(IF(AK13 = "LMGTE PRO", TRUE, FALSE), IF(O13 = "Bronze", TRUE, FALSE)), "LMGTE AM", AK13) | AO13: =IF(AND(IF(AK13 = "GT3-P", TRUE, FALSE), IF(O13 = "Bronze", TRUE, FALSE)), "GT3-A", AK13) | AQ13: ='Lineup Legality - OOE'!L33 | AS13: =IF(J13 <> "", CONCATENATE("$", ROUND(SUM('Total Costs'!AZ12:BI12), 3), " Million"), "")
B14: =IF(D14 <> "", B13 + 1, "") | D14: =IF(ISERROR(AH14), "", AH14) | E14: =IF(ISERROR(AL14), "", AL14) | H14: =IF(ISERROR(AF14), "", IF(AF14 = 0, "", AF14)) | K14: =IF(ISERROR(AC14), "", AC14) | L14: =IF(ISERROR(AD14), "", AD14) | Q14: ='Lineup Legality - OOE'!L37 | W14: =IF(ISERROR(AS14), "", AS14) | AC14: =IF(J14 <> "", IF(VLOOKUP(J14, purchasedCars, 2, FALSE) = "", "", VLOOKUP(J14, purchasedCars, 2, FALSE)),"") | AD14: =IF(J14 <> "", IF(VLOOKUP(J14, purchasedCars, 3, FALSE) = "", "", VLOOKUP(J14, purchasedCars, 3, FALSE)),"") | AF14: =IF(AI14 = 1, VLOOKUP(TRIM(AL14), gemSupplier, 2, FALSE), IF(AI14 = 2, VLOOKUP(TRIM(AL14), nasccSupplier, 2, FALSE), IF(AI14 = 2.1, VLOOKUP(TRIM(AL14), nasccSupplier, 2, FALSE), IF(AI14 = 2.2, VLOOKUP(TRIM(AL14), nasccSupplier, 2, FALSE), IF(AI14 = 3, VLOOKUP(TRIM(AL14), euemSupplier, 2, FALSE), IF(AI14 = 4, VLOOKUP(TRIM(AL14), wgtssSupplier, 2, FALSE), IF(AI14 = 5, VLOOKUP(TRIM(AL14), wgtmSupplier, 2, FALSE), IF(AI14 = 7, VLOOKUP(TRIM(AL14), asmSupplier, 2, FALSE), "")))))))) | AH14: =IF(C14 <> "", VLOOKUP(C14, oneOffs, 2, FALSE), "") | AI14: =IF(D14 <> "", VLOOKUP(D14, seriesCodeClasses, 2, FALSE), 0) -> 0 | AJ14: =IF(AL14 <> "", VLOOKUP(AL14, classIndexes, 2, FALSE), 0) -> 0 | AK14: =IF(AI14 = 0, "", IF(AI14 = 1, VLOOKUP(K14, gemClasses, 2, FALSE), IF(AI14 = 2, VLOOKUP(K14, nasccClasses, 2, FALSE), IF(AI14 = 2.1, VLOOKUP(K14, nasccClasses, 2, FALSE), IF(AI14 = 2.2, VLOOKUP(K14, nasccClasses, 2, FALSE), IF(AI14 = 3, VLOOKUP(K14, euemClasses, 2, FALSE), IF(AI14 = 4, VLOOKUP(K14, wgtssClasses, 2, FALSE), IF(AI14 = 5, VLOOKUP(K14, wgtmClasses, 2, FALSE), IF(AI14 = 6, VLOOKUP(K14, wpcClasses, 2, FALSE), IF(AI14 = 7, VLOOKUP(K14, asmClasses, 2, FALSE), "")))))))))) | AL14: =IF(AI14 = 1, AN14, IF(AI14 = 5, AO14, AK14)) | AN14: =IF(AND(IF(AK14 = "LMGTE PRO", TRUE, FALSE), IF(O14 = "Bronze", TRUE, FALSE)), "LMGTE AM", AK14) | AO14: =IF(AND(IF(AK14 = "GT3-P", TRUE, FALSE), IF(O14 = "Bronze", TRUE, FALSE)), "GT3-A", AK14) | AQ14: ='Lineup Legality - OOE'!L37 | AS14: =IF(J14 <> "", CONCATENATE("$", ROUND(SUM('Total Costs'!AZ13:BI13), 3), " Million"), "")
B15: =IF(D15 <> "", B14 + 1, "") | D15: =IF(ISERROR(AH15), "", AH15) | E15: =IF(ISERROR(AL15), "", AL15) | H15: =IF(ISERROR(AF15), "", IF(AF15 = 0, "", AF15)) | K15: =IF(ISERROR(AC15), "", AC15) | L15: =IF(ISERROR(AD15), "", AD15) | Q15: ='Lineup Legality - OOE'!L41 | W15: =IF(ISERROR(AS15), "", AS15) | Z15: Please Enter Setup Bonus Areas as their names listed in 'Setup Bonuses' | AC15: =IF(J15 <> "", IF(VLOOKUP(J15, purchasedCars, 2, FALSE) = "", "", VLOOKUP(J15, purchasedCars, 2, FALSE)),"") | AD15: =IF(J15 <> "", IF(VLOOKUP(J15, purchasedCars, 3, FALSE) = "", "", VLOOKUP(J15, purchasedCars, 3, FALSE)),"") | AF15: =IF(AI15 = 1, VLOOKUP(TRIM(AL15), gemSupplier, 2, FALSE), IF(AI15 = 2, VLOOKUP(TRIM(AL15), nasccSupplier, 2, FALSE), IF(AI15 = 2.1, VLOOKUP(TRIM(AL15), nasccSupplier, 2, FALSE), IF(AI15 = 2.2, VLOOKUP(TRIM(AL15), nasccSupplier, 2, FALSE), IF(AI15 = 3, VLOOKUP(TRIM(AL15), euemSupplier, 2, FALSE), IF(AI15 = 4, VLOOKUP(TRIM(AL15), wgtssSupplier, 2, FALSE), IF(AI15 = 5, VLOOKUP(TRIM(AL15), wgtmSupplier, 2, FALSE), IF(AI15 = 7, VLOOKUP(TRIM(AL15), asmSupplier, 2, FALSE), "")))))))) | AH15: =IF(C15 <> "", VLOOKUP(C15, oneOffs, 2, FALSE), "") | AI15: =IF(D15 <> "", VLOOKUP(D15, seriesCodeClasses, 2, FALSE), 0) -> 0 | AJ15: =IF(AL15 <> "", VLOOKUP(AL15, classIndexes, 2, FALSE), 0) -> 0 | AK15: =IF(AI15 = 0, "", IF(AI15 = 1, VLOOKUP(K15, gemClasses, 2, FALSE), IF(AI15 = 2, VLOOKUP(K15, nasccClasses, 2, FALSE), IF(AI15 = 2.1, VLOOKUP(K15, nasccClasses, 2, FALSE), IF(AI15 = 2.2, VLOOKUP(K15, nasccClasses, 2, FALSE), IF(AI15 = 3, VLOOKUP(K15, euemClasses, 2, FALSE), IF(AI15 = 4, VLOOKUP(K15, wgtssClasses, 2, FALSE), IF(AI15 = 5, VLOOKUP(K15, wgtmClasses, 2, FALSE), IF(AI15 = 6, VLOOKUP(K15, wpcClasses, 2, FALSE), IF(AI15 = 7, VLOOKUP(K15, asmClasses, 2, FALSE), "")))))))))) | AL15: =IF(AI15 = 1, AN15, IF(AI15 = 5, AO15, AK15)) | AN15: =IF(AND(IF(AK15 = "LMGTE PRO", TRUE, FALSE), IF(O15 = "Bronze", TRUE, FALSE)), "LMGTE AM", AK15) | AO15: =IF(AND(IF(AK15 = "GT3-P", TRUE, FALSE), IF(O15 = "Bronze", TRUE, FALSE)), "GT3-A", AK15) | AQ15: ='Lineup Legality - OOE'!L41 | AS15: =IF(J15 <> "", CONCATENATE("$", ROUND(SUM('Total Costs'!AZ14:BI14), 3), " Million"), "")
B16: =IF(D16 <> "", B15 + 1, "") | D16: =IF(ISERROR(AH16), "", AH16) | E16: =IF(ISERROR(AL16), "", AL16) | H16: =IF(ISERROR(AF16), "", IF(AF16 = 0, "", AF16)) | K16: =IF(ISERROR(AC16), "", AC16) | L16: =IF(ISERROR(AD16), "", AD16) | Q16: ='Lineup Legality - OOE'!L45 | W16: =IF(ISERROR(AS16), "", AS16) | AC16: =IF(J16 <> "", IF(VLOOKUP(J16, purchasedCars, 2, FALSE) = "", "", VLOOKUP(J16, purchasedCars, 2, FALSE)),"") | AD16: =IF(J16 <> "", IF(VLOOKUP(J16, purchasedCars, 3, FALSE) = "", "", VLOOKUP(J16, purchasedCars, 3, FALSE)),"") | AF16: =IF(AI16 = 1, VLOOKUP(TRIM(AL16), gemSupplier, 2, FALSE), IF(AI16 = 2, VLOOKUP(TRIM(AL16), nasccSupplier, 2, FALSE), IF(AI16 = 2.1, VLOOKUP(TRIM(AL16), nasccSupplier, 2, FALSE), IF(AI16 = 2.2, VLOOKUP(TRIM(AL16), nasccSupplier, 2, FALSE), IF(AI16 = 3, VLOOKUP(TRIM(AL16), euemSupplier, 2, FALSE), IF(AI16 = 4, VLOOKUP(TRIM(AL16), wgtssSupplier, 2, FALSE), IF(AI16 = 5, VLOOKUP(TRIM(AL16), wgtmSupplier, 2, FALSE), IF(AI16 = 7, VLOOKUP(TRIM(AL16), asmSupplier, 2, FALSE), "")))))))) | AH16: =IF(C16 <> "", VLOOKUP(C16, oneOffs, 2, FALSE), "") | AI16: =IF(D16 <> "", VLOOKUP(D16, seriesCodeClasses, 2, FALSE), 0) -> 0 | AJ16: =IF(AL16 <> "", VLOOKUP(AL16, classIndexes, 2, FALSE), 0) -> 0 | AK16: =IF(AI16 = 0, "", IF(AI16 = 1, VLOOKUP(K16, gemClasses, 2, FALSE), IF(AI16 = 2, VLOOKUP(K16, nasccClasses, 2, FALSE), IF(AI16 = 2.1, VLOOKUP(K16, nasccClasses, 2, FALSE), IF(AI16 = 2.2, VLOOKUP(K16, nasccClasses, 2, FALSE), IF(AI16 = 3, VLOOKUP(K16, euemClasses, 2, FALSE), IF(AI16 = 4, VLOOKUP(K16, wgtssClasses, 2, FALSE), IF(AI16 = 5, VLOOKUP(K16, wgtmClasses, 2, FALSE), IF(AI16 = 6, VLOOKUP(K16, wpcClasses, 2, FALSE), IF(AI16 = 7, VLOOKUP(K16, asmClasses, 2, FALSE), "")))))))))) | AL16: =IF(AI16 = 1, AN16, IF(AI16 = 5, AO16, AK16)) | AN16: =IF(AND(IF(AK16 = "LMGTE PRO", TRUE, FALSE), IF(O16 = "Bronze", TRUE, FALSE)), "LMGTE AM", AK16) | AO16: =IF(AND(IF(AK16 = "GT3-P", TRUE, FALSE), IF(O16 = "Bronze", TRUE, FALSE)), "GT3-A", AK16) | AQ16: ='Lineup Legality - OOE'!L45 | AS16: =IF(J16 <> "", CONCATENATE("$", ROUND(SUM('Total Costs'!AZ15:BI15), 3), " Million"), "")
B17: =IF(D17 <> "", B16 + 1, "") | D17: =IF(ISERROR(AH17), "", AH17) | E17: =IF(ISERROR(AL17), "", AL17) | H17: =IF(ISERROR(AF17), "", IF(AF17 = 0, "", AF17)) | K17: =IF(ISERROR(AC17), "", AC17) | L17: =IF(ISERROR(AD17), "", AD17) | Q17: ='Lineup Legality - OOE'!L49 | W17: =IF(ISERROR(AS17), "", AS17) | Z17: Enter Bonus Levels as "LX", where X is the Level Number (ie L2 for Level 2) | AC17: =IF(J17 <> "", IF(VLOOKUP(J17, purchasedCars, 2, FALSE) = "", "", VLOOKUP(J17, purchasedCars, 2, FALSE)),"") | AD17: =IF(J17 <> "", IF(VLOOKUP(J17, purchasedCars, 3, FALSE) = "", "", VLOOKUP(J17, purchasedCars, 3, FALSE)),"") | AF17: =IF(AI17 = 1, VLOOKUP(TRIM(AL17), gemSupplier, 2, FALSE), IF(AI17 = 2, VLOOKUP(TRIM(AL17), nasccSupplier, 2, FALSE), IF(AI17 = 2.1, VLOOKUP(TRIM(AL17), nasccSupplier, 2, FALSE), IF(AI17 = 2.2, VLOOKUP(TRIM(AL17), nasccSupplier, 2, FALSE), IF(AI17 = 3, VLOOKUP(TRIM(AL17), euemSupplier, 2, FALSE), IF(AI17 = 4, VLOOKUP(TRIM(AL17), wgtssSupplier, 2, FALSE), IF(AI17 = 5, VLOOKUP(TRIM(AL17), wgtmSupplier, 2, FALSE), IF(AI17 = 7, VLOOKUP(TRIM(AL17), asmSupplier, 2, FALSE), "")))))))) | AH17: =IF(C17 <> "", VLOOKUP(C17, oneOffs, 2, FALSE), "") | AI17: =IF(D17 <> "", VLOOKUP(D17, seriesCodeClasses, 2, FALSE), 0) -> 0 | AJ17: =IF(AL17 <> "", VLOOKUP(AL17, classIndexes, 2, FALSE), 0) -> 0 | AK17: =IF(AI17 = 0, "", IF(AI17 = 1, VLOOKUP(K17, gemClasses, 2, FALSE), IF(AI17 = 2, VLOOKUP(K17, nasccClasses, 2, FALSE), IF(AI17 = 2.1, VLOOKUP(K17, nasccClasses, 2, FALSE), IF(AI17 = 2.2, VLOOKUP(K17, nasccClasses, 2, FALSE), IF(AI17 = 3, VLOOKUP(K17, euemClasses, 2, FALSE), IF(AI17 = 4, VLOOKUP(K17, wgtssClasses, 2, FALSE), IF(AI17 = 5, VLOOKUP(K17, wgtmClasses, 2, FALSE), IF(AI17 = 6, VLOOKUP(K17, wpcClasses, 2, FALSE), IF(AI17 = 7, VLOOKUP(K17, asmClasses, 2, FALSE), "")))))))))) | AL17: =IF(AI17 = 1, AN17, IF(AI17 = 5, AO17, AK17)) | AN17: =IF(AND(IF(AK17 = "LMGTE PRO", TRUE, FALSE), IF(O17 = "Bronze", TRUE, FALSE)), "LMGTE AM", AK17) | AO17: =IF(AND(IF(AK17 = "GT3-P", TRUE, FALSE), IF(O17 = "Bronze", TRUE, FALSE)), "GT3-A", AK17) | AQ17: ='Lineup Legality - OOE'!L49 | AS17: =IF(J17 <> "", CONCATENATE("$", ROUND(SUM('Total Costs'!AZ16:BI16), 3), " Million"), "")
B18: =IF(D18 <> "", B17 + 1, "") | D18: =IF(ISERROR(AH18), "", AH18) | E18: =IF(ISERROR(AL18), "", AL18) | H18: =IF(ISERROR(AF18), "", IF(AF18 = 0, "", AF18)) | K18: =IF(ISERROR(AC18), "", AC18) | L18: =IF(ISERROR(AD18), "", AD18) | Q18: ='Lineup Legality - OOE'!L53 | W18: =IF(ISERROR(AS18), "", AS18) | AC18: =IF(J18 <> "", IF(VLOOKUP(J18, purchasedCars, 2, FALSE) = "", "", VLOOKUP(J18, purchasedCars, 2, FALSE)),"") | AD18: =IF(J18 <> "", IF(VLOOKUP(J18, purchasedCars, 3, FALSE) = "", "", VLOOKUP(J18, purchasedCars, 3, FALSE)),"") | AF18: =IF(AI18 = 1, VLOOKUP(TRIM(AL18), gemSupplier, 2, FALSE), IF(AI18 = 2, VLOOKUP(TRIM(AL18), nasccSupplier, 2, FALSE), IF(AI18 = 2.1, VLOOKUP(TRIM(AL18), nasccSupplier, 2, FALSE), IF(AI18 = 2.2, VLOOKUP(TRIM(AL18), nasccSupplier, 2, FALSE), IF(AI18 = 3, VLOOKUP(TRIM(AL18), euemSupplier, 2, FALSE), IF(AI18 = 4, VLOOKUP(TRIM(AL18), wgtssSupplier, 2, FALSE), IF(AI18 = 5, VLOOKUP(TRIM(AL18), wgtmSupplier, 2, FALSE), IF(AI18 = 7, VLOOKUP(TRIM(AL18), asmSupplier, 2, FALSE), "")))))))) | AH18: =IF(C18 <> "", VLOOKUP(C18, oneOffs, 2, FALSE), "") | AI18: =IF(D18 <> "", VLOOKUP(D18, seriesCodeClasses, 2, FALSE), 0) -> 0 | AJ18: =IF(AL18 <> "", VLOOKUP(AL18, classIndexes, 2, FALSE), 0) -> 0 | AK18: =IF(AI18 = 0, "", IF(AI18 = 1, VLOOKUP(K18, gemClasses, 2, FALSE), IF(AI18 = 2, VLOOKUP(K18, nasccClasses, 2, FALSE), IF(AI18 = 2.1, VLOOKUP(K18, nasccClasses, 2, FALSE), IF(AI18 = 2.2, VLOOKUP(K18, nasccClasses, 2, FALSE), IF(AI18 = 3, VLOOKUP(K18, euemClasses, 2, FALSE), IF(AI18 = 4, VLOOKUP(K18, wgtssClasses, 2, FALSE), IF(AI18 = 5, VLOOKUP(K18, wgtmClasses, 2, FALSE), IF(AI18 = 6, VLOOKUP(K18, wpcClasses, 2, FALSE), IF(AI18 = 7, VLOOKUP(K18, asmClasses, 2, FALSE), "")))))))))) | AL18: =IF(AI18 = 1, AN18, IF(AI18 = 5, AO18, AK18)) | AN18: =IF(AND(IF(AK18 = "LMGTE PRO", TRUE, FALSE), IF(O18 = "Bronze", TRUE, FALSE)), "LMGTE AM", AK18) | AO18: =IF(AND(IF(AK18 = "GT3-P", TRUE, FALSE), IF(O18 = "Bronze", TRUE, FALSE)), "GT3-A", AK18) | AQ18: ='Lineup Legality - OOE'!L53 | AS18: =IF(J18 <> "", CONCATENATE("$", ROUND(SUM('Total Costs'!AZ17:BI17), 3), " Million"), "")
B19: =IF(D19 <> "", B18 + 1, "") | D19: =IF(ISERROR(AH19), "", AH19) | E19: =IF(ISERROR(AL19), "", AL19) | H19: =IF(ISERROR(AF19), "", IF(AF19 = 0, "", AF19)) | K19: =IF(ISERROR(AC19), "", AC19) | L19: =IF(ISERROR(AD19), "", AD19) | Q19: ='Lineup Legality - OOE'!L57 | W19: =IF(ISERROR(AS19), "", AS19) | Z19: Reliability Bonuses must be entered as the full Level Name (ie Level 2) | AC19: =IF(J19 <> "", IF(VLOOKUP(J19, purchasedCars, 2, FALSE) = "", "", VLOOKUP(J19, purchasedCars, 2, FALSE)),"") | AD19: =IF(J19 <> "", IF(VLOOKUP(J19, purchasedCars, 3, FALSE) = "", "", VLOOKUP(J19, purchasedCars, 3, FALSE)),"") | AF19: =IF(AI19 = 1, VLOOKUP(TRIM(AL19), gemSupplier, 2, FALSE), IF(AI19 = 2, VLOOKUP(TRIM(AL19), nasccSupplier, 2, FALSE), IF(AI19 = 2.1, VLOOKUP(TRIM(AL19), nasccSupplier, 2, FALSE), IF(AI19 = 2.2, VLOOKUP(TRIM(AL19), nasccSupplier, 2, FALSE), IF(AI19 = 3, VLOOKUP(TRIM(AL19), euemSupplier, 2, FALSE), IF(AI19 = 4, VLOOKUP(TRIM(AL19), wgtssSupplier, 2, FALSE), IF(AI19 = 5, VLOOKUP(TRIM(AL19), wgtmSupplier, 2, FALSE), IF(AI19 = 7, VLOOKUP(TRIM(AL19), asmSupplier, 2, FALSE), "")))))))) | AH19: =IF(C19 <> "", VLOOKUP(C19, oneOffs, 2, FALSE), "") | AI19: =IF(D19 <> "", VLOOKUP(D19, seriesCodeClasses, 2, FALSE), 0) -> 0 | AJ19: =IF(AL19 <> "", VLOOKUP(AL19, classIndexes, 2, FALSE), 0) -> 0 | AK19: =IF(AI19 = 0, "", IF(AI19 = 1, VLOOKUP(K19, gemClasses, 2, FALSE), IF(AI19 = 2, VLOOKUP(K19, nasccClasses, 2, FALSE), IF(AI19 = 2.1, VLOOKUP(K19, nasccClasses, 2, FALSE), IF(AI19 = 2.2, VLOOKUP(K19, nasccClasses, 2, FALSE), IF(AI19 = 3, VLOOKUP(K19, euemClasses, 2, FALSE), IF(AI19 = 4, VLOOKUP(K19, wgtssClasses, 2, FALSE), IF(AI19 = 5, VLOOKUP(K19, wgtmClasses, 2, FALSE), IF(AI19 = 6, VLOOKUP(K19, wpcClasses, 2, FALSE), IF(AI19 = 7, VLOOKUP(K19, asmClasses, 2, FALSE), "")))))))))) | AL19: =IF(AI19 = 1, AN19, IF(AI19 = 5, AO19, AK19)) | AN19: =IF(AND(IF(AK19 = "LMGTE PRO", TRUE, FALSE), IF(O19 = "Bronze", TRUE, FALSE)), "LMGTE AM", AK19) | AO19: =IF(AND(IF(AK19 = "GT3-P", TRUE, FALSE), IF(O19 = "Bronze", TRUE, FALSE)), "GT3-A", AK19) | AQ19: ='Lineup Legality - OOE'!L57 | AS19: =IF(J19 <> "", CONCATENATE("$", ROUND(SUM('Total Costs'!AZ18:BI18), 3), " Million"), "")
B20: =IF(D20 <> "", B19 + 1, "") | D20: =IF(ISERROR(AH20), "", AH20) | E20: =IF(ISERROR(AL20), "", AL20) | H20: =IF(ISERROR(AF20), "", IF(AF20 = 0, "", AF20)) | K20: =IF(ISERROR(AC20), "", AC20) | L20: =IF(ISERROR(AD20), "", AD20) | Q20: ='Lineup Legality - OOE'!L61 | W20: =IF(ISERROR(AS20), "", AS20) | AC20: =IF(J20 <> "", IF(VLOOKUP(J20, purchasedCars, 2, FALSE) = "", "", VLOOKUP(J20, purchasedCars, 2, FALSE)),"") | AD20: =IF(J20 <> "", IF(VLOOKUP(J20, purchasedCars, 3, FALSE) = "", "", VLOOKUP(J20, purchasedCars, 3, FALSE)),"") | AF20: =IF(AI20 = 1, VLOOKUP(TRIM(AL20), gemSupplier, 2, FALSE), IF(AI20 = 2, VLOOKUP(TRIM(AL20), nasccSupplier, 2, FALSE), IF(AI20 = 2.1, VLOOKUP(TRIM(AL20), nasccSupplier, 2, FALSE), IF(AI20 = 2.2, VLOOKUP(TRIM(AL20), nasccSupplier, 2, FALSE), IF(AI20 = 3, VLOOKUP(TRIM(AL20), euemSupplier, 2, FALSE), IF(AI20 = 4, VLOOKUP(TRIM(AL20), wgtssSupplier, 2, FALSE), IF(AI20 = 5, VLOOKUP(TRIM(AL20), wgtmSupplier, 2, FALSE), IF(AI20 = 7, VLOOKUP(TRIM(AL20), asmSupplier, 2, FALSE), "")))))))) | AH20: =IF(C20 <> "", VLOOKUP(C20, oneOffs, 2, FALSE), "") | AI20: =IF(D20 <> "", VLOOKUP(D20, seriesCodeClasses, 2, FALSE), 0) -> 0 | AJ20: =IF(AL20 <> "", VLOOKUP(AL20, classIndexes, 2, FALSE), 0) -> 0 | AK20: =IF(AI20 = 0, "", IF(AI20 = 1, VLOOKUP(K20, gemClasses, 2, FALSE), IF(AI20 = 2, VLOOKUP(K20, nasccClasses, 2, FALSE), IF(AI20 = 2.1, VLOOKUP(K20, nasccClasses, 2, FALSE), IF(AI20 = 2.2, VLOOKUP(K20, nasccClasses, 2, FALSE), IF(AI20 = 3, VLOOKUP(K20, euemClasses, 2, FALSE), IF(AI20 = 4, VLOOKUP(K20, wgtssClasses, 2, FALSE), IF(AI20 = 5, VLOOKUP(K20, wgtmClasses, 2, FALSE), IF(AI20 = 6, VLOOKUP(K20, wpcClasses, 2, FALSE), IF(AI20 = 7, VLOOKUP(K20, asmClasses, 2, FALSE), "")))))))))) | AL20: =IF(AI20 = 1, AN20, IF(AI20 = 5, AO20, AK20)) | AN20: =IF(AND(IF(AK20 = "LMGTE PRO", TRUE, FALSE), IF(O20 = "Bronze", TRUE, FALSE)), "LMGTE AM", AK20) | AO20: =IF(AND(IF(AK20 = "GT3-P", TRUE, FALSE), IF(O20 = "Bronze", TRUE, FALSE)), "GT3-A", AK20) | AQ20: ='Lineup Legality - OOE'!L61 | AS20: =IF(J20 <> "", CONCATENATE("$", ROUND(SUM('Total Costs'!AZ19:BI19), 3), " Million"), "")
B21: =IF(D21 <> "", B20 + 1, "") | D21: =IF(ISERROR(AH21), "", AH21) | E21: =IF(ISERROR(AL21), "", AL21) | H21: =IF(ISERROR(AF21), "", IF(AF21 = 0, "", AF21)) | K21: =IF(ISERROR(AC21), "", AC21) | L21: =IF(ISERROR(AD21), "", AD21) | Q21: ='Lineup Legality - OOE'!L65 | W21: =IF(ISERROR(AS21), "", AS21) | Z21: Entry Costs are Automatically Calculated and displayed | AC21: =IF(J21 <> "", IF(VLOOKUP(J21, purchasedCars, 2, FALSE) = "", "", VLOOKUP(J21, purchasedCars, 2, FALSE)),"") | AD21: =IF(J21 <> "", IF(VLOOKUP(J21, purchasedCars, 3, FALSE) = "", "", VLOOKUP(J21, purchasedCars, 3, FALSE)),"") | AF21: =IF(AI21 = 1, VLOOKUP(TRIM(AL21), gemSupplier, 2, FALSE), IF(AI21 = 2, VLOOKUP(TRIM(AL21), nasccSupplier, 2, FALSE), IF(AI21 = 2.1, VLOOKUP(TRIM(AL21), nasccSupplier, 2, FALSE), IF(AI21 = 2.2, VLOOKUP(TRIM(AL21), nasccSupplier, 2, FALSE), IF(AI21 = 3, VLOOKUP(TRIM(AL21), euemSupplier, 2, FALSE), IF(AI21 = 4, VLOOKUP(TRIM(AL21), wgtssSupplier, 2, FALSE), IF(AI21 = 5, VLOOKUP(TRIM(AL21), wgtmSupplier, 2, FALSE), IF(AI21 = 7, VLOOKUP(TRIM(AL21), asmSupplier, 2, FALSE), "")))))))) | AH21: =IF(C21 <> "", VLOOKUP(C21, oneOffs, 2, FALSE), "") | AI21: =IF(D21 <> "", VLOOKUP(D21, seriesCodeClasses, 2, FALSE), 0) -> 0 | AJ21: =IF(AL21 <> "", VLOOKUP(AL21, classIndexes, 2, FALSE), 0) -> 0 | AK21: =IF(AI21 = 0, "", IF(AI21 = 1, VLOOKUP(K21, gemClasses, 2, FALSE), IF(AI21 = 2, VLOOKUP(K21, nasccClasses, 2, FALSE), IF(AI21 = 2.1, VLOOKUP(K21, nasccClasses, 2, FALSE), IF(AI21 = 2.2, VLOOKUP(K21, nasccClasses, 2, FALSE), IF(AI21 = 3, VLOOKUP(K21, euemClasses, 2, FALSE), IF(AI21 = 4, VLOOKUP(K21, wgtssClasses, 2, FALSE), IF(AI21 = 5, VLOOKUP(K21, wgtmClasses, 2, FALSE), IF(AI21 = 6, VLOOKUP(K21, wpcClasses, 2, FALSE), IF(AI21 = 7, VLOOKUP(K21, asmClasses, 2, FALSE), "")))))))))) | AL21: =IF(AI21 = 1, AN21, IF(AI21 = 5, AO21, AK21)) | AN21: =IF(AND(IF(AK21 = "LMGTE PRO", TRUE, FALSE), IF(O21 = "Bronze", TRUE, FALSE)), "LMGTE AM", AK21) | AO21: =IF(AND(IF(AK21 = "GT3-P", TRUE, FALSE), IF(O21 = "Bronze", TRUE, FALSE)), "GT3-A", AK21) | AQ21: ='Lineup Legality - OOE'!L65 | AS21: =IF(J21 <> "", CONCATENATE("$", ROUND(SUM('Total Costs'!AZ20:BI20), 3), " Million"), "")
B22: =IF(D22 <> "", B21 + 1, "") | D22: =IF(ISERROR(AH22), "", AH22) | E22: =IF(ISERROR(AL22), "", AL22) | H22: =IF(ISERROR(AF22), "", IF(AF22 = 0, "", AF22)) | K22: =IF(ISERROR(AC22), "", AC22) | L22: =IF(ISERROR(AD22), "", AD22) | Q22: ='Lineup Legality - OOE'!L69 | W22: =IF(ISERROR(AS22), "", AS22) | AC22: =IF(J22 <> "", IF(VLOOKUP(J22, purchasedCars, 2, FALSE) = "", "", VLOOKUP(J22, purchasedCars, 2, FALSE)),"") | AD22: =IF(J22 <> "", IF(VLOOKUP(J22, purchasedCars, 3, FALSE) = "", "", VLOOKUP(J22, purchasedCars, 3, FALSE)),"") | AF22: =IF(AI22 = 1, VLOOKUP(TRIM(AL22), gemSupplier, 2, FALSE), IF(AI22 = 2, VLOOKUP(TRIM(AL22), nasccSupplier, 2, FALSE), IF(AI22 = 2.1, VLOOKUP(TRIM(AL22), nasccSupplier, 2, FALSE), IF(AI22 = 2.2, VLOOKUP(TRIM(AL22), nasccSupplier, 2, FALSE), IF(AI22 = 3, VLOOKUP(TRIM(AL22), euemSupplier, 2, FALSE), IF(AI22 = 4, VLOOKUP(TRIM(AL22), wgtssSupplier, 2, FALSE), IF(AI22 = 5, VLOOKUP(TRIM(AL22), wgtmSupplier, 2, FALSE), IF(AI22 = 7, VLOOKUP(TRIM(AL22), asmSupplier, 2, FALSE), "")))))))) | AH22: =IF(C22 <> "", VLOOKUP(C22, oneOffs, 2, FALSE), "") | AI22: =IF(D22 <> "", VLOOKUP(D22, seriesCodeClasses, 2, FALSE), 0) -> 0 | AJ22: =IF(AL22 <> "", VLOOKUP(AL22, classIndexes, 2, FALSE), 0) -> 0 | AK22: =IF(AI22 = 0, "", IF(AI22 = 1, VLOOKUP(K22, gemClasses, 2, FALSE), IF(AI22 = 2, VLOOKUP(K22, nasccClasses, 2, FALSE), IF(AI22 = 2.1, VLOOKUP(K22, nasccClasses, 2, FALSE), IF(AI22 = 2.2, VLOOKUP(K22, nasccClasses, 2, FALSE), IF(AI22 = 3, VLOOKUP(K22, euemClasses, 2, FALSE), IF(AI22 = 4, VLOOKUP(K22, wgtssClasses, 2, FALSE), IF(AI22 = 5, VLOOKUP(K22, wgtmClasses, 2, FALSE), IF(AI22 = 6, VLOOKUP(K22, wpcClasses, 2, FALSE), IF(AI22 = 7, VLOOKUP(K22, asmClasses, 2, FALSE), "")))))))))) | AL22: =IF(AI22 = 1, AN22, IF(AI22 = 5, AO22, AK22)) | AN22: =IF(AND(IF(AK22 = "LMGTE PRO", TRUE, FALSE), IF(O22 = "Bronze", TRUE, FALSE)), "LMGTE AM", AK22) | AO22: =IF(AND(IF(AK22 = "GT3-P", TRUE, FALSE), IF(O22 = "Bronze", TRUE, FALSE)), "GT3-A", AK22) | AQ22: ='Lineup Legality - OOE'!L69 | AS22: =IF(J22 <> "", CONCATENATE("$", ROUND(SUM('Total Costs'!AZ21:BI21), 3), " Million"), "")
B23: =IF(D23 <> "", B22 + 1, "") | D23: =IF(ISERROR(AH23), "", AH23) | E23: =IF(ISERROR(AL23), "", AL23) | H23: =IF(ISERROR(AF23), "", IF(AF23 = 0, "", AF23)) | K23: =IF(ISERROR(AC23), "", AC23) | L23: =IF(ISERROR(AD23), "", AD23) | Q23: ='Lineup Legality - OOE'!L73 | W23: =IF(ISERROR(AS23), "", AS23) | AC23: =IF(J23 <> "", IF(VLOOKUP(J23, purchasedCars, 2, FALSE) = "", "", VLOOKUP(J23, purchasedCars, 2, FALSE)),"") | AD23: =IF(J23 <> "", IF(VLOOKUP(J23, purchasedCars, 3, FALSE) = "", "", VLOOKUP(J23, purchasedCars, 3, FALSE)),"") | AF23: =IF(AI23 = 1, VLOOKUP(TRIM(AL23), gemSupplier, 2, FALSE), IF(AI23 = 2, VLOOKUP(TRIM(AL23), nasccSupplier, 2, FALSE), IF(AI23 = 2.1, VLOOKUP(TRIM(AL23), nasccSupplier, 2, FALSE), IF(AI23 = 2.2, VLOOKUP(TRIM(AL23), nasccSupplier, 2, FALSE), IF(AI23 = 3, VLOOKUP(TRIM(AL23), euemSupplier, 2, FALSE), IF(AI23 = 4, VLOOKUP(TRIM(AL23), wgtssSupplier, 2, FALSE), IF(AI23 = 5, VLOOKUP(TRIM(AL23), wgtmSupplier, 2, FALSE), IF(AI23 = 7, VLOOKUP(TRIM(AL23), asmSupplier, 2, FALSE), "")))))))) | AH23: =IF(C23 <> "", VLOOKUP(C23, oneOffs, 2, FALSE), "") | AI23: =IF(D23 <> "", VLOOKUP(D23, seriesCodeClasses, 2, FALSE), 0) -> 0 | AJ23: =IF(AL23 <> "", VLOOKUP(AL23, classIndexes, 2, FALSE), 0) -> 0 | AK23: =IF(AI23 = 0, "", IF(AI23 = 1, VLOOKUP(K23, gemClasses, 2, FALSE), IF(AI23 = 2, VLOOKUP(K23, nasccClasses, 2, FALSE), IF(AI23 = 2.1, VLOOKUP(K23, nasccClasses, 2, FALSE), IF(AI23 = 2.2, VLOOKUP(K23, nasccClasses, 2, FALSE), IF(AI23 = 3, VLOOKUP(K23, euemClasses, 2, FALSE), IF(AI23 = 4, VLOOKUP(K23, wgtssClasses, 2, FALSE), IF(AI23 = 5, VLOOKUP(K23, wgtmClasses, 2, FALSE), IF(AI23 = 6, VLOOKUP(K23, wpcClasses, 2, FALSE), IF(AI23 = 7, VLOOKUP(K23, asmClasses, 2, FALSE), "")))))))))) | AL23: =IF(AI23 = 1, AN23, IF(AI23 = 5, AO23, AK23)) | AN23: =IF(AND(IF(AK23 = "LMGTE PRO", TRUE, FALSE), IF(O23 = "Bronze", TRUE, FALSE)), "LMGTE AM", AK23) | AO23: =IF(AND(IF(AK23 = "GT3-P", TRUE, FALSE), IF(O23 = "Bronze", TRUE, FALSE)), "GT3-A", AK23) | AQ23: ='Lineup Legality - OOE'!L73 | AS23: =IF(J23 <> "", CONCATENATE("$", ROUND(SUM('Total Costs'!AZ22:BI22), 3), " Million"), "")
B24: =IF(D24 <> "", B23 + 1, "") | D24: =IF(ISERROR(AH24), "", AH24) | E24: =IF(ISERROR(AL24), "", AL24) | H24: =IF(ISERROR(AF24), "", IF(AF24 = 0, "", AF24)) | K24: =IF(ISERROR(AC24), "", AC24) | L24: =IF(ISERROR(AD24), "", AD24) | Q24: ='Lineup Legality - OOE'!L77 | W24: =IF(ISERROR(AS24), "", AS24) | AC24: =IF(J24 <> "", IF(VLOOKUP(J24, purchasedCars, 2, FALSE) = "", "", VLOOKUP(J24, purchasedCars, 2, FALSE)),"") | AD24: =IF(J24 <> "", IF(VLOOKUP(J24, purchasedCars, 3, FALSE) = "", "", VLOOKUP(J24, purchasedCars, 3, FALSE)),"") | AF24: =IF(AI24 = 1, VLOOKUP(TRIM(AL24), gemSupplier, 2, FALSE), IF(AI24 = 2, VLOOKUP(TRIM(AL24), nasccSupplier, 2, FALSE), IF(AI24 = 2.1, VLOOKUP(TRIM(AL24), nasccSupplier, 2, FALSE), IF(AI24 = 2.2, VLOOKUP(TRIM(AL24), nasccSupplier, 2, FALSE), IF(AI24 = 3, VLOOKUP(TRIM(AL24), euemSupplier, 2, FALSE), IF(AI24 = 4, VLOOKUP(TRIM(AL24), wgtssSupplier, 2, FALSE), IF(AI24 = 5, VLOOKUP(TRIM(AL24), wgtmSupplier, 2, FALSE), IF(AI24 = 7, VLOOKUP(TRIM(AL24), asmSupplier, 2, FALSE), "")))))))) | AH24: =IF(C24 <> "", VLOOKUP(C24, oneOffs, 2, FALSE), "") | AI24: =IF(D24 <> "", VLOOKUP(D24, seriesCodeClasses, 2, FALSE), 0) -> 0 | AJ24: =IF(AL24 <> "", VLOOKUP(AL24, classIndexes, 2, FALSE), 0) -> 0 | AK24: =IF(AI24 = 0, "", IF(AI24 = 1, VLOOKUP(K24, gemClasses, 2, FALSE), IF(AI24 = 2, VLOOKUP(K24, nasccClasses, 2, FALSE), IF(AI24 = 2.1, VLOOKUP(K24, nasccClasses, 2, FALSE), IF(AI24 = 2.2, VLOOKUP(K24, nasccClasses, 2, FALSE), IF(AI24 = 3, VLOOKUP(K24, euemClasses, 2, FALSE), IF(AI24 = 4, VLOOKUP(K24, wgtssClasses, 2, FALSE), IF(AI24 = 5, VLOOKUP(K24, wgtmClasses, 2, FALSE), IF(AI24 = 6, VLOOKUP(K24, wpcClasses, 2, FALSE), IF(AI24 = 7, VLOOKUP(K24, asmClasses, 2, FALSE), "")))))))))) | AL24: =IF(AI24 = 1, AN24, IF(AI24 = 5, AO24, AK24)) | AN24: =IF(AND(IF(AK24 = "LMGTE PRO", TRUE, FALSE), IF(O24 = "Bronze", TRUE, FALSE)), "LMGTE AM", AK24) | AO24: =IF(AND(IF(AK24 = "GT3-P", TRUE, FALSE), IF(O24 = "Bronze", TRUE, FALSE)), "GT3-A", AK24) | AQ24: ='Lineup Legality - OOE'!L77 | AS24: =IF(J24 <> "", CONCATENATE("$", ROUND(SUM('Total Costs'!AZ23:BI23), 3), " Million"), "")
B25: =IF(D25 <> "", B24 + 1, "") | D25: =IF(ISERROR(AH25), "", AH25) | E25: =IF(ISERROR(AL25), "", AL25) | H25: =IF(ISERROR(AF25), "", IF(AF25 = 0, "", AF25)) | K25: =IF(ISERROR(AC25), "", AC25) | L25: =IF(ISERROR(AD25), "", AD25) | Q25: ='Lineup Legality - OOE'!L81 | W25: =IF(ISERROR(AS25), "", AS25) | AC25: =IF(J25 <> "", IF(VLOOKUP(J25, purchasedCars, 2, FALSE) = "", "", VLOOKUP(J25, purchasedCars, 2, FALSE)),"") | AD25: =IF(J25 <> "", IF(VLOOKUP(J25, purchasedCars, 3, FALSE) = "", "", VLOOKUP(J25, purchasedCars, 3, FALSE)),"") | AF25: =IF(AI25 = 1, VLOOKUP(TRIM(AL25), gemSupplier, 2, FALSE), IF(AI25 = 2, VLOOKUP(TRIM(AL25), nasccSupplier, 2, FALSE), IF(AI25 = 2.1, VLOOKUP(TRIM(AL25), nasccSupplier, 2, FALSE), IF(AI25 = 2.2, VLOOKUP(TRIM(AL25), nasccSupplier, 2, FALSE), IF(AI25 = 3, VLOOKUP(TRIM(AL25), euemSupplier, 2, FALSE), IF(AI25 = 4, VLOOKUP(TRIM(AL25), wgtssSupplier, 2, FALSE), IF(AI25 = 5, VLOOKUP(TRIM(AL25), wgtmSupplier, 2, FALSE), IF(AI25 = 7, VLOOKUP(TRIM(AL25), asmSupplier, 2, FALSE), "")))))))) | AH25: =IF(C25 <> "", VLOOKUP(C25, oneOffs, 2, FALSE), "") | AI25: =IF(D25 <> "", VLOOKUP(D25, seriesCodeClasses, 2, FALSE), 0) -> 0 | AJ25: =IF(AL25 <> "", VLOOKUP(AL25, classIndexes, 2, FALSE), 0) -> 0 | AK25: =IF(AI25 = 0, "", IF(AI25 = 1, VLOOKUP(K25, gemClasses, 2, FALSE), IF(AI25 = 2, VLOOKUP(K25, nasccClasses, 2, FALSE), IF(AI25 = 2.1, VLOOKUP(K25, nasccClasses, 2, FALSE), IF(AI25 = 2.2, VLOOKUP(K25, nasccClasses, 2, FALSE), IF(AI25 = 3, VLOOKUP(K25, euemClasses, 2, FALSE), IF(AI25 = 4, VLOOKUP(K25, wgtssClasses, 2, FALSE), IF(AI25 = 5, VLOOKUP(K25, wgtmClasses, 2, FALSE), IF(AI25 = 6, VLOOKUP(K25, wpcClasses, 2, FALSE), IF(AI25 = 7, VLOOKUP(K25, asmClasses, 2, FALSE), "")))))))))) | AL25: =IF(AI25 = 1, AN25, IF(AI25 = 5, AO25, AK25)) | AN25: =IF(AND(IF(AK25 = "LMGTE PRO", TRUE, FALSE), IF(O25 = "Bronze", TRUE, FALSE)), "LMGTE AM", AK25) | AO25: =IF(AND(IF(AK25 = "GT3-P", TRUE, FALSE), IF(O25 = "Bronze", TRUE, FALSE)), "GT3-A", AK25) | AQ25: ='Lineup Legality - OOE'!L81 | AS25: =IF(J25 <> "", CONCATENATE("$", ROUND(SUM('Total Costs'!AZ24:BI24), 3), " Million"), "")
B26: =IF(D26 <> "", B25 + 1, "") | D26: =IF(ISERROR(AH26), "", AH26) | E26: =IF(ISERROR(AL26), "", AL26) | H26: =IF(ISERROR(AF26), "", IF(AF26 = 0, "", AF26)) | K26: =IF(ISERROR(AC26), "", AC26) | L26: =IF(ISERROR(AD26), "", AD26) | Q26: ='Lineup Legality - OOE'!L85 | W26: =IF(ISERROR(AS26), "", AS26) | AC26: =IF(J26 <> "", IF(VLOOKUP(J26, purchasedCars, 2, FALSE) = "", "", VLOOKUP(J26, purchasedCars, 2, FALSE)),"") | AD26: =IF(J26 <> "", IF(VLOOKUP(J26, purchasedCars, 3, FALSE) = "", "", VLOOKUP(J26, purchasedCars, 3, FALSE)),"") | AF26: =IF(AI26 = 1, VLOOKUP(TRIM(AL26), gemSupplier, 2, FALSE), IF(AI26 = 2, VLOOKUP(TRIM(AL26), nasccSupplier, 2, FALSE), IF(AI26 = 2.1, VLOOKUP(TRIM(AL26), nasccSupplier, 2, FALSE), IF(AI26 = 2.2, VLOOKUP(TRIM(AL26), nasccSupplier, 2, FALSE), IF(AI26 = 3, VLOOKUP(TRIM(AL26), euemSupplier, 2, FALSE), IF(AI26 = 4, VLOOKUP(TRIM(AL26), wgtssSupplier, 2, FALSE), IF(AI26 = 5, VLOOKUP(TRIM(AL26), wgtmSupplier, 2, FALSE), IF(AI26 = 7, VLOOKUP(TRIM(AL26), asmSupplier, 2, FALSE), "")))))))) | AH26: =IF(C26 <> "", VLOOKUP(C26, oneOffs, 2, FALSE), "") | AI26: =IF(D26 <> "", VLOOKUP(D26, seriesCodeClasses, 2, FALSE), 0) -> 0 | AJ26: =IF(AL26 <> "", VLOOKUP(AL26, classIndexes, 2, FALSE), 0) -> 0 | AK26: =IF(AI26 = 0, "", IF(AI26 = 1, VLOOKUP(K26, gemClasses, 2, FALSE), IF(AI26 = 2, VLOOKUP(K26, nasccClasses, 2, FALSE), IF(AI26 = 2.1, VLOOKUP(K26, nasccClasses, 2, FALSE), IF(AI26 = 2.2, VLOOKUP(K26, nasccClasses, 2, FALSE), IF(AI26 = 3, VLOOKUP(K26, euemClasses, 2, FALSE), IF(AI26 = 4, VLOOKUP(K26, wgtssClasses, 2, FALSE), IF(AI26 = 5, VLOOKUP(K26, wgtmClasses, 2, FALSE), IF(AI26 = 6, VLOOKUP(K26, wpcClasses, 2, FALSE), IF(AI26 = 7, VLOOKUP(K26, asmClasses, 2, FALSE), "")))))))))) | AL26: =IF(AI26 = 1, AN26, IF(AI26 = 5, AO26, AK26)) | AN26: =IF(AND(IF(AK26 = "LMGTE PRO", TRUE, FALSE), IF(O26 = "Bronze", TRUE, FALSE)), "LMGTE AM", AK26) | AO26: =IF(AND(IF(AK26 = "GT3-P", TRUE, FALSE), IF(O26 = "Bronze", TRUE, FALSE)), "GT3-A", AK26) | AQ26: ='Lineup Legality - OOE'!L85 | AS26: =IF(J26 <> "", CONCATENATE("$", ROUND(SUM('Total Costs'!AZ25:BI25), 3), " Million"), "")
B27: =IF(D27 <> "", B26 + 1, "") | D27: =IF(ISERROR(AH27), "", AH27) | E27: =IF(ISERROR(AL27), "", AL27) | H27: =IF(ISERROR(AF27), "", IF(AF27 = 0, "", AF27)) | K27: =IF(ISERROR(AC27), "", AC27) | L27: =IF(ISERROR(AD27), "", AD27) | Q27: ='Lineup Legality - OOE'!L89 | W27: =IF(ISERROR(AS27), "", AS27) | AC27: =IF(J27 <> "", IF(VLOOKUP(J27, purchasedCars, 2, FALSE) = "", "", VLOOKUP(J27, purchasedCars, 2, FALSE)),"") | AD27: =IF(J27 <> "", IF(VLOOKUP(J27, purchasedCars, 3, FALSE) = "", "", VLOOKUP(J27, purchasedCars, 3, FALSE)),"") | AF27: =IF(AI27 = 1, VLOOKUP(TRIM(AL27), gemSupplier, 2, FALSE), IF(AI27 = 2, VLOOKUP(TRIM(AL27), nasccSupplier, 2, FALSE), IF(AI27 = 2.1, VLOOKUP(TRIM(AL27), nasccSupplier, 2, FALSE), IF(AI27 = 2.2, VLOOKUP(TRIM(AL27), nasccSupplier, 2, FALSE), IF(AI27 = 3, VLOOKUP(TRIM(AL27), euemSupplier, 2, FALSE), IF(AI27 = 4, VLOOKUP(TRIM(AL27), wgtssSupplier, 2, FALSE), IF(AI27 = 5, VLOOKUP(TRIM(AL27), wgtmSupplier, 2, FALSE), IF(AI27 = 7, VLOOKUP(TRIM(AL27), asmSupplier, 2, FALSE), "")))))))) | AH27: =IF(C27 <> "", VLOOKUP(C27, oneOffs, 2, FALSE), "") | AI27: =IF(D27 <> "", VLOOKUP(D27, seriesCodeClasses, 2, FALSE), 0) -> 0 | AJ27: =IF(AL27 <> "", VLOOKUP(AL27, classIndexes, 2, FALSE), 0) -> 0 | AK27: =IF(AI27 = 0, "", IF(AI27 = 1, VLOOKUP(K27, gemClasses, 2, FALSE), IF(AI27 = 2, VLOOKUP(K27, nasccClasses, 2, FALSE), IF(AI27 = 2.1, VLOOKUP(K27, nasccClasses, 2, FALSE), IF(AI27 = 2.2, VLOOKUP(K27, nasccClasses, 2, FALSE), IF(AI27 = 3, VLOOKUP(K27, euemClasses, 2, FALSE), IF(AI27 = 4, VLOOKUP(K27, wgtssClasses, 2, FALSE), IF(AI27 = 5, VLOOKUP(K27, wgtmClasses, 2, FALSE), IF(AI27 = 6, VLOOKUP(K27, wpcClasses, 2, FALSE), IF(AI27 = 7, VLOOKUP(K27, asmClasses, 2, FALSE), "")))))))))) | AL27: =IF(AI27 = 1, AN27, IF(AI27 = 5, AO27, AK27)) | AN27: =IF(AND(IF(AK27 = "LMGTE PRO", TRUE, FALSE), IF(O27 = "Bronze", TRUE, FALSE)), "LMGTE AM", AK27) | AO27: =IF(AND(IF(AK27 = "GT3-P", TRUE, FALSE), IF(O27 = "Bronze", TRUE, FALSE)), "GT3-A", AK27) | AQ27: ='Lineup Legality - OOE'!L89 | AS27: =IF(J27 <> "", CONCATENATE("$", ROUND(SUM('Total Costs'!AZ26:BI26), 3), " Million"), "")
B28: =IF(D28 <> "", B27 + 1, "") | D28: =IF(ISERROR(AH28), "", AH28) | E28: =IF(ISERROR(AL28), "", AL28) | H28: =IF(ISERROR(AF28), "", IF(AF28 = 0, "", AF28)) | K28: =IF(ISERROR(AC28), "", AC28) | L28: =IF(ISERROR(AD28), "", AD28) | Q28: ='Lineup Legality - OOE'!L93 | W28: =IF(ISERROR(AS28), "", AS28) | AC28: =IF(J28 <> "", IF(VLOOKUP(J28, purchasedCars, 2, FALSE) = "", "", VLOOKUP(J28, purchasedCars, 2, FALSE)),"") | AD28: =IF(J28 <> "", IF(VLOOKUP(J28, purchasedCars, 3, FALSE) = "", "", VLOOKUP(J28, purchasedCars, 3, FALSE)),"") | AF28: =IF(AI28 = 1, VLOOKUP(TRIM(AL28), gemSupplier, 2, FALSE), IF(AI28 = 2, VLOOKUP(TRIM(AL28), nasccSupplier, 2, FALSE), IF(AI28 = 2.1, VLOOKUP(TRIM(AL28), nasccSupplier, 2, FALSE), IF(AI28 = 2.2, VLOOKUP(TRIM(AL28), nasccSupplier, 2, FALSE), IF(AI28 = 3, VLOOKUP(TRIM(AL28), euemSupplier, 2, FALSE), IF(AI28 = 4, VLOOKUP(TRIM(AL28), wgtssSupplier, 2, FALSE), IF(AI28 = 5, VLOOKUP(TRIM(AL28), wgtmSupplier, 2, FALSE), IF(AI28 = 7, VLOOKUP(TRIM(AL28), asmSupplier, 2, FALSE), "")))))))) | AH28: =IF(C28 <> "", VLOOKUP(C28, oneOffs, 2, FALSE), "") | AI28: =IF(D28 <> "", VLOOKUP(D28, seriesCodeClasses, 2, FALSE), 0) -> 0 | AJ28: =IF(AL28 <> "", VLOOKUP(AL28, classIndexes, 2, FALSE), 0) -> 0 | AK28: =IF(AI28 = 0, "", IF(AI28 = 1, VLOOKUP(K28, gemClasses, 2, FALSE), IF(AI28 = 2, VLOOKUP(K28, nasccClasses, 2, FALSE), IF(AI28 = 2.1, VLOOKUP(K28, nasccClasses, 2, FALSE), IF(AI28 = 2.2, VLOOKUP(K28, nasccClasses, 2, FALSE), IF(AI28 = 3, VLOOKUP(K28, euemClasses, 2, FALSE), IF(AI28 = 4, VLOOKUP(K28, wgtssClasses, 2, FALSE), IF(AI28 = 5, VLOOKUP(K28, wgtmClasses, 2, FALSE), IF(AI28 = 6, VLOOKUP(K28, wpcClasses, 2, FALSE), IF(AI28 = 7, VLOOKUP(K28, asmClasses, 2, FALSE), "")))))))))) | AL28: =IF(AI28 = 1, AN28, IF(AI28 = 5, AO28, AK28)) | AN28: =IF(AND(IF(AK28 = "LMGTE PRO", TRUE, FALSE), IF(O28 = "Bronze", TRUE, FALSE)), "LMGTE AM", AK28) | AO28: =IF(AND(IF(AK28 = "GT3-P", TRUE, FALSE), IF(O28 = "Bronze", TRUE, FALSE)), "GT3-A", AK28) | AQ28: ='Lineup Legality - OOE'!L93 | AS28: =IF(J28 <> "", CONCATENATE("$", ROUND(SUM('Total Costs'!AZ27:BI27), 3), " Million"), "")
B29: =IF(D29 <> "", B28 + 1, "") | D29: =IF(ISERROR(AH29), "", AH29) | E29: =IF(ISERROR(AL29), "", AL29) | H29: =IF(ISERROR(AF29), "", IF(AF29 = 0, "", AF29)) | K29: =IF(ISERROR(AC29), "", AC29) | L29: =IF(ISERROR(AD29), "", AD29) | Q29: ='Lineup Legality - OOE'!L97 | W29: =IF(ISERROR(AS29), "", AS29) | AC29: =IF(J29 <> "", IF(VLOOKUP(J29, purchasedCars, 2, FALSE) = "", "", VLOOKUP(J29, purchasedCars, 2, FALSE)),"") | AD29: =IF(J29 <> "", IF(VLOOKUP(J29, purchasedCars, 3, FALSE) = "", "", VLOOKUP(J29, purchasedCars, 3, FALSE)),"") | AF29: =IF(AI29 = 1, VLOOKUP(TRIM(AL29), gemSupplier, 2, FALSE), IF(AI29 = 2, VLOOKUP(TRIM(AL29), nasccSupplier, 2, FALSE), IF(AI29 = 2.1, VLOOKUP(TRIM(AL29), nasccSupplier, 2, FALSE), IF(AI29 = 2.2, VLOOKUP(TRIM(AL29), nasccSupplier, 2, FALSE), IF(AI29 = 3, VLOOKUP(TRIM(AL29), euemSupplier, 2, FALSE), IF(AI29 = 4, VLOOKUP(TRIM(AL29), wgtssSupplier, 2, FALSE), IF(AI29 = 5, VLOOKUP(TRIM(AL29), wgtmSupplier, 2, FALSE), IF(AI29 = 7, VLOOKUP(TRIM(AL29), asmSupplier, 2, FALSE), "")))))))) | AH29: =IF(C29 <> "", VLOOKUP(C29, oneOffs, 2, FALSE), "") | AI29: =IF(D29 <> "", VLOOKUP(D29, seriesCodeClasses, 2, FALSE), 0) -> 0 | AJ29: =IF(AL29 <> "", VLOOKUP(AL29, classIndexes, 2, FALSE), 0) -> 0 | AK29: =IF(AI29 = 0, "", IF(AI29 = 1, VLOOKUP(K29, gemClasses, 2, FALSE), IF(AI29 = 2, VLOOKUP(K29, nasccClasses, 2, FALSE), IF(AI29 = 2.1, VLOOKUP(K29, nasccClasses, 2, FALSE), IF(AI29 = 2.2, VLOOKUP(K29, nasccClasses, 2, FALSE), IF(AI29 = 3, VLOOKUP(K29, euemClasses, 2, FALSE), IF(AI29 = 4, VLOOKUP(K29, wgtssClasses, 2, FALSE), IF(AI29 = 5, VLOOKUP(K29, wgtmClasses, 2, FALSE), IF(AI29 = 6, VLOOKUP(K29, wpcClasses, 2, FALSE), IF(AI29 = 7, VLOOKUP(K29, asmClasses, 2, FALSE), "")))))))))) | AL29: =IF(AI29 = 1, AN29, IF(AI29 = 5, AO29, AK29)) | AN29: =IF(AND(IF(AK29 = "LMGTE PRO", TRUE, FALSE), IF(O29 = "Bronze", TRUE, FALSE)), "LMGTE AM", AK29) | AO29: =IF(AND(IF(AK29 = "GT3-P", TRUE, FALSE), IF(O29 = "Bronze", TRUE, FALSE)), "GT3-A", AK29) | AQ29: ='Lineup Legality - OOE'!L97 | AS29: =IF(J29 <> "", CONCATENATE("$", ROUND(SUM('Total Costs'!AZ28:BI28), 3), " Million"), "")
B30: =IF(D30 <> "", B29 + 1, "") | D30: =IF(ISERROR(AH30), "", AH30) | E30: =IF(ISERROR(AL30), "", AL30) | H30: =IF(ISERROR(AF30), "", IF(AF30 = 0, "", AF30)) | K30: =IF(ISERROR(AC30), "", AC30) | L30: =IF(ISERROR(AD30), "", AD30) | Q30: ='Lineup Legality - OOE'!L101 | W30: =IF(ISERROR(AS30), "", AS30) | AC30: =IF(J30 <> "", IF(VLOOKUP(J30, purchasedCars, 2, FALSE) = "", "", VLOOKUP(J30, purchasedCars, 2, FALSE)),"") | AD30: =IF(J30 <> "", IF(VLOOKUP(J30, purchasedCars, 3, FALSE) = "", "", VLOOKUP(J30, purchasedCars, 3, FALSE)),"") | AF30: =IF(AI30 = 1, VLOOKUP(TRIM(AL30), gemSupplier, 2, FALSE), IF(AI30 = 2, VLOOKUP(TRIM(AL30), nasccSupplier, 2, FALSE), IF(AI30 = 2.1, VLOOKUP(TRIM(AL30), nasccSupplier, 2, FALSE), IF(AI30 = 2.2, VLOOKUP(TRIM(AL30), nasccSupplier, 2, FALSE), IF(AI30 = 3, VLOOKUP(TRIM(AL30), euemSupplier, 2, FALSE), IF(AI30 = 4, VLOOKUP(TRIM(AL30), wgtssSupplier, 2, FALSE), IF(AI30 = 5, VLOOKUP(TRIM(AL30), wgtmSupplier, 2, FALSE), IF(AI30 = 7, VLOOKUP(TRIM(AL30), asmSupplier, 2, FALSE), "")))))))) | AH30: =IF(C30 <> "", VLOOKUP(C30, oneOffs, 2, FALSE), "") | AI30: =IF(D30 <> "", VLOOKUP(D30, seriesCodeClasses, 2, FALSE), 0) -> 0 | AJ30: =IF(AL30 <> "", VLOOKUP(AL30, classIndexes, 2, FALSE), 0) -> 0 | AK30: =IF(AI30 = 0, "", IF(AI30 = 1, VLOOKUP(K30, gemClasses, 2, FALSE), IF(AI30 = 2, VLOOKUP(K30, nasccClasses, 2, FALSE), IF(AI30 = 2.1, VLOOKUP(K30, nasccClasses, 2, FALSE), IF(AI30 = 2.2, VLOOKUP(K30, nasccClasses, 2, FALSE), IF(AI30 = 3, VLOOKUP(K30, euemClasses, 2, FALSE), IF(AI30 = 4, VLOOKUP(K30, wgtssClasses, 2, FALSE), IF(AI30 = 5, VLOOKUP(K30, wgtmClasses, 2, FALSE), IF(AI30 = 6, VLOOKUP(K30, wpcClasses, 2, FALSE), IF(AI30 = 7, VLOOKUP(K30, asmClasses, 2, FALSE), "")))))))))) | AL30: =IF(AI30 = 1, AN30, IF(AI30 = 5, AO30, AK30)) | AN30: =IF(AND(IF(AK30 = "LMGTE PRO", TRUE, FALSE), IF(O30 = "Bronze", TRUE, FALSE)), "LMGTE AM", AK30) | AO30: =IF(AND(IF(AK30 = "GT3-P", TRUE, FALSE), IF(O30 = "Bronze", TRUE, FALSE)), "GT3-A", AK30) | AQ30: ='Lineup Legality - OOE'!L101 | AS30: =IF(J30 <> "", CONCATENATE("$", ROUND(SUM('Total Costs'!AZ29:BI29), 3), " Million"), "")
B31: =IF(D31 <> "", B30 + 1, "") | D31: =IF(ISERROR(AH31), "", AH31) | E31: =IF(ISERROR(AL31), "", AL31) | H31: =IF(ISERROR(AF31), "", IF(AF31 = 0, "", AF31)) | K31: =IF(ISERROR(AC31), "", AC31) | L31: =IF(ISERROR(AD31), "", AD31) | Q31: ='Lineup Legality - OOE'!L105 | W31: =IF(ISERROR(AS31), "", AS31) | AC31: =IF(J31 <> "", IF(VLOOKUP(J31, purchasedCars, 2, FALSE) = "", "", VLOOKUP(J31, purchasedCars, 2, FALSE)),"") | AD31: =IF(J31 <> "", IF(VLOOKUP(J31, purchasedCars, 3, FALSE) = "", "", VLOOKUP(J31, purchasedCars, 3, FALSE)),"") | AF31: =IF(AI31 = 1, VLOOKUP(TRIM(AL31), gemSupplier, 2, FALSE), IF(AI31 = 2, VLOOKUP(TRIM(AL31), nasccSupplier, 2, FALSE), IF(AI31 = 2.1, VLOOKUP(TRIM(AL31), nasccSupplier, 2, FALSE), IF(AI31 = 2.2, VLOOKUP(TRIM(AL31), nasccSupplier, 2, FALSE), IF(AI31 = 3, VLOOKUP(TRIM(AL31), euemSupplier, 2, FALSE), IF(AI31 = 4, VLOOKUP(TRIM(AL31), wgtssSupplier, 2, FALSE), IF(AI31 = 5, VLOOKUP(TRIM(AL31), wgtmSupplier, 2, FALSE), IF(AI31 = 7, VLOOKUP(TRIM(AL31), asmSupplier, 2, FALSE), "")))))))) | AH31: =IF(C31 <> "", VLOOKUP(C31, oneOffs, 2, FALSE), "") | AI31: =IF(D31 <> "", VLOOKUP(D31, seriesCodeClasses, 2, FALSE), 0) -> 0 | AJ31: =IF(AL31 <> "", VLOOKUP(AL31, classIndexes, 2, FALSE), 0) -> 0 | AK31: =IF(AI31 = 0, "", IF(AI31 = 1, VLOOKUP(K31, gemClasses, 2, FALSE), IF(AI31 = 2, VLOOKUP(K31, nasccClasses, 2, FALSE), IF(AI31 = 2.1, VLOOKUP(K31, nasccClasses, 2, FALSE), IF(AI31 = 2.2, VLOOKUP(K31, nasccClasses, 2, FALSE), IF(AI31 = 3, VLOOKUP(K31, euemClasses, 2, FALSE), IF(AI31 = 4, VLOOKUP(K31, wgtssClasses, 2, FALSE), IF(AI31 = 5, VLOOKUP(K31, wgtmClasses, 2, FALSE), IF(AI31 = 6, VLOOKUP(K31, wpcClasses, 2, FALSE), IF(AI31 = 7, VLOOKUP(K31, asmClasses, 2, FALSE), "")))))))))) | AL31: =IF(AI31 = 1, AN31, IF(AI31 = 5, AO31, AK31)) | AN31: =IF(AND(IF(AK31 = "LMGTE PRO", TRUE, FALSE), IF(O31 = "Bronze", TRUE, FALSE)), "LMGTE AM", AK31) | AO31: =IF(AND(IF(AK31 = "GT3-P", TRUE, FALSE), IF(O31 = "Bronze", TRUE, FALSE)), "GT3-A", AK31) | AQ31: ='Lineup Legality - OOE'!L105 | AS31: =IF(J31 <> "", CONCATENATE("$", ROUND(SUM('Total Costs'!AZ30:BI30), 3), " Million"), "")
B32: =IF(D32 <> "", B31 + 1, "") | D32: =IF(ISERROR(AH32), "", AH32) | E32: =IF(ISERROR(AL32), "", AL32) | H32: =IF(ISERROR(AF32), "", IF(AF32 = 0, "", AF32)) | K32: =IF(ISERROR(AC32), "", AC32) | L32: =IF(ISERROR(AD32), "", AD32) | Q32: ='Lineup Legality - OOE'!L109 | W32: =IF(ISERROR(AS32), "", AS32) | AC32: =IF(J32 <> "", IF(VLOOKUP(J32, purchasedCars, 2, FALSE) = "", "", VLOOKUP(J32, purchasedCars, 2, FALSE)),"") | AD32: =IF(J32 <> "", IF(VLOOKUP(J32, purchasedCars, 3, FALSE) = "", "", VLOOKUP(J32, purchasedCars, 3, FALSE)),"") | AF32: =IF(AI32 = 1, VLOOKUP(TRIM(AL32), gemSupplier, 2, FALSE), IF(AI32 = 2, VLOOKUP(TRIM(AL32), nasccSupplier, 2, FALSE), IF(AI32 = 2.1, VLOOKUP(TRIM(AL32), nasccSupplier, 2, FALSE), IF(AI32 = 2.2, VLOOKUP(TRIM(AL32), nasccSupplier, 2, FALSE), IF(AI32 = 3, VLOOKUP(TRIM(AL32), euemSupplier, 2, FALSE), IF(AI32 = 4, VLOOKUP(TRIM(AL32), wgtssSupplier, 2, FALSE), IF(AI32 = 5, VLOOKUP(TRIM(AL32), wgtmSupplier, 2, FALSE), IF(AI32 = 7, VLOOKUP(TRIM(AL32), asmSupplier, 2, FALSE), "")))))))) | AH32: =IF(C32 <> "", VLOOKUP(C32, oneOffs, 2, FALSE), "") | AI32: =IF(D32 <> "", VLOOKUP(D32, seriesCodeClasses, 2, FALSE), 0) -> 0 | AJ32: =IF(AL32 <> "", VLOOKUP(AL32, classIndexes, 2, FALSE), 0) -> 0 | AK32: =IF(AI32 = 0, "", IF(AI32 = 1, VLOOKUP(K32, gemClasses, 2, FALSE), IF(AI32 = 2, VLOOKUP(K32, nasccClasses, 2, FALSE), IF(AI32 = 2.1, VLOOKUP(K32, nasccClasses, 2, FALSE), IF(AI32 = 2.2, VLOOKUP(K32, nasccClasses, 2, FALSE), IF(AI32 = 3, VLOOKUP(K32, euemClasses, 2, FALSE), IF(AI32 = 4, VLOOKUP(K32, wgtssClasses, 2, FALSE), IF(AI32 = 5, VLOOKUP(K32, wgtmClasses, 2, FALSE), IF(AI32 = 6, VLOOKUP(K32, wpcClasses, 2, FALSE), IF(AI32 = 7, VLOOKUP(K32, asmClasses, 2, FALSE), "")))))))))) | AL32: =IF(AI32 = 1, AN32, IF(AI32 = 5, AO32, AK32)) | AN32: =IF(AND(IF(AK32 = "LMGTE PRO", TRUE, FALSE), IF(O32 = "Bronze", TRUE, FALSE)), "LMGTE AM", AK32) | AO32: =IF(AND(IF(AK32 = "GT3-P", TRUE, FALSE), IF(O32 = "Bronze", TRUE, FALSE)), "GT3-A", AK32) | AQ32: ='Lineup Legality - OOE'!L109 | AS32: =IF(J32 <> "", CONCATENATE("$", ROUND(SUM('Total Costs'!AZ31:BI31), 3), " Million"), "")
B33: =IF(D33 <> "", B32 + 1, "") | D33: =IF(ISERROR(AH33), "", AH33) | E33: =IF(ISERROR(AL33), "", AL33) | H33: =IF(ISERROR(AF33), "", IF(AF33 = 0, "", AF33)) | K33: =IF(ISERROR(AC33), "", AC33) | L33: =IF(ISERROR(AD33), "", AD33) | Q33: ='Lineup Legality - OOE'!L113 | W33: =IF(ISERROR(AS33), "", AS33) | AC33: =IF(J33 <> "", IF(VLOOKUP(J33, purchasedCars, 2, FALSE) = "", "", VLOOKUP(J33, purchasedCars, 2, FALSE)),"") | AD33: =IF(J33 <> "", IF(VLOOKUP(J33, purchasedCars, 3, FALSE) = "", "", VLOOKUP(J33, purchasedCars, 3, FALSE)),"") | AF33: =IF(AI33 = 1, VLOOKUP(TRIM(AL33), gemSupplier, 2, FALSE), IF(AI33 = 2, VLOOKUP(TRIM(AL33), nasccSupplier, 2, FALSE), IF(AI33 = 2.1, VLOOKUP(TRIM(AL33), nasccSupplier, 2, FALSE), IF(AI33 = 2.2, VLOOKUP(TRIM(AL33), nasccSupplier, 2, FALSE), IF(AI33 = 3, VLOOKUP(TRIM(AL33), euemSupplier, 2, FALSE), IF(AI33 = 4, VLOOKUP(TRIM(AL33), wgtssSupplier, 2, FALSE), IF(AI33 = 5, VLOOKUP(TRIM(AL33), wgtmSupplier, 2, FALSE), IF(AI33 = 7, VLOOKUP(TRIM(AL33), asmSupplier, 2, FALSE), "")))))))) | AH33: =IF(C33 <> "", VLOOKUP(C33, oneOffs, 2, FALSE), "") | AI33: =IF(D33 <> "", VLOOKUP(D33, seriesCodeClasses, 2, FALSE), 0) -> 0 | AJ33: =IF(AL33 <> "", VLOOKUP(AL33, classIndexes, 2, FALSE), 0) -> 0 | AK33: =IF(AI33 = 0, "", IF(AI33 = 1, VLOOKUP(K33, gemClasses, 2, FALSE), IF(AI33 = 2, VLOOKUP(K33, nasccClasses, 2, FALSE), IF(AI33 = 2.1, VLOOKUP(K33, nasccClasses, 2, FALSE), IF(AI33 = 2.2, VLOOKUP(K33, nasccClasses, 2, FALSE), IF(AI33 = 3, VLOOKUP(K33, euemClasses, 2, FALSE), IF(AI33 = 4, VLOOKUP(K33, wgtssClasses, 2, FALSE), IF(AI33 = 5, VLOOKUP(K33, wgtmClasses, 2, FALSE), IF(AI33 = 6, VLOOKUP(K33, wpcClasses, 2, FALSE), IF(AI33 = 7, VLOOKUP(K33, asmClasses, 2, FALSE), "")))))))))) | AL33: =IF(AI33 = 1, AN33, IF(AI33 = 5, AO33, AK33)) | AN33: =IF(AND(IF(AK33 = "LMGTE PRO", TRUE, FALSE), IF(O33 = "Bronze", TRUE, FALSE)), "LMGTE AM", AK33) | AO33: =IF(AND(IF(AK33 = "GT3-P", TRUE, FALSE), IF(O33 = "Bronze", TRUE, FALSE)), "GT3-A", AK33) | AQ33: ='Lineup Legality - OOE'!L113 | AS33: =IF(J33 <> "", CONCATENATE("$", ROUND(SUM('Total Costs'!AZ32:BI32), 3), " Million"), "")
B34: =IF(D34 <> "", B33 + 1, "") | D34: =IF(ISERROR(AH34), "", AH34) | E34: =IF(ISERROR(AL34), "", AL34) | H34: =IF(ISERROR(AF34), "", IF(AF34 = 0, "", AF34)) | K34: =IF(ISERROR(AC34), "", AC34) | L34: =IF(ISERROR(AD34), "", AD34) | Q34: ='Lineup Legality - OOE'!L117 | W34: =IF(ISERROR(AS34), "", AS34) | AC34: =IF(J34 <> "", IF(VLOOKUP(J34, purchasedCars, 2, FALSE) = "", "", VLOOKUP(J34, purchasedCars, 2, FALSE)),"") | AD34: =IF(J34 <> "", IF(VLOOKUP(J34, purchasedCars, 3, FALSE) = "", "", VLOOKUP(J34, purchasedCars, 3, FALSE)),"") | AF34: =IF(AI34 = 1, VLOOKUP(TRIM(AL34), gemSupplier, 2, FALSE), IF(AI34 = 2, VLOOKUP(TRIM(AL34), nasccSupplier, 2, FALSE), IF(AI34 = 2.1, VLOOKUP(TRIM(AL34), nasccSupplier, 2, FALSE), IF(AI34 = 2.2, VLOOKUP(TRIM(AL34), nasccSupplier, 2, FALSE), IF(AI34 = 3, VLOOKUP(TRIM(AL34), euemSupplier, 2, FALSE), IF(AI34 = 4, VLOOKUP(TRIM(AL34), wgtssSupplier, 2, FALSE), IF(AI34 = 5, VLOOKUP(TRIM(AL34), wgtmSupplier, 2, FALSE), IF(AI34 = 7, VLOOKUP(TRIM(AL34), asmSupplier, 2, FALSE), "")))))))) | AH34: =IF(C34 <> "", VLOOKUP(C34, oneOffs, 2, FALSE), "") | AI34: =IF(D34 <> "", VLOOKUP(D34, seriesCodeClasses, 2, FALSE), 0) -> 0 | AJ34: =IF(AL34 <> "", VLOOKUP(AL34, classIndexes, 2, FALSE), 0) -> 0 | AK34: =IF(AI34 = 0, "", IF(AI34 = 1, VLOOKUP(K34, gemClasses, 2, FALSE), IF(AI34 = 2, VLOOKUP(K34, nasccClasses, 2, FALSE), IF(AI34 = 2.1, VLOOKUP(K34, nasccClasses, 2, FALSE), IF(AI34 = 2.2, VLOOKUP(K34, nasccClasses, 2, FALSE), IF(AI34 = 3, VLOOKUP(K34, euemClasses, 2, FALSE), IF(AI34 = 4, VLOOKUP(K34, wgtssClasses, 2, FALSE), IF(AI34 = 5, VLOOKUP(K34, wgtmClasses, 2, FALSE), IF(AI34 = 6, VLOOKUP(K34, wpcClasses, 2, FALSE), IF(AI34 = 7, VLOOKUP(K34, asmClasses, 2, FALSE), "")))))))))) | AL34: =IF(AI34 = 1, AN34, IF(AI34 = 5, AO34, AK34)) | AN34: =IF(AND(IF(AK34 = "LMGTE PRO", TRUE, FALSE), IF(O34 = "Bronze", TRUE, FALSE)), "LMGTE AM", AK34) | AO34: =IF(AND(IF(AK34 = "GT3-P", TRUE, FALSE), IF(O34 = "Bronze", TRUE, FALSE)), "GT3-A", AK34) | AQ34: ='Lineup Legality - OOE'!L117 | AS34: =IF(J34 <> "", CONCATENATE("$", ROUND(SUM('Total Costs'!AZ33:BI33), 3), " Million"), "")
B35: =IF(D35 <> "", B34 + 1, "") | D35: =IF(ISERROR(AH35), "", AH35) | E35: =IF(ISERROR(AL35), "", AL35) | H35: =IF(ISERROR(AF35), "", IF(AF35 = 0, "", AF35)) | K35: =IF(ISERROR(AC35), "", AC35) | L35: =IF(ISERROR(AD35), "", AD35) | Q35: ='Lineup Legality - OOE'!L121 | W35: =IF(ISERROR(AS35), "", AS35) | AC35: =IF(J35 <> "", IF(VLOOKUP(J35, purchasedCars, 2, FALSE) = "", "", VLOOKUP(J35, purchasedCars, 2, FALSE)),"") | AD35: =IF(J35 <> "", IF(VLOOKUP(J35, purchasedCars, 3, FALSE) = "", "", VLOOKUP(J35, purchasedCars, 3, FALSE)),"") | AF35: =IF(AI35 = 1, VLOOKUP(TRIM(AL35), gemSupplier, 2, FALSE), IF(AI35 = 2, VLOOKUP(TRIM(AL35), nasccSupplier, 2, FALSE), IF(AI35 = 2.1, VLOOKUP(TRIM(AL35), nasccSupplier, 2, FALSE), IF(AI35 = 2.2, VLOOKUP(TRIM(AL35), nasccSupplier, 2, FALSE), IF(AI35 = 3, VLOOKUP(TRIM(AL35), euemSupplier, 2, FALSE), IF(AI35 = 4, VLOOKUP(TRIM(AL35), wgtssSupplier, 2, FALSE), IF(AI35 = 5, VLOOKUP(TRIM(AL35), wgtmSupplier, 2, FALSE), IF(AI35 = 7, VLOOKUP(TRIM(AL35), asmSupplier, 2, FALSE), "")))))))) | AH35: =IF(C35 <> "", VLOOKUP(C35, oneOffs, 2, FALSE), "") | AI35: =IF(D35 <> "", VLOOKUP(D35, seriesCodeClasses, 2, FALSE), 0) -> 0 | AJ35: =IF(AL35 <> "", VLOOKUP(AL35, classIndexes, 2, FALSE), 0) -> 0 | AK35: =IF(AI35 = 0, "", IF(AI35 = 1, VLOOKUP(K35, gemClasses, 2, FALSE), IF(AI35 = 2, VLOOKUP(K35, nasccClasses, 2, FALSE), IF(AI35 = 2.1, VLOOKUP(K35, nasccClasses, 2, FALSE), IF(AI35 = 2.2, VLOOKUP(K35, nasccClasses, 2, FALSE), IF(AI35 = 3, VLOOKUP(K35, euemClasses, 2, FALSE), IF(AI35 = 4, VLOOKUP(K35, wgtssClasses, 2, FALSE), IF(AI35 = 5, VLOOKUP(K35, wgtmClasses, 2, FALSE), IF(AI35 = 6, VLOOKUP(K35, wpcClasses, 2, FALSE), IF(AI35 = 7, VLOOKUP(K35, asmClasses, 2, FALSE), "")))))))))) | AL35: =IF(AI35 = 1, AN35, IF(AI35 = 5, AO35, AK35)) | AN35: =IF(AND(IF(AK35 = "LMGTE PRO", TRUE, FALSE), IF(O35 = "Bronze", TRUE, FALSE)), "LMGTE AM", AK35) | AO35: =IF(AND(IF(AK35 = "GT3-P", TRUE, FALSE), IF(O35 = "Bronze", TRUE, FALSE)), "GT3-A", AK35) | AQ35: ='Lineup Legality - OOE'!L121 | AS35: =IF(J35 <> "", CONCATENATE("$", ROUND(SUM('Total Costs'!AZ34:BI34), 3), " Million"), "")
B36: =IF(D36 <> "", B35 + 1, "") | D36: =IF(ISERROR(AH36), "", AH36) | E36: =IF(ISERROR(AL36), "", AL36) | H36: =IF(ISERROR(AF36), "", IF(AF36 = 0, "", AF36)) | K36: =IF(ISERROR(AC36), "", AC36) | L36: =IF(ISERROR(AD36), "", AD36) | Q36: ='Lineup Legality - OOE'!L125 | W36: =IF(ISERROR(AS36), "", AS36) | AC36: =IF(J36 <> "", IF(VLOOKUP(J36, purchasedCars, 2, FALSE) = "", "", VLOOKUP(J36, purchasedCars, 2, FALSE)),"") | AD36: =IF(J36 <> "", IF(VLOOKUP(J36, purchasedCars, 3, FALSE) = "", "", VLOOKUP(J36, purchasedCars, 3, FALSE)),"") | AF36: =IF(AI36 = 1, VLOOKUP(TRIM(AL36), gemSupplier, 2, FALSE), IF(AI36 = 2, VLOOKUP(TRIM(AL36), nasccSupplier, 2, FALSE), IF(AI36 = 2.1, VLOOKUP(TRIM(AL36), nasccSupplier, 2, FALSE), IF(AI36 = 2.2, VLOOKUP(TRIM(AL36), nasccSupplier, 2, FALSE), IF(AI36 = 3, VLOOKUP(TRIM(AL36), euemSupplier, 2, FALSE), IF(AI36 = 4, VLOOKUP(TRIM(AL36), wgtssSupplier, 2, FALSE), IF(AI36 = 5, VLOOKUP(TRIM(AL36), wgtmSupplier, 2, FALSE), IF(AI36 = 7, VLOOKUP(TRIM(AL36), asmSupplier, 2, FALSE), "")))))))) | AH36: =IF(C36 <> "", VLOOKUP(C36, oneOffs, 2, FALSE), "") | AI36: =IF(D36 <> "", VLOOKUP(D36, seriesCodeClasses, 2, FALSE), 0) -> 0 | AJ36: =IF(AL36 <> "", VLOOKUP(AL36, classIndexes, 2, FALSE), 0) -> 0 | AK36: =IF(AI36 = 0, "", IF(AI36 = 1, VLOOKUP(K36, gemClasses, 2, FALSE), IF(AI36 = 2, VLOOKUP(K36, nasccClasses, 2, FALSE), IF(AI36 = 2.1, VLOOKUP(K36, nasccClasses, 2, FALSE), IF(AI36 = 2.2, VLOOKUP(K36, nasccClasses, 2, FALSE), IF(AI36 = 3, VLOOKUP(K36, euemClasses, 2, FALSE), IF(AI36 = 4, VLOOKUP(K36, wgtssClasses, 2, FALSE), IF(AI36 = 5, VLOOKUP(K36, wgtmClasses, 2, FALSE), IF(AI36 = 6, VLOOKUP(K36, wpcClasses, 2, FALSE), IF(AI36 = 7, VLOOKUP(K36, asmClasses, 2, FALSE), "")))))))))) | AL36: =IF(AI36 = 1, AN36, IF(AI36 = 5, AO36, AK36)) | AN36: =IF(AND(IF(AK36 = "LMGTE PRO", TRUE, FALSE), IF(O36 = "Bronze", TRUE, FALSE)), "LMGTE AM", AK36) | AO36: =IF(AND(IF(AK36 = "GT3-P", TRUE, FALSE), IF(O36 = "Bronze", TRUE, FALSE)), "GT3-A", AK36) | AQ36: ='Lineup Legality - OOE'!L125 | AS36: =IF(J36 <> "", CONCATENATE("$", ROUND(SUM('Total Costs'!AZ35:BI35), 3), " Million"), "")
B37: =IF(D37 <> "", B36 + 1, "") | D37: =IF(ISERROR(AH37), "", AH37) | E37: =IF(ISERROR(AL37), "", AL37) | H37: =IF(ISERROR(AF37), "", IF(AF37 = 0, "", AF37)) | K37: =IF(ISERROR(AC37), "", AC37) | L37: =IF(ISERROR(AD37), "", AD37) | Q37: ='Lineup Legality - OOE'!L129 | W37: =IF(ISERROR(AS37), "", AS37) | AC37: =IF(J37 <> "", IF(VLOOKUP(J37, purchasedCars, 2, FALSE) = "", "", VLOOKUP(J37, purchasedCars, 2, FALSE)),"") | AD37: =IF(J37 <> "", IF(VLOOKUP(J37, purchasedCars, 3, FALSE) = "", "", VLOOKUP(J37, purchasedCars, 3, FALSE)),"") | AF37: =IF(AI37 = 1, VLOOKUP(TRIM(AL37), gemSupplier, 2, FALSE), IF(AI37 = 2, VLOOKUP(TRIM(AL37), nasccSupplier, 2, FALSE), IF(AI37 = 2.1, VLOOKUP(TRIM(AL37), nasccSupplier, 2, FALSE), IF(AI37 = 2.2, VLOOKUP(TRIM(AL37), nasccSupplier, 2, FALSE), IF(AI37 = 3, VLOOKUP(TRIM(AL37), euemSupplier, 2, FALSE), IF(AI37 = 4, VLOOKUP(TRIM(AL37), wgtssSupplier, 2, FALSE), IF(AI37 = 5, VLOOKUP(TRIM(AL37), wgtmSupplier, 2, FALSE), IF(AI37 = 7, VLOOKUP(TRIM(AL37), asmSupplier, 2, FALSE), "")))))))) | AH37: =IF(C37 <> "", VLOOKUP(C37, oneOffs, 2, FALSE), "") | AI37: =IF(D37 <> "", VLOOKUP(D37, seriesCodeClasses, 2, FALSE), 0) -> 0 | AJ37: =IF(AL37 <> "", VLOOKUP(AL37, classIndexes, 2, FALSE), 0) -> 0 | AK37: =IF(AI37 = 0, "", IF(AI37 = 1, VLOOKUP(K37, gemClasses, 2, FALSE), IF(AI37 = 2, VLOOKUP(K37, nasccClasses, 2, FALSE), IF(AI37 = 2.1, VLOOKUP(K37, nasccClasses, 2, FALSE), IF(AI37 = 2.2, VLOOKUP(K37, nasccClasses, 2, FALSE), IF(AI37 = 3, VLOOKUP(K37, euemClasses, 2, FALSE), IF(AI37 = 4, VLOOKUP(K37, wgtssClasses, 2, FALSE), IF(AI37 = 5, VLOOKUP(K37, wgtmClasses, 2, FALSE), IF(AI37 = 6, VLOOKUP(K37, wpcClasses, 2, FALSE), IF(AI37 = 7, VLOOKUP(K37, asmClasses, 2, FALSE), "")))))))))) | AL37: =IF(AI37 = 1, AN37, IF(AI37 = 5, AO37, AK37)) | AN37: =IF(AND(IF(AK37 = "LMGTE PRO", TRUE, FALSE), IF(O37 = "Bronze", TRUE, FALSE)), "LMGTE AM", AK37) | AO37: =IF(AND(IF(AK37 = "GT3-P", TRUE, FALSE), IF(O37 = "Bronze", TRUE, FALSE)), "GT3-A", AK37) | AQ37: ='Lineup Legality - OOE'!L129 | AS37: =IF(J37 <> "", CONCATENATE("$", ROUND(SUM('Total Costs'!AZ36:BI36), 3), " Million"), "")
